Workbook

Sheet Summary
A1: Dish Cost — Summary
A2: Cost % = (ingredient cost per container + packaging) ÷ selling price. Prices exclude VAT; delivery app commission not included.
A4: Dish | B4: Section | C4: Single | H4: Small | M4: Medium | R4: Large
C5: Cost | D5: Store price | E5: Store % | F5: Delivery price | G5: Delivery % | H5: Cost | I5: Store price | J5: Store % | K5: Delivery price | L5: Delivery % | M5: Cost | N5: Store price | O5: Store % | P5: Delivery price | Q5: Delivery % | R5: Cost | S5: Store price | T5: Store % | U5: Delivery price | V5: Delivery %
A6: Fool & Cheese | B6: Eggs & fool | H6: ='Fool & Cheese'!C34 -> 0.45620846 | I6: ='Fool & Cheese'!C35 -> 1.5 | J6: ='Fool & Cheese'!C36 -> 0.30413897 | K6: =IF('Fool & Cheese'!C37="","",'Fool & Cheese'!C37) -> 1.9 | L6: ='Fool & Cheese'!C38 -> 0.24010972 | M6: ='Fool & Cheese'!D34 -> 0.89191692 | N6: ='Fool & Cheese'!D35 -> 2.8 | O6: ='Fool & Cheese'!D36 -> 0.31854176 | P6: =IF('Fool & Cheese'!D37="","",'Fool & Cheese'!D37) -> 3.4 | Q6: ='Fool & Cheese'!D38 -> 0.26232851 | R6: ='Fool & Cheese'!E34 -> 1.8111005 | S6: ='Fool & Cheese'!E35 -> 5.4 | T6: ='Fool & Cheese'!E36 -> 0.33538898 | U6: =IF('Fool & Cheese'!E37="","",'Fool & Cheese'!E37) -> 6.4 | V6: ='Fool & Cheese'!E38 -> 0.28298446
A7: Fasolya | B7: Eggs & fool | H7: =Fasolya!C34 -> 0.40906598 | I7: =Fasolya!C35 -> 1.3 | J7: =Fasolya!C36 -> 0.31466614 | K7: =IF(Fasolya!C37="","",Fasolya!C37) -> 1.7 | L7: =Fasolya!C38 -> 0.24062705 | M7: =Fasolya!D34 -> 0.79763196 | N7: =Fasolya!D35 -> 2.4 | O7: =Fasolya!D36 -> 0.33234665 | P7: =IF(Fasolya!D37="","",Fasolya!D37) -> 3 | Q7: =Fasolya!D38 -> 0.26587732 | R7: =Fasolya!E34 -> 1.6225306 | S7: =Fasolya!E35 -> 4.6 | T7: =Fasolya!E36 -> 0.35272404 | U7: =IF(Fasolya!E37="","",Fasolya!E37) -> 5.6 | V7: =Fasolya!E38 -> 0.2897376
A8: S.Egg Bin Aqool | B8: Eggs & fool | H8: ='S.Egg Bin Aqool'!C37 -> 0.43909871 | I8: ='S.Egg Bin Aqool'!C38 -> 1.6 | J8: ='S.Egg Bin Aqool'!C39 -> 0.27443669 | K8: =IF('S.Egg Bin Aqool'!C40="","",'S.Egg Bin Aqool'!C40) -> 2 | L8: ='S.Egg Bin Aqool'!C41 -> 0.21954935 | M8: ='S.Egg Bin Aqool'!D37 -> 0.85769741 | N8: ='S.Egg Bin Aqool'!D38 -> 3 | O8: ='S.Egg Bin Aqool'!D39 -> 0.28589914 | P8: =IF('S.Egg Bin Aqool'!D40="","",'S.Egg Bin Aqool'!D40) -> 3.6 | Q8: ='S.Egg Bin Aqool'!D41 -> 0.23824928 | R8: ='S.Egg Bin Aqool'!E37 -> 1.7426615 | S8: ='S.Egg Bin Aqool'!E38 -> 5.6 | T8: ='S.Egg Bin Aqool'!E39 -> 0.31118955 | U8: =IF('S.Egg Bin Aqool'!E40="","",'S.Egg Bin Aqool'!E40) -> 6.8 | V8: ='S.Egg Bin Aqool'!E41 -> 0.25627375
A9: Egg Shakshoka | B9: Eggs & fool | H9: ='Egg Shakshoka'!C31 -> 0.2567158 | I9: ='Egg Shakshoka'!C32 -> 1.2 | J9: ='Egg Shakshoka'!C33 -> 0.21392983 | K9: =IF('Egg Shakshoka'!C34="","",'Egg Shakshoka'!C34) -> 1.6 | L9: ='Egg Shakshoka'!C35 -> 0.16044737 | M9: ='Egg Shakshoka'!D31 -> 0.49293159 | N9: ='Egg Shakshoka'!D32 -> 2.2 | O9: ='Egg Shakshoka'!D33 -> 0.22405981 | P9: =IF('Egg Shakshoka'!D34="","",'Egg Shakshoka'!D34) -> 2.8 | Q9: ='Egg Shakshoka'!D35 -> 0.176047 | R9: ='Egg Shakshoka'!E31 -> 1.0131298 | S9: ='Egg Shakshoka'!E32 -> 4.2 | T9: ='Egg Shakshoka'!E33 -> 0.24122139 | U9: =IF('Egg Shakshoka'!E34="","",'Egg Shakshoka'!E34) -> 5 | V9: ='Egg Shakshoka'!E35 -> 0.20262597
A10: Egg Vegatable | B10: Eggs & fool | H10: ='Egg Vegatable'!C34 -> 0.27302865 | I10: ='Egg Vegatable'!C35 -> 1.2 | J10: ='Egg Vegatable'!C36 -> 0.22752387 | K10: =IF('Egg Vegatable'!C37="","",'Egg Vegatable'!C37) -> 1.6 | L10: ='Egg Vegatable'!C38 -> 0.1706429 | M10: ='Egg Vegatable'!D34 -> 0.52555729 | N10: ='Egg Vegatable'!D35 -> 2.2 | O10: ='Egg Vegatable'!D36 -> 0.23888968 | P10: =IF('Egg Vegatable'!D37="","",'Egg Vegatable'!D37) -> 2.8 | Q10: ='Egg Vegatable'!D38 -> 0.18769903 | R10: ='Egg Vegatable'!E34 -> 1.0783812 | S10: ='Egg Vegatable'!E35 -> 4.2 | T10: ='Egg Vegatable'!E36 -> 0.25675744 | U10: =IF('Egg Vegatable'!E37="","",'Egg Vegatable'!E37) -> 5 | V10: ='Egg Vegatable'!E38 -> 0.21567625
A11: Egg Makhalama | B11: Eggs & fool | H11: ='Egg Makhalama'!C34 -> 0.27681915 | I11: ='Egg Makhalama'!C35 -> 1.4 | J11: ='Egg Makhalama'!C36 -> 0.19772796 | K11: =IF('Egg Makhalama'!C37="","",'Egg Makhalama'!C37) -> 1.85 | L11: ='Egg Makhalama'!C38 -> 0.14963197 | M11: ='Egg Makhalama'!D34 -> 0.54337829 | N11: ='Egg Makhalama'!D35 -> 2.6 | O11: ='Egg Makhalama'!D36 -> 0.20899165 | P11: =IF('Egg Makhalama'!D37="","",'Egg Makhalama'!D37) -> 3.2 | Q11: ='Egg Makhalama'!D38 -> 0.16980572 | R11: ='Egg Makhalama'!E34 -> 1.1012232 | S11: ='Egg Makhalama'!E35 -> 5 | T11: ='Egg Makhalama'!E36 -> 0.22024465 | U11: =IF('Egg Makhalama'!E37="","",'Egg Makhalama'!E37) -> 6 | V11: ='Egg Makhalama'!E38 -> 0.18353721
A12: Egg Cheese | B12: Eggs & fool | H12: ='Egg Cheese'!C23 -> 0.33889824 | I12: ='Egg Cheese'!C24 -> 1.3 | J12: ='Egg Cheese'!C25 -> 0.26069095 | K12: =IF('Egg Cheese'!C26="","",'Egg Cheese'!C26) -> 1.7 | L12: ='Egg Cheese'!C27 -> 0.1993519 | M12: ='Egg Cheese'!D23 -> 0.65729647 | N12: ='Egg Cheese'!D24 -> 2.4 | O12: ='Egg Cheese'!D25 -> 0.27387353 | P12: =IF('Egg Cheese'!D26="","",'Egg Cheese'!D26) -> 3 | Q12: ='Egg Cheese'!D27 -> 0.21909882 | R12: ='Egg Cheese'!E23 -> 1.3418596 | S12: ='Egg Cheese'!E24 -> 4.6 | T12: ='Egg Cheese'!E25 -> 0.29170861 | U12: =IF('Egg Cheese'!E26="","",'Egg Cheese'!E26) -> 5.6 | V12: ='Egg Cheese'!E27 -> 0.23961779
A13: Egg Fried | B13: Eggs & fool | H13: ='Egg Fried'!C22 -> 0.21722 | I13: ='Egg Fried'!C23 -> 0.9 | J13: ='Egg Fried'!C24 -> 0.24135556 | K13: =IF('Egg Fried'!C25="","",'Egg Fried'!C25) -> 1.2 | L13: ='Egg Fried'!C26 -> 0.18101667 | M13: ='Egg Fried'!D22 -> 0.41394 | N13: ='Egg Fried'!D23 -> 1.7 | O13: ='Egg Fried'!D24 -> 0.24349412 | P13: =IF('Egg Fried'!D25="","",'Egg Fried'!D25) -> 2.2 | Q13: ='Egg Fried'!D26 -> 0.18815455 | R13: ='Egg Fried'!E22 -> 0.85514667 | S13: ='Egg Fried'!E23 -> 3.3 | T13: ='Egg Fried'!E24 -> 0.25913535 | U13: =IF('Egg Fried'!E25="","",'Egg Fried'!E25) -> 3.8 | V13: ='Egg Fried'!E26 -> 0.2250386
A14: Egg Eyoon | B14: Eggs & fool | H14: ='Egg Eyoon'!C22 -> 0.21722 | I14: ='Egg Eyoon'!C23 -> 0.9 | J14: ='Egg Eyoon'!C24 -> 0.24135556 | K14: =IF('Egg Eyoon'!C25="","",'Egg Eyoon'!C25) -> 1.2 | L14: ='Egg Eyoon'!C26 -> 0.18101667 | M14: ='Egg Eyoon'!D22 -> 0.41394 | N14: ='Egg Eyoon'!D23 -> 1.7 | O14: ='Egg Eyoon'!D24 -> 0.24349412 | P14: =IF('Egg Eyoon'!D25="","",'Egg Eyoon'!D25) -> 2.2 | Q14: ='Egg Eyoon'!D26 -> 0.18815455 | R14: ='Egg Eyoon'!E22 -> 0.85514667 | S14: ='Egg Eyoon'!E23 -> 3.3 | T14: ='Egg Eyoon'!E24 -> 0.25913535 | U14: =IF('Egg Eyoon'!E25="","",'Egg Eyoon'!E25) -> 3.8 | V14: ='Egg Eyoon'!E26 -> 0.2250386
A15: Egg & Fasolya | B15: Eggs & fool | H15: ='Egg & Fasolya'!C35 -> 0.47906598 | I15: ='Egg & Fasolya'!C36 -> 1.6 | J15: ='Egg & Fasolya'!C37 -> 0.29941624 | K15: =IF('Egg & Fasolya'!C38="","",'Egg & Fasolya'!C38) -> 2 | L15: ='Egg & Fasolya'!C39 -> 0.23953299 | M15: ='Egg & Fasolya'!D35 -> 0.93763196 | N15: ='Egg & Fasolya'!D36 -> 3 | O15: ='Egg & Fasolya'!D37 -> 0.31254399 | P15: =IF('Egg & Fasolya'!D38="","",'Egg & Fasolya'!D38) -> 3.6 | Q15: ='Egg & Fasolya'!D39 -> 0.26045332 | R15: ='Egg & Fasolya'!E35 -> 1.9025306 | S15: ='Egg & Fasolya'!E36 -> 5.6 | T15: ='Egg & Fasolya'!E37 -> 0.3397376 | U15: =IF('Egg & Fasolya'!E38="","",'Egg & Fasolya'!E38) -> 6.8 | V15: ='Egg & Fasolya'!E39 -> 0.27978391
A16: Egg & Tomato | B16: Eggs & fool | H16: ='Egg & Tomato'!C29 -> 0.2900575 | I16: ='Egg & Tomato'!C30 -> 1.2 | J16: ='Egg & Tomato'!C31 -> 0.24171458 | K16: =IF('Egg & Tomato'!C32="","",'Egg & Tomato'!C32) -> 1.6 | L16: ='Egg & Tomato'!C33 -> 0.18128594 | M16: ='Egg & Tomato'!D29 -> 0.559615 | N16: ='Egg & Tomato'!D30 -> 2.2 | O16: ='Egg & Tomato'!D31 -> 0.25437045 | P16: =IF('Egg & Tomato'!D32="","",'Egg & Tomato'!D32) -> 2.8 | Q16: ='Egg & Tomato'!D33 -> 0.1998625 | R16: ='Egg & Tomato'!E29 -> 1.1464967 | S16: ='Egg & Tomato'!E30 -> 4.2 | T16: ='Egg & Tomato'!E31 -> 0.2729754 | U16: =IF('Egg & Tomato'!E32="","",'Egg & Tomato'!E32) -> 5 | V16: ='Egg & Tomato'!E33 -> 0.22929933
A17: Fool | B17: Eggs & fool | H17: =Fool!C34 -> 0.42244376 | I17: =Fool!C35 -> 1.4 | J17: =Fool!C36 -> 0.30174554 | K17: =IF(Fool!C37="","",Fool!C37) -> 1.7 | L17: =Fool!C38 -> 0.24849633 | M17: =Fool!D34 -> 0.82438751 | N17: =Fool!D35 -> 2.6 | O17: =Fool!D36 -> 0.31707212 | P17: =IF(Fool!D37="","",Fool!D37) -> 3 | Q17: =Fool!D38 -> 0.27479584 | R17: =Fool!E34 -> 1.6760417 | S17: =Fool!E35 -> 5 | T17: =Fool!E36 -> 0.33520834 | U17: =IF(Fool!E37="","",Fool!E37) -> 5.6 | V17: =Fool!E38 -> 0.29929316
A18: Rice & Chicken | B18: Traditional | H18: ='Rice & Chicken'!C37 -> 0.49338804 | I18: ='Rice & Chicken'!C38 -> 1.2 | J18: ='Rice & Chicken'!C39 -> 0.4111567 | K18: =IF('Rice & Chicken'!C40="","",'Rice & Chicken'!C40) -> 1.2 | L18: ='Rice & Chicken'!C41 -> 0.4111567 | M18: ='Rice & Chicken'!D37 -> 0.88418007 | N18: ='Rice & Chicken'!D38 -> 2.3 | O18: ='Rice & Chicken'!D39 -> 0.38442612 | P18: =IF('Rice & Chicken'!D40="","",'Rice & Chicken'!D40) -> 2.3 | Q18: ='Rice & Chicken'!D41 -> 0.38442612 | R18: ='Rice & Chicken'!E37 -> 1.7444601 | S18: ='Rice & Chicken'!E38 -> 4.4 | T18: ='Rice & Chicken'!E39 -> 0.39646821 | U18: =IF('Rice & Chicken'!E40="","",'Rice & Chicken'!E40) -> 4.4 | V18: ='Rice & Chicken'!E41 -> 0.39646821
A19: Black Eye Beans | B19: Traditional | C19: ='Black Eye Beans'!C23 -> 0.087489063 | D19: ='Black Eye Beans'!C24 -> 0.4 | E19: ='Black Eye Beans'!C25 -> 0.21872266 | F19: =IF('Black Eye Beans'!C26="","",'Black Eye Beans'!C26) -> 0.4 | G19: ='Black Eye Beans'!C27 -> 0.21872266 | H19: ='Black Eye Beans'!D23 -> 0.10885208 | I19: ='Black Eye Beans'!D24 -> 0.6 | J19: ='Black Eye Beans'!D25 -> 0.18142014 | K19: =IF('Black Eye Beans'!D26="","",'Black Eye Beans'!D26) -> 0.75 | L19: ='Black Eye Beans'!D27 -> 0.14513611 | M19: ='Black Eye Beans'!E23 -> 0.19720417 | N19: ='Black Eye Beans'!E24 -> 1 | O19: ='Black Eye Beans'!E25 -> 0.19720417 | P19: =IF('Black Eye Beans'!E26="","",'Black Eye Beans'!E26) -> 1.3 | Q19: ='Black Eye Beans'!E27 -> 0.15169551 | R19: ='Black Eye Beans'!F23 -> 0.421675 | S19: ='Black Eye Beans'!F24 -> 1.8 | T19: ='Black Eye Beans'!F25 -> 0.23426389 | U19: =IF('Black Eye Beans'!F26="","",'Black Eye Beans'!F26) -> 2.2 | V19: ='Black Eye Beans'!F27 -> 0.19167045
A20: Nakhi | B20: Traditional | C20: =Nakhi!C24 -> 0.083955682 | D20: =Nakhi!C25 -> 0.4 | E20: =Nakhi!C26 -> 0.2098892 | F20: =IF(Nakhi!C27="","",Nakhi!C27) -> 0.4 | G20: =Nakhi!C28 -> 0.2098892 | H20: =Nakhi!D24 -> 0.10929917 | I20: =Nakhi!D25 -> 0.6 | J20: =Nakhi!D26 -> 0.18216529 | K20: =IF(Nakhi!D27="","",Nakhi!D27) -> 0.75 | L20: =Nakhi!D28 -> 0.14573223 | M20: =Nakhi!E24 -> 0.21047818 | N20: =Nakhi!E25 -> 1 | O20: =Nakhi!E26 -> 0.21047818 | P20: =IF(Nakhi!E27="","",Nakhi!E27) -> 1.2 | Q20: =Nakhi!E28 -> 0.17539848 | R20: =Nakhi!F24 -> 0.4028303 | S20: =Nakhi!F25 -> 1.8 | T20: =Nakhi!F26 -> 0.22379461 | U20: =IF(Nakhi!F27="","",Nakhi!F27) -> 2.2 | V20: =Nakhi!F28 -> 0.18310468
A21: Dall | B21: Traditional | C21: =Dall!C37 -> 0.1212619 | D21: =Dall!C38 -> 0.6 | E21: =Dall!C39 -> 0.20210316 | F21: =IF(Dall!C40="","",Dall!C40) -> 0.6 | G21: =Dall!C41 -> 0.20210316 | H21: =Dall!D37 -> 0.16403769 | I21: =Dall!D38 -> 1 | J21: =Dall!D39 -> 0.16403769 | K21: =IF(Dall!D40="","",Dall!D40) -> 1.35 | L21: =Dall!D41 -> 0.1215094 | M21: =Dall!E37 -> 0.25525653 | N21: =Dall!E38 -> 1.6 | O21: =Dall!E39 -> 0.15953533 | P21: =IF(Dall!E40="","",Dall!E40) -> 2.2 | Q21: =Dall!E41 -> 0.1160257 | R21: =Dall!F37 -> 0.53777973 | S21: =Dall!F38 -> 2.9 | T21: =Dall!F39 -> 0.18544129 | U21: =IF(Dall!F40="","",Dall!F40) -> 3.8 | V21: =Dall!F41 -> 0.14152098
A22: Bajela | B22: Traditional | C22: =Bajela!C24 -> 0.14612606 | D22: =Bajela!C25 -> 0.4 | E22: =Bajela!C26 -> 0.36531515 | F22: =IF(Bajela!C27="","",Bajela!C27) -> 0.4 | G22: =Bajela!C28 -> 0.36531515 | H22: =Bajela!D24 -> 0.22194343 | I22: =Bajela!D25 -> 0.6 | J22: =Bajela!D26 -> 0.36990572 | K22: =IF(Bajela!D27="","",Bajela!D27) -> 0.75 | L22: =Bajela!D28 -> 0.29592458 | M22: =Bajela!E24 -> 0.33611515 | N22: =Bajela!E25 -> 1 | O22: =Bajela!E26 -> 0.33611515 | P22: =IF(Bajela!E27="","",Bajela!E27) -> 1.2 | Q22: =Bajela!E28 -> 0.28009596 | R22: =Bajela!F24 -> 0.69949697 | S22: =Bajela!F25 -> 1.9 | T22: =Bajela!F26 -> 0.3681563 | U22: =IF(Bajela!F27="","",Bajela!F27) -> 2.2 | V22: =Bajela!F28 -> 0.31795317
A23: Harees | B23: Traditional | C23: =Harees!C25 -> 0.25394688 | D23: =Harees!C26 -> 0.6 | E23: =Harees!C27 -> 0.42324479 | F23: =IF(Harees!C28="","",Harees!C28) -> 0.6 | G23: =Harees!C29 -> 0.42324479 | H23: =Harees!D25 -> 0.32079583 | I23: =Harees!D26 -> 1 | J23: =Harees!D27 -> 0.32079583 | K23: =IF(Harees!D28="","",Harees!D28) -> 1.35 | L23: =Harees!D29 -> 0.23762654 | M23: =Harees!E25 -> 0.64109167 | N23: =Harees!E26 -> 1.6 | O23: =Harees!E27 -> 0.40068229 | P23: =IF(Harees!E28="","",Harees!E28) -> 2.4 | Q23: =Harees!E29 -> 0.26712153 | R23: =Harees!F25 -> 1.1375095 | S23: =Harees!F26 -> 2.9 | T23: =Harees!F27 -> 0.39224466 | U23: =IF(Harees!F28="","",Harees!F28) -> 4.4 | V23: =Harees!F29 -> 0.25852489
A24: Jareesh | B24: Traditional | H24: =Jareesh!C33 -> 0.18505557 | I24: =Jareesh!C34 -> 1 | J24: =Jareesh!C35 -> 0.18505557 | K24: =IF(Jareesh!C36="","",Jareesh!C36) -> 1 | L24: =Jareesh!C37 -> 0.18505557 | M24: =Jareesh!D33 -> 0.34300419 | N24: =Jareesh!D34 -> 1.6 | O24: =Jareesh!D35 -> 0.21437762 | P24: =IF(Jareesh!D36="","",Jareesh!D36) -> 1.6 | Q24: =Jareesh!D37 -> 0.21437762 | R24: =Jareesh!E33 -> 0.8689445 | S24: =Jareesh!E34 -> 2.9 | T24: =Jareesh!E35 -> 0.29963603 | U24: =IF(Jareesh!E36="","",Jareesh!E36) -> 2.9 | V24: =Jareesh!E37 -> 0.29963603
A25: Shilla | B25: Traditional | C25: =Shilla!C38 -> 0.11820006 | D25: =Shilla!C39 -> 0.6 | E25: =Shilla!C40 -> 0.19700009 | F25: =IF(Shilla!C41="","",Shilla!C41) -> 0.6 | G25: =Shilla!C42 -> 0.19700009 | H25: =Shilla!D38 -> 0.17307282 | I25: =Shilla!D39 -> 1 | J25: =Shilla!D40 -> 0.17307282 | K25: =IF(Shilla!D41="","",Shilla!D41) -> 1.35 | L25: =Shilla!D42 -> 0.12820209 | M25: =Shilla!E38 -> 0.27178586 | N25: =Shilla!E39 -> 1.6 | O25: =Shilla!E40 -> 0.16986616 | P25: =IF(Shilla!E41="","",Shilla!E41) -> 2.2 | Q25: =Shilla!E42 -> 0.12353903 | R25: =Shilla!F38 -> 0.52146692 | S25: =Shilla!F39 -> 2.9 | T25: =Shilla!F40 -> 0.17981618 | U25: =IF(Shilla!F41="","",Shilla!F41) -> 3.8 | V25: =Shilla!F42 -> 0.13722814
A26: Madrooba | B26: Traditional | C26: =Madrooba!C41 -> 0.16117204 | D26: =Madrooba!C42 -> 0.6 | E26: =Madrooba!C43 -> 0.26862006 | F26: =IF(Madrooba!C44="","",Madrooba!C44) -> 0.6 | G26: =Madrooba!C45 -> 0.26862006 | H26: =Madrooba!D41 -> 0.25850107 | I26: =Madrooba!D42 -> 1.1 | J26: =Madrooba!D43 -> 0.23500097 | K26: =IF(Madrooba!D44="","",Madrooba!D44) -> 1.35 | L26: =Madrooba!D45 -> 0.19148227 | M26: =Madrooba!E41 -> 0.49650213 | N26: =Madrooba!E42 -> 1.8 | O26: =Madrooba!E43 -> 0.27583452 | P26: =IF(Madrooba!E44="","",Madrooba!E44) -> 2.4 | Q26: =Madrooba!E45 -> 0.20687589 | R26: =Madrooba!F41 -> 1.0202709 | S26: =Madrooba!F42 -> 3.2 | T26: =Madrooba!F43 -> 0.31883467 | U26: =IF(Madrooba!F44="","",Madrooba!F44) -> 4.4 | V26: =Madrooba!F45 -> 0.23187976
A27: Beef Liver | B27: Main dishes | H27: ='Beef Liver'!C34 -> 0.51369327 | I27: ='Beef Liver'!C35 -> 1.8 | J27: ='Beef Liver'!C36 -> 0.28538515 | K27: =IF('Beef Liver'!C37="","",'Beef Liver'!C37) -> 2.2 | L27: ='Beef Liver'!C38 -> 0.23349694 | M27: ='Beef Liver'!D34 -> 1.0148785 | N27: ='Beef Liver'!D35 -> 3.4 | O27: ='Beef Liver'!D36 -> 0.29849369 | P27: =IF('Beef Liver'!D37="","",'Beef Liver'!D37) -> 4 | Q27: ='Beef Liver'!D38 -> 0.25371964 | R27: ='Beef Liver'!E34 -> 1.7514976 | S27: ='Beef Liver'!E35 -> 6.2 | T27: ='Beef Liver'!E36 -> 0.28249961 | U27: =IF('Beef Liver'!E37="","",'Beef Liver'!E37) -> 7.5 | V27: ='Beef Liver'!E38 -> 0.23353301
A28: Chicken Liver | B28: Main dishes | H28: ='Chicken Liver'!C40 -> 0.6053255 | I28: ='Chicken Liver'!C41 -> 2 | J28: ='Chicken Liver'!C42 -> 0.30266275 | K28: =IF('Chicken Liver'!C43="","",'Chicken Liver'!C43) -> 2.2 | L28: ='Chicken Liver'!C44 -> 0.27514795 | M28: ='Chicken Liver'!D40 -> 1.198143 | N28: ='Chicken Liver'!D41 -> 3.6 | O28: ='Chicken Liver'!D42 -> 0.3328175 | P28: =IF('Chicken Liver'!D43="","",'Chicken Liver'!D43) -> 4 | Q28: ='Chicken Liver'!D44 -> 0.29953575 | R28: ='Chicken Liver'!E40 -> 2.3895527 | S28: ='Chicken Liver'!E41 -> 6.8 | T28: ='Chicken Liver'!E42 -> 0.3514048 | U28: =IF('Chicken Liver'!E43="","",'Chicken Liver'!E43) -> 7.5 | V28: ='Chicken Liver'!E44 -> 0.31860702
A29: Qeema Meat | B29: Main dishes | H29: ='Qeema Meat'!C35 -> 0.51531775 | I29: ='Qeema Meat'!C36 -> 2.5 | J29: ='Qeema Meat'!C37 -> 0.2061271 | K29: =IF('Qeema Meat'!C38="","",'Qeema Meat'!C38) -> 2.5 | L29: ='Qeema Meat'!C39 -> 0.2061271 | M29: ='Qeema Meat'!D35 -> 1.0181275 | N29: ='Qeema Meat'!D36 -> 3.2 | O29: ='Qeema Meat'!D37 -> 0.31816484 | P29: =IF('Qeema Meat'!D38="","",'Qeema Meat'!D38) -> 3.5 | Q29: ='Qeema Meat'!D39 -> 0.29089357 | R29: ='Qeema Meat'!E35 -> 2.0635217 | S29: ='Qeema Meat'!E36 -> 5.4 | T29: ='Qeema Meat'!E37 -> 0.38213364 | U29: =IF('Qeema Meat'!E38="","",'Qeema Meat'!E38) -> 6 | V29: ='Qeema Meat'!E39 -> 0.34392028
A30: Nashif Chicken | B30: Main dishes | H30: ='Nashif Chicken'!C48 -> 0.42435552 | I30: ='Nashif Chicken'!C49 -> 1.8 | J30: ='Nashif Chicken'!C50 -> 0.23575307 | K30: =IF('Nashif Chicken'!C51="","",'Nashif Chicken'!C51) -> 2.2 | L30: ='Nashif Chicken'!C52 -> 0.19288887 | M30: ='Nashif Chicken'!D48 -> 0.82821105 | N30: ='Nashif Chicken'!D49 -> 3.4 | O30: ='Nashif Chicken'!D50 -> 0.24359148 | P30: =IF('Nashif Chicken'!D51="","",'Nashif Chicken'!D51) -> 4 | Q30: ='Nashif Chicken'!D52 -> 0.20705276 | R30: ='Nashif Chicken'!E48 -> 2.1702961 | S30: ='Nashif Chicken'!E49 -> 6.6 | T30: ='Nashif Chicken'!E50 -> 0.32883275 | U30: =IF('Nashif Chicken'!E51="","",'Nashif Chicken'!E51) -> 7.6 | V30: ='Nashif Chicken'!E52 -> 0.28556528
A31: Nashif Meat | B31: Main dishes | H31: ='Nashif Meat'!C42 -> 0.56822167 | I31: ='Nashif Meat'!C43 -> 2 | J31: ='Nashif Meat'!C44 -> 0.28411083 | K31: =IF('Nashif Meat'!C45="","",'Nashif Meat'!C45) -> 1.5 | L31: ='Nashif Meat'!C46 -> 0.37881444 | M31: ='Nashif Meat'!D42 -> 1.1167353 | N31: ='Nashif Meat'!D43 -> 3.8 | O31: ='Nashif Meat'!D44 -> 0.29387772 | P31: =IF('Nashif Meat'!D45="","",'Nashif Meat'!D45) -> 2.8 | Q31: ='Nashif Meat'!D46 -> 0.39883405 | R31: ='Nashif Meat'!E42 -> 2.2684173 | S31: ='Nashif Meat'!E43 -> 7 | T31: ='Nashif Meat'!E44 -> 0.32405962 | U31: =IF('Nashif Meat'!E45="","",'Nashif Meat'!E45) -> 5.4 | V31: ='Nashif Meat'!E46 -> 0.42007728
A32: Aseeda | B32: Sweets | C32: =Aseeda!C25 -> 0.0802147 | D32: =Aseeda!C26 -> 0.4 | E32: =Aseeda!C27 -> 0.20053675 | F32: =IF(Aseeda!C28="","",Aseeda!C28) -> 0.4 | G32: =Aseeda!C29 -> 0.20053675 | H32: =Aseeda!D25 -> 0.11849117 | I32: =Aseeda!D26 -> 0.7 | J32: =Aseeda!D27 -> 0.1692731 | K32: =IF(Aseeda!D28="","",Aseeda!D28) -> 1 | L32: =Aseeda!D29 -> 0.11849117 | M32: =Aseeda!E25 -> 0.17773675 | N32: =Aseeda!E26 -> 1 | O32: =Aseeda!E27 -> 0.17773675 | P32: =IF(Aseeda!E28="","",Aseeda!E28) -> 1.5 | Q32: =Aseeda!E29 -> 0.11849117 | R32: =Aseeda!F25 -> 0.37634017 | S32: =Aseeda!F26 -> 1.9 | T32: =Aseeda!F27 -> 0.19807377 | U32: =IF(Aseeda!F28="","",Aseeda!F28) -> 2.5 | V32: =Aseeda!F29 -> 0.15053607
A33: Qeemat | B33: Sweets | M33: =Qeemat!C25 -> 0.47186349 | N33: =Qeemat!C26 -> 1.4 | O33: =Qeemat!C27 -> 0.33704535 | P33: =IF(Qeemat!C28="","",Qeemat!C28) -> 1.8 | Q33: =Qeemat!C29 -> 0.26214638
A34: Balaleet | B34: Sweets | H34: =Balaleet!C25 -> 0.28695556 | I34: =Balaleet!C26 -> 1 | J34: =Balaleet!C27 -> 0.28695556 | K34: =IF(Balaleet!C28="","",Balaleet!C28) | L34: =Balaleet!C29 | M34: =Balaleet!D25 -> 0.43363333 | N34: =Balaleet!D26 -> 1.6 | O34: =Balaleet!D27 -> 0.27102083 | P34: =IF(Balaleet!D28="","",Balaleet!D28) -> 2 | Q34: =Balaleet!D29 -> 0.21681667 | R34: =Balaleet!E25 -> 0.89453333 | S34: =Balaleet!E26 -> 3 | T34: =Balaleet!E27 -> 0.29817778 | U34: =IF(Balaleet!E28="","",Balaleet!E28) | V34: =Balaleet!E29
A35: Fateeta | B35: Sweets | C35: =Fateeta!C24 -> 0.167105 | D35: =Fateeta!C25 -> 0.6 | E35: =Fateeta!C26 -> 0.27850833 | F35: =IF(Fateeta!C27="","",Fateeta!C27) -> 0.4 | G35: =Fateeta!C28 -> 0.4177625 | H35: =Fateeta!D24 -> 0.23337857 | I35: =Fateeta!D25 -> 0.9 | J35: =Fateeta!D26 -> 0.25930952 | K35: =IF(Fateeta!D27="","",Fateeta!D27) -> 1 | L35: =Fateeta!D28 -> 0.23337857 | M35: =Fateeta!E24 -> 0.3949625 | N35: =Fateeta!E25 -> 1.6 | O35: =Fateeta!E26 -> 0.24685156 | P35: =IF(Fateeta!E27="","",Fateeta!E27) -> 1.5 | Q35: =Fateeta!E28 -> 0.26330833 | R35: =Fateeta!F24 -> 0.81079167 | S35: =Fateeta!F25 -> 3 | T35: =Fateeta!F26 -> 0.27026389 | U35: =IF(Fateeta!F27="","",Fateeta!F27) -> 2.5 | V35: =Fateeta!F28 -> 0.32431667

Sheet LIST
A1: Sn | B1: Item | C1: Category | D1: Price (BHD) | E1: Pack qty | F1: Unit | G1: Unit price | H1: Previous price | I1: Market price
A2: 1 | B2: Bagal Leaves | C2: Vegetables | D2: 0.04 | E2: 50 | F2: g | G2: =IFERROR(D2/E2,0) -> 0.0008 | H2: 0.025 | I2: 0.025
A3: 2 | B3: Coriander Leaves | C3: Vegetables | D3: 0.095 | E3: 55 | F3: g | G3: =IFERROR(D3/E3,0) -> 0.0017272727 | H3: 0.08 | I3: 0.07
A4: 3 | B4: Curry Leaves | C4: Vegetables | D4: 1.95 | E4: 1000 | F4: g | G4: =IFERROR(D4/E4,0) -> 0.00195 | H4: 1.959 | I4: 1.087
A5: 4 | B5: Cabbage White | C5: Vegetables | D5: 0.4 | E5: 1000 | F5: g | G5: =IFERROR(D5/E5,0) -> 0.0004 | H5: 0.274 | I5: 0.23
A6: 5 | B6: Cauliflower | C6: Vegetables | D6: 0.65 | E6: 1000 | F6: g | G6: =IFERROR(D6/E6,0) -> 0.00065 | H6: 0.9 | I6: 0.375
A7: 6 | B7: Carrot | C7: Vegetables | D7: 0.85 | E7: 1000 | F7: g | G7: =IFERROR(D7/E7,0) -> 0.00085 | H7: 0.45 | I7: 0.45
A8: 7 | B8: Cucuamber | C8: Vegetables | D8: 0.45 | E8: 1000 | F8: g | G8: =IFERROR(D8/E8,0) -> 0.00045 | H8: 0.55 | I8: 0.35
A9: 8 | B9: Dill Leaves | C9: Vegetables | D9: 0.09 | E9: 60 | F9: g | G9: =IFERROR(D9/E9,0) -> 0.0015 | H9: 0.097 | I9: 0.08
A10: 9 | B10: Eggplant | C10: Vegetables | D10: 0.55 | E10: 1000 | F10: g | G10: =IFERROR(D10/E10,0) -> 0.00055 | H10: 0.58 | I10: 0.36
A11: 10 | B11: Garlic Peeled | C11: Vegetables | D11: 1.5 | E11: 1000 | F11: g | G11: =IFERROR(D11/E11,0) -> 0.0015 | H11: 1.4 | I11: 1.2
A12: 11 | B12: Green Capiscum | C12: Vegetables | D12: 0.65 | E12: 1000 | F12: g | G12: =IFERROR(D12/E12,0) -> 0.00065 | H12: 0.85 | I12: 0.571
A13: 12 | B13: Ginger + Garlic Mix | C13: Vegetables | D13: 1.2 | E13: 1000 | F13: g | G13: =IFERROR(D13/E13,0) -> 0.0012 | H13: 0.5 | I13: 0.5
... A29: 28 | B29: Chana Dal | C29: Beans & grains | D29: 0.581 | E29: 1000 | F29: g | G29: =IFERROR(D29/E29,0) -> 0.000581 | H29: 0.7 | I29: 0.433
A30: 29 | B30: Green lentils | C30: Beans & grains | D30: 0.4 | E30: 1000 | F30: g | G30: =IFERROR(D30/E30,0) -> 0.0004 | H30: 0.78
A31: 30 | B31: Harees | C31: Beans & grains | D31: 0.45 | E31: 1000 | F31: g | G31: =IFERROR(D31/E31,0) -> 0.00045 | H31: 0.5
A32: 31 | B32: Jareesh | C32: Beans & grains | D32: 0 | E32: 1000 | F32: g | G32: =IFERROR(D32/E32,0) -> 0 | H32: 0
A33: 32 | B33: Masoor Daal | C33: Beans & grains | D33: 0.454 | E33: 1000 | F33: g | G33: =IFERROR(D33/E33,0) -> 0.000454 | H33: 0.55 | I33: 0.433
A34: 33 | B34: Moong Dal | C34: Beans & grains | D34: 0.668 | E34: 1000 | F34: g | G34: =IFERROR(D34/E34,0) -> 0.000668 | H34: 0.74 | I34: 0.566
A35: 34 | B35: Rice 1121 | C35: Beans & grains | D35: 0.575 | E35: 1000 | F35: g | G35: =IFERROR(D35/E35,0) -> 0.000575 | H35: 0.525 | I35: 0.425
A36: 35 | B36: Raison | C36: Beans & grains | D36: 1.75 | E36: 1000 | F36: g | G36: =IFERROR(D36/E36,0) -> 0.00175 | H36: 1.65 | I36: 1.3
A37: 36 | B37: Rice Broken | C37: Beans & grains | D37: 0.3 | E37: 1000 | F37: g | G37: =IFERROR(D37/E37,0) -> 0.0003 | H37: 0.25
A38: 37 | B38: Sugar | C38: Beans & grains | D38: 0.3 | E38: 1000 | F38: g | G38: =IFERROR(D38/E38,0) -> 0.0003 | H38: 0.4
A39: 38 | B39: White Kidney Beans | C39: Beans & grains | D39: 0.818 | E39: 1000 | F39: g | G39: =IFERROR(D39/E39,0) -> 0.000818 | H39: 0.9 | I39: 0.766
A40: 39 | B40: Black Pepper Seeds | C40: Spices | D40: 4.09 | E40: 1000 | F40: g | G40: =IFERROR(D40/E40,0) -> 0.00409 | H40: 4.18
A41: 40 | B41: Black Pepper Powder | C41: Spices | D41: 2.272 | E41: 1000 | F41: g | G41: =IFERROR(D41/E41,0) -> 0.002272 | H41: 4.62
A42: 41 | B42: Black Lemone Powdre | C42: Spices | D42: 4.62 | E42: 1000 | F42: g | G42: =IFERROR(D42/E42,0) -> 0.00462 | H42: 0
A43: 42 | B43: Black Lemone Whole | C43: Spices | D43: 1.76 | E43: 1000 | F43: g | G43: =IFERROR(D43/E43,0) -> 0.00176 | H43: 1.6
A44: 43 | B44: Coriander Powder | C44: Spices | D44: 1.8 | E44: 1000 | F44: g | G44: =IFERROR(D44/E44,0) -> 0.0018 | H44: 1.3
A45: 44 | B45: Curry Powder | C45: Spices | D45: 1.65 | E45: 1000 | F45: g | G45: =IFERROR(D45/E45,0) -> 0.00165 | H45: 1.5
A46: 45 | B46: Cloves Seeds | C46: Spices | D46: 5.3636 | E46: 1000 | F46: g | G46: =IFERROR(D46/E46,0) -> 0.0053636 | H46: 6.5
A47: 46 | B47: Cummin Powder | C47: Spices | D47: 2.818 | E47: 1000 | F47: g | G47: =IFERROR(D47/E47,0) -> 0.002818 | H47: 3.1
A48: 47 | B48: Cummin Seeds | C48: Spices | D48: 2.8 | E48: 1000 | F48: g | G48: =IFERROR(D48/E48,0) -> 0.0028 | H48: 5.6
A49: 48 | B49: Cinamon Stick | C49: Spices | D49: 2.3636 | E49: 1000 | F49: g | G49: =IFERROR(D49/E49,0) -> 0.0023636 | H49: 2.6
A50: 49 | B50: Cinamon Powder | C50: Spices | D50: 2.6454 | E50: 1000 | F50: g | G50: =IFERROR(D50/E50,0) -> 0.0026454 | H50: 2.91
A51: 50 | B51: Cardmon Seeds | C51: Spices | D51: 16 | E51: 1000 | F51: g | G51: =IFERROR(D51/E51,0) -> 0.016 | H51: 15
... A63: 62 | B63: Tandori Masala Powder | C63: Spices | D63: 4 | E63: 1000 | F63: g | G63: =IFERROR(D63/E63,0) -> 0.004 | H63: 4.8
A64: 63 | B64: Beef Liver | C64: Frozen & meat | D64: 1.409 | E64: 1000 | F64: g | G64: =IFERROR(D64/E64,0) -> 0.001409 | H64: 1.21 | I64: 0.95
A65: 64 | B65: Beef Slice | C65: Frozen & meat | D65: 2.636 | E65: 900 | F65: g | G65: =IFERROR(D65/E65,0) -> 0.0029288889 | H65: 2.365 | I65: 1.833
A66: 65 | B66: Meat Boby Vel | C66: Frozen & meat | D66: 2.2 | E66: 1000 | F66: g | G66: =IFERROR(D66/E66,0) -> 0.0022 | H66: 2.2
A67: 66 | B67: Crispy Chcike | C67: Frozen & meat | D67: 2.2 | E67: 1000 | F67: g | G67: =IFERROR(D67/E67,0) -> 0.0022 | H67: 2 | I67: 1.8
A68: 67 | B68: Chicken Breast | C68: Frozen & meat | D68: 1.5 | E68: 1000 | F68: g | G68: =IFERROR(D68/E68,0) -> 0.0015 | H68: 1.32 | I68: 1.15
A69: 68 | B69: Chicken Liver | C69: Frozen & meat | D69: 0.386 | E69: 450 | F69: g | G69: =IFERROR(D69/E69,0) -> 0.00085777778 | H69: 0.385 | I69: 0.32
A70: 69 | B70: Full Chicken | C70: Frozen & meat | D70: 1.363 | E70: 1000 | F70: g | G70: =IFERROR(D70/E70,0) -> 0.001363 | H70: 1.293 | I70: 1.15
A71: 70 | B71: Minced Beef | C71: Frozen & meat | D71: 0.239 | E71: 400 | F71: g | G71: =IFERROR(D71/E71,0) -> 0.0005975 | H71: 0.29
A72: 71 | B72: Qeema Meat | C72: Frozen & meat | D72: 2.2 | E72: 1000 | F72: g | G72: =IFERROR(D72/E72,0) -> 0.0022 | H72: 1.76 | I72: 1.5
A73: 72 | B73: Annar Sause | C73: Grocery | D73: 0.75 | E73: 1000 | F73: g | G73: =IFERROR(D73/E73,0) -> 0.00075 | H73: 0.73
A74: 73 | B74: Butter | C74: Grocery | D74: 0.8 | E74: 1000 | F74: g | G74: =IFERROR(D74/E74,0) -> 0.0008 | H74: 1.08
A75: 74 | B75: Balaleet | C75: Grocery | D75: 0.54 | E75: 500 | F75: g | G75: =IFERROR(D75/E75,0) -> 0.00108 | H75: 0.565
A76: 75 | B76: Baking Powder | C76: Grocery | D76: 1.545 | E76: 440 | F76: g | G76: =IFERROR(D76/E76,0) -> 0.0035113636 | H76: 1.7
A77: 76 | B77: Custard | C77: Grocery | D77: 1 | E77: 450 | F77: g | G77: =IFERROR(D77/E77,0) -> 0.0022222222 | H77: 1.1
A78: 77 | B78: Cucuamber Pickel | C78: Grocery | D78: 0.513 | E78: 1000 | F78: g | G78: =IFERROR(D78/E78,0) -> 0.000513 | H78: 0.446
A79: 78 | B79: Fool | C79: Grocery | D79: 0.458 | E79: 450 | F79: g | G79: =IFERROR(D79/E79,0) -> 0.0010177778 | H79: 0.504
A80: 79 | B80: Egg | C80: Grocery | D80: 0.035 | E80: 1 | F80: pc | G80: =IFERROR(D80/E80,0) -> 0.035 | H80: 0.047
A81: 80 | B81: Flour Brown | C81: Grocery | D81: 0.1 | E81: 1000 | F81: g | G81: =IFERROR(D81/E81,0) -> 0.0001 | H81: 0.1
A82: 81 | B82: Flour White | C82: Grocery | D82: 0.1 | E82: 1000 | F82: g | G82: =IFERROR(D82/E82,0) -> 0.0001 | H82: 0.1
A83: 82 | B83: Flour Kabab | C83: Grocery | D83: 0.3333 | E83: 1000 | F83: g | G83: =IFERROR(D83/E83,0) -> 0.0003333 | H83: 0.403
A84: 83 | B84: Flour Corn | C84: Grocery | D84: 0.386 | E84: 1000 | F84: g | G84: =IFERROR(D84/E84,0) -> 0.000386 | H84: 0.35
... A95: 94 | B95: Oil Corn | C95: Grocery | D95: 0.9 | E95: 1000 | F95: ml | G95: =IFERROR(D95/E95,0) -> 0.0009 | H95: 1
A96: 95 | B96: Vegetable Oil | C96: Grocery | D96: 0.594 | E96: 1000 | F96: ml | G96: =IFERROR(D96/E96,0) -> 0.000594 | H96: 0.666 | I96: 0.558
A97: 96 | B97: Olive Oil | C97: Grocery | D97: 1.54 | E97: 5000 | F97: ml | G97: =IFERROR(D97/E97,0) -> 0.000308 | H97: 1.85
A98: 97 | B98: Qeemat Powder | C98: Grocery | D98: 1.45 | E98: 1000 | F98: g | G98: =IFERROR(D98/E98,0) -> 0.00145 | H98: 1.45
A99: 98 | B99: Date Syrup | C99: Grocery | D99: 1.25 | E99: 300 | F99: g | G99: =IFERROR(D99/E99,0) -> 0.0041666667 | H99: 1.21
A100: 99 | B100: Rose Water + Safroon | C100: Grocery | D100: 0.3 | E100: 450 | F100: ml | G100: =IFERROR(D100/E100,0) -> 0.00066666667 | H100: 0
A101: 100 | B101: Rose Water | C101: Grocery | D101: 0.2 | E101: 450 | F101: ml | G101: =IFERROR(D101/E101,0) -> 0.00044444444 | H101: 0.15
A102: 101 | B102: Sago | C102: Grocery | D102: 0.6 | E102: 1000 | F102: g | G102: =IFERROR(D102/E102,0) -> 0.0006 | H102: 0.6
A103: 102 | B103: Safroon | C103: Grocery | D103: 1.166 | E103: 1 | F103: g | G103: =IFERROR(D103/E103,0) -> 1.166 | H103: 1.09
A104: 103 | B104: Sambosa Pepper | C104: Grocery | D104: 0.012 | E104: 1 | F104: pc | G104: =IFERROR(D104/E104,0) -> 0.012 | H104: 0.03
A105: 104 | B105: Saboosa | C105: Grocery | D105: 0.025 | E105: 1 | F105: pc | G105: =IFERROR(D105/E105,0) -> 0.025 | H105: 0.029
A106: 105 | B106: Sodium Bicarbonate | C106: Grocery | D106: 0.3 | E106: 1000 | F106: g | G106: =IFERROR(D106/E106,0) -> 0.0003 | H106: 0.3
A107: 106 | B107: Tahina | C107: Grocery | D107: 0.9696 | E107: 1000 | F107: g | G107: =IFERROR(D107/E107,0) -> 0.0009696 | H107: 1.466 | I107: 1.1
A108: 107 | B108: Tea | C108: Grocery | D108: 2 | E108: 1000 | F108: g | G108: =IFERROR(D108/E108,0) -> 0.002 | H108: 1.7
A109: 108 | B109: Tea Bag | C109: Grocery | D109: 0.011 | E109: 1 | F109: pc | G109: =IFERROR(D109/E109,0) -> 0.011 | H109: 1.1
A110: 109 | B110: Tomato Paste | C110: Grocery | D110: 0.6 | E110: 1000 | F110: g | G110: =IFERROR(D110/E110,0) -> 0.0006 | H110: 0.84
A111: 110 | B111: Yest Powdre | C111: Grocery | D111: 1.572 | E111: 500 | F111: g | G111: =IFERROR(D111/E111,0) -> 0.003144 | H111: 1.73
A112: 111 | B112: Vinger | C112: Grocery | D112: 0.5 | E112: 3000 | F112: g | G112: =IFERROR(D112/E112,0) -> 0.00016666667 | H112: 0.5
A113: 112 | B113: Cheddar Cheese | C113: Grocery | D113: 3.7 | E113: 1700 | F113: g | G113: =IFERROR(D113/E113,0) -> 0.0021764706 | H113: 3.2
A114: 113 | B114: Date Paste | C114: Grocery | D114: 0.73 | E114: 1000 | F114: g | G114: =IFERROR(D114/E114,0) -> 0.00073
A115: 114 | B115: MACARONI | C115: Grocery | D115: 0.6 | E115: 500 | F115: g | G115: =IFERROR(D115/E115,0) -> 0.0012 | H115: 0.605
A116: 115 | B116: Nahai | C116: Grocery | D116: 1.08 | E116: 1000 | F116: g | G116: =IFERROR(D116/E116,0) -> 0.00108
A117: 116 | B117: HASHOO | C117: Grocery | D117: 0 | E117: 1000 | F117: g | G117: =IFERROR(D117/E117,0) -> 0
A118: 117 | B118: MABOOJ + DAQOOS | C118: Grocery | D118: 0 | E118: 1000 | F118: g | G118: =IFERROR(D118/E118,0) -> 0
A119: 118 | B119: SPOON | C119: Packaging & extras | D119: 0.32 | E119: 50 | F119: pc | G119: =IFERROR(D119/E119,0) -> 0.0064 | H119: 0.29
A120: 119 | B120: CONTENER NO : (1) | C120: Packaging & extras | D120: 12.5 | E120: 500 | F120: pc | G120: =IFERROR(D120/E120,0) -> 0.025 | H120: 15
A121: 120 | B121: CONTENER NO : (3) | C121: Packaging & extras | D121: 6.3 | E121: 300 | F121: pc | G121: =IFERROR(D121/E121,0) -> 0.021 | H121: 13
A122: 121 | B122: CONTENER NO : (4) | C122: Packaging & extras | D122: 9.45 | E122: 300 | F122: pc | G122: =IFERROR(D122/E122,0) -> 0.0315 | H122: 17
A123: 122 | B123: CONTENER NO : (5) | C123: Packaging & extras | D123: 17.5 | E123: 150 | F123: pc | G123: =IFERROR(D123/E123,0) -> 0.11666667 | H123: 17
A124: 123 | B124: Alluminium Container S | C124: Packaging & extras | D124: 0.6 | E124: 250 | F124: g | G124: =IFERROR(D124/E124,0) -> 0.0024
A125: 124 | B125: Alluminium Container M | C125: Packaging & extras | D125: 0.6 | E125: 100 | F125: g | G125: =IFERROR(D125/E125,0) -> 0.006
A126: 125 | B126: Alluminium Container L | C126: Packaging & extras | D126: 0.6 | E126: 100 | F126: g | G126: =IFERROR(D126/E126,0) -> 0.006
A127: 126 | B127: Bread | C127: Packaging & extras | D127: 0.012 | E127: 1 | F127: pc | G127: =IFERROR(D127/E127,0) -> 0.012
A128: 127 | B128: Bag Small | C128: Packaging & extras | D128: 0.02 | E128: 1 | F128: pc | G128: =IFERROR(D128/E128,0) -> 0.02
A129: 128 | B129: Bag Medium | C129: Packaging & extras | D129: 0.03 | E129: 1 | F129: pc | G129: =IFERROR(D129/E129,0) -> 0.03
A130: 129 | B130: Bag Large | C130: Packaging & extras | D130: 0.04 | E130: 1 | F130: pc | G130: =IFERROR(D130/E130,0) -> 0.04
A131: 130 | B131: Bag XS | C131: Packaging & extras | D131: 0.01 | E131: 1 | F131: pc | G131: =IFERROR(D131/E131,0) -> 0.01
B133: Blue cells are inputs: change a price here and every dish sheet recalculates.

Sheet Fool & Cheese
A1: Fool & Cheese
A2: Eggs & fool · one container takes several recipes · target 25%
A4: # | B4: Item | C4: Qty | D4: Unit | E4: Unit price | F4: Cost
A5: 1 | B5: Fool | C5: 190 | D5: =IFERROR(INDEX(LIST!$F$2:$F$131,MATCH(B5,LIST!$B$2:$B$131,0)),"") -> g | E5: =IFERROR(INDEX(LIST!$G$2:$G$131,MATCH(B5,LIST!$B$2:$B$131,0)),0) -> 0.0010177778 | F5: =C5*E5 -> 0.19337778
A6: 2 | B6: Cheddar Cheese | C6: 20 | D6: =IFERROR(INDEX(LIST!$F$2:$F$131,MATCH(B6,LIST!$B$2:$B$131,0)),"") -> g | E6: =IFERROR(INDEX(LIST!$G$2:$G$131,MATCH(B6,LIST!$B$2:$B$131,0)),0) -> 0.0021764706 | F6: =C6*E6 -> 0.043529412
A7: 3 | B7: Tahina | C7: 15 | D7: =IFERROR(INDEX(LIST!$F$2:$F$131,MATCH(B7,LIST!$B$2:$B$131,0)),"") -> g | E7: =IFERROR(INDEX(LIST!$G$2:$G$131,MATCH(B7,LIST!$B$2:$B$131,0)),0) -> 0.0009696 | F7: =C7*E7 -> 0.014544
A8: 4 | B8: Vegetable Oil | C8: 30 | D8: =IFERROR(INDEX(LIST!$F$2:$F$131,MATCH(B8,LIST!$B$2:$B$131,0)),"") -> ml | E8: =IFERROR(INDEX(LIST!$G$2:$G$131,MATCH(B8,LIST!$B$2:$B$131,0)),0) -> 0.000594 | F8: =C8*E8 -> 0.01782
A9: 5 | B9: Onion | C9: 60 | D9: =IFERROR(INDEX(LIST!$F$2:$F$131,MATCH(B9,LIST!$B$2:$B$131,0)),"") -> g | E9: =IFERROR(INDEX(LIST!$G$2:$G$131,MATCH(B9,LIST!$B$2:$B$131,0)),0) -> 0.00045 | F9: =C9*E9 -> 0.027
A10: 6 | B10: Tomato Paste | C10: 120 | D10: =IFERROR(INDEX(LIST!$F$2:$F$131,MATCH(B10,LIST!$B$2:$B$131,0)),"") -> g | E10: =IFERROR(INDEX(LIST!$G$2:$G$131,MATCH(B10,LIST!$B$2:$B$131,0)),0) -> 0.0006 | F10: =C10*E10 -> 0.072
A11: 7 | B11: Coriander Leaves | C11: 1 | D11: =IFERROR(INDEX(LIST!$F$2:$F$131,MATCH(B11,LIST!$B$2:$B$131,0)),"") -> g | E11: =IFERROR(INDEX(LIST!$G$2:$G$131,MATCH(B11,LIST!$B$2:$B$131,0)),0) -> 0.0017272727 | F11: =C11*E11 -> 0.0017272727
A12: 8 | B12: Green Capiscum | C12: 10 | D12: =IFERROR(INDEX(LIST!$F$2:$F$131,MATCH(B12,LIST!$B$2:$B$131,0)),"") -> g | E12: =IFERROR(INDEX(LIST!$G$2:$G$131,MATCH(B12,LIST!$B$2:$B$131,0)),0) -> 0.00065 | F12: =C12*E12 -> 0.0065
A13: 9 | B13: Mix Masala Powder | C13: 1.25 | D13: =IFERROR(INDEX(LIST!$F$2:$F$131,MATCH(B13,LIST!$B$2:$B$131,0)),"") -> g | E13: =IFERROR(INDEX(LIST!$G$2:$G$131,MATCH(B13,LIST!$B$2:$B$131,0)),0) -> 0.00165 | F13: =C13*E13 -> 0.0020625
A14: 10 | B14: Turmeric Powder | C14: 1.25 | D14: =IFERROR(INDEX(LIST!$F$2:$F$131,MATCH(B14,LIST!$B$2:$B$131,0)),"") -> g | E14: =IFERROR(INDEX(LIST!$G$2:$G$131,MATCH(B14,LIST!$B$2:$B$131,0)),0) -> 0.0018 | F14: =C14*E14 -> 0.00225
A15: 11 | B15: Cummin Powder | C15: 1.25 | D15: =IFERROR(INDEX(LIST!$F$2:$F$131,MATCH(B15,LIST!$B$2:$B$131,0)),"") -> g | E15: =IFERROR(INDEX(LIST!$G$2:$G$131,MATCH(B15,LIST!$B$2:$B$131,0)),0) -> 0.002818 | F15: =C15*E15 -> 0.0035225
A16: 12 | B16: Tandori Masala Powder | C16: 2.5 | D16: =IFERROR(INDEX(LIST!$F$2:$F$131,MATCH(B16,LIST!$B$2:$B$131,0)),"") -> g | E16: =IFERROR(INDEX(LIST!$G$2:$G$131,MATCH(B16,LIST!$B$2:$B$131,0)),0) -> 0.004 | F16: =C16*E16 -> 0.01
... A18: 14 | B18: Salt | C18: 2.5 | D18: =IFERROR(INDEX(LIST!$F$2:$F$131,MATCH(B18,LIST!$B$2:$B$131,0)),"") -> g | E18: =IFERROR(INDEX(LIST!$G$2:$G$131,MATCH(B18,LIST!$B$2:$B$131,0)),0) -> 0.000165 | F18: =C18*E18 -> 0.0004125
B19: TOTAL RECIPE COST | F19: =SUM(F5:F18) -> 0.39680846
B21: Size | C21: Small | D21: Medium | E21: Large
B22: Recipes per container | C22: 1 | D22: 2 | E22: 4
B23: Ingredient cost | C23: =$F$19*C22 -> 0.39680846 | D23: =$F$19*D22 -> 0.79361692 | E23: =$F$19*E22 -> 1.5872338
B24: Container | C24: CONTENER NO : (3) | D24: CONTENER NO : (4) | E24: CONTENER NO : (5)
B25: Container cost | C25: =IFERROR(INDEX(LIST!$G$2:$G$131,MATCH(C24,LIST!$B$2:$B$131,0)),0) -> 0.021 | D25: =IFERROR(INDEX(LIST!$G$2:$G$131,MATCH(D24,LIST!$B$2:$B$131,0)),0) -> 0.0315 | E25: =IFERROR(INDEX(LIST!$G$2:$G$131,MATCH(E24,LIST!$B$2:$B$131,0)),0) -> 0.11666667
B26: Spoons (qty) | C26: 1 | D26: 2 | E26: 3
B27: Spoon cost | C27: =C26*IFERROR(INDEX(LIST!$G$2:$G$131,MATCH("SPOON",LIST!$B$2:$B$131,0)),0) -> 0.0064 | D27: =D26*IFERROR(INDEX(LIST!$G$2:$G$131,MATCH("SPOON",LIST!$B$2:$B$131,0)),0) -> 0.0128 | E27: =E26*IFERROR(INDEX(LIST!$G$2:$G$131,MATCH("SPOON",LIST!$B$2:$B$131,0)),0) -> 0.0192
B28: Bread (qty) | C28: 1 | D28: 2 | E28: 4
B29: Bread cost | C29: =C28*IFERROR(INDEX(LIST!$G$2:$G$131,MATCH("Bread",LIST!$B$2:$B$131,0)),0) -> 0.012 | D29: =D28*IFERROR(INDEX(LIST!$G$2:$G$131,MATCH("Bread",LIST!$B$2:$B$131,0)),0) -> 0.024 | E29: =E28*IFERROR(INDEX(LIST!$G$2:$G$131,MATCH("Bread",LIST!$B$2:$B$131,0)),0) -> 0.048
B30: Bag | C30: Bag Small | D30: Bag Medium | E30: Bag Large
B31: Bag cost | C31: =IFERROR(INDEX(LIST!$G$2:$G$131,MATCH(C30,LIST!$B$2:$B$131,0)),0) -> 0.02 | D31: =IFERROR(INDEX(LIST!$G$2:$G$131,MATCH(D30,LIST!$B$2:$B$131,0)),0) -> 0.03 | E31: =IFERROR(INDEX(LIST!$G$2:$G$131,MATCH(E30,LIST!$B$2:$B$131,0)),0) -> 0.04
B32: Other costs | C32: 0 | D32: 0 | E32: 0
B33: Packaging total | C33: =C25+C27+C29+C31+C32 -> 0.0594 | D33: =D25+D27+D29+D31+D32 -> 0.0983 | E33: =E25+E27+E29+E31+E32 -> 0.22386667
B34: TOTAL COST | C34: =C23+C33 -> 0.45620846 | D34: =D23+D33 -> 0.89191692 | E34: =E23+E33 -> 1.8111005
B35: Store price | C35: 1.5 | D35: 2.8 | E35: 5.4
B36: Store cost % | C36: =IF(C35=0,"",C34/C35) -> 0.30413897 | D36: =IF(D35=0,"",D34/D35) -> 0.31854176 | E36: =IF(E35=0,"",E34/E35) -> 0.33538898
B37: Delivery price | C37: 1.9 | D37: 3.4 | E37: 6.4
B38: Delivery cost % | C38: =IF(N(C37)=0,"",C34/C37) -> 0.24010972 | D38: =IF(N(D37)=0,"",D34/D37) -> 0.26232851 | E38: =IF(N(E37)=0,"",E34/E37) -> 0.28298446
B39: Store profit | C39: =C35-C34 -> 1.0437915 | D39: =D35-D34 -> 1.9080831 | E39: =E35-E34 -> 3.5888995
B40: Delivery profit | C40: =IF(N(C37)=0,"",C37-C34) -> 1.4437915 | D40: =IF(N(D37)=0,"",D37-D34) -> 2.5080831 | E40: =IF(N(E37)=0,"",E37-E34) -> 4.5888995

Sheet Fasolya
A1: Fasolya
A2: Eggs & fool · one container takes several recipes · target 30%
A4: # | B4: Item | C4: Qty | D4: Unit | E4: Unit price | F4: Cost
A5: 1 | B5: Baked Beans | C5: 190 | D5: =IFERROR(INDEX(LIST!$F$2:$F$131,MATCH(B5,LIST!$B$2:$B$131,0)),"") -> g | E5: =IFERROR(INDEX(LIST!$G$2:$G$131,MATCH(B5,LIST!$B$2:$B$131,0)),0) -> 0.00094736842 | F5: =C5*E5 -> 0.18
A6: 2 | B6: Cheddar Cheese | C6: 10 | D6: =IFERROR(INDEX(LIST!$F$2:$F$131,MATCH(B6,LIST!$B$2:$B$131,0)),"") -> g | E6: =IFERROR(INDEX(LIST!$G$2:$G$131,MATCH(B6,LIST!$B$2:$B$131,0)),0) -> 0.0021764706 | F6: =C6*E6 -> 0.021764706
A7: 3 | B7: Tahina | C7: 15 | D7: =IFERROR(INDEX(LIST!$F$2:$F$131,MATCH(B7,LIST!$B$2:$B$131,0)),"") -> g | E7: =IFERROR(INDEX(LIST!$G$2:$G$131,MATCH(B7,LIST!$B$2:$B$131,0)),0) -> 0.0009696 | F7: =C7*E7 -> 0.014544
A8: 4 | B8: Vegetable Oil | C8: 30 | D8: =IFERROR(INDEX(LIST!$F$2:$F$131,MATCH(B8,LIST!$B$2:$B$131,0)),"") -> ml | E8: =IFERROR(INDEX(LIST!$G$2:$G$131,MATCH(B8,LIST!$B$2:$B$131,0)),0) -> 0.000594 | F8: =C8*E8 -> 0.01782
A9: 5 | B9: Onion | C9: 60 | D9: =IFERROR(INDEX(LIST!$F$2:$F$131,MATCH(B9,LIST!$B$2:$B$131,0)),"") -> g | E9: =IFERROR(INDEX(LIST!$G$2:$G$131,MATCH(B9,LIST!$B$2:$B$131,0)),0) -> 0.00045 | F9: =C9*E9 -> 0.027
A10: 6 | B10: Tomato | C10: 120 | D10: =IFERROR(INDEX(LIST!$F$2:$F$131,MATCH(B10,LIST!$B$2:$B$131,0)),"") -> g | E10: =IFERROR(INDEX(LIST!$G$2:$G$131,MATCH(B10,LIST!$B$2:$B$131,0)),0) -> 0.0005 | F10: =C10*E10 -> 0.06
A11: 7 | B11: Coriander Leaves | C11: 1 | D11: =IFERROR(INDEX(LIST!$F$2:$F$131,MATCH(B11,LIST!$B$2:$B$131,0)),"") -> g | E11: =IFERROR(INDEX(LIST!$G$2:$G$131,MATCH(B11,LIST!$B$2:$B$131,0)),0) -> 0.0017272727 | F11: =C11*E11 -> 0.0017272727
A12: 8 | B12: Green Capiscum | C12: 10 | D12: =IFERROR(INDEX(LIST!$F$2:$F$131,MATCH(B12,LIST!$B$2:$B$131,0)),"") -> g | E12: =IFERROR(INDEX(LIST!$G$2:$G$131,MATCH(B12,LIST!$B$2:$B$131,0)),0) -> 0.00065 | F12: =C12*E12 -> 0.0065
A13: 9 | B13: Mix Masala Powder | C13: 1.25 | D13: =IFERROR(INDEX(LIST!$F$2:$F$131,MATCH(B13,LIST!$B$2:$B$131,0)),"") -> g | E13: =IFERROR(INDEX(LIST!$G$2:$G$131,MATCH(B13,LIST!$B$2:$B$131,0)),0) -> 0.00165 | F13: =C13*E13 -> 0.0020625
A14: 10 | B14: Turmeric Powder | C14: 1.25 | D14: =IFERROR(INDEX(LIST!$F$2:$F$131,MATCH(B14,LIST!$B$2:$B$131,0)),"") -> g | E14: =IFERROR(INDEX(LIST!$G$2:$G$131,MATCH(B14,LIST!$B$2:$B$131,0)),0) -> 0.0018 | F14: =C14*E14 -> 0.00225
A15: 11 | B15: Cummin Powder | C15: 1.25 | D15: =IFERROR(INDEX(LIST!$F$2:$F$131,MATCH(B15,LIST!$B$2:$B$131,0)),"") -> g | E15: =IFERROR(INDEX(LIST!$G$2:$G$131,MATCH(B15,LIST!$B$2:$B$131,0)),0) -> 0.002818 | F15: =C15*E15 -> 0.0035225
A16: 12 | B16: Tandori Masala Powder | C16: 2.5 | D16: =IFERROR(INDEX(LIST!$F$2:$F$131,MATCH(B16,LIST!$B$2:$B$131,0)),"") -> g | E16: =IFERROR(INDEX(LIST!$G$2:$G$131,MATCH(B16,LIST!$B$2:$B$131,0)),0) -> 0.004 | F16: =C16*E16 -> 0.01
... A18: 14 | B18: Salt | C18: 2.5 | D18: =IFERROR(INDEX(LIST!$F$2:$F$131,MATCH(B18,LIST!$B$2:$B$131,0)),"") -> g | E18: =IFERROR(INDEX(LIST!$G$2:$G$131,MATCH(B18,LIST!$B$2:$B$131,0)),0) -> 0.000165 | F18: =C18*E18 -> 0.0004125
B19: TOTAL RECIPE COST | F19: =SUM(F5:F18) -> 0.34966598
B21: Size | C21: Small | D21: Medium | E21: Large
B22: Recipes per container | C22: 1 | D22: 2 | E22: 4
B23: Ingredient cost | C23: =$F$19*C22 -> 0.34966598 | D23: =$F$19*D22 -> 0.69933196 | E23: =$F$19*E22 -> 1.3986639
B24: Container | C24: CONTENER NO : (3) | D24: CONTENER NO : (4) | E24: CONTENER NO : (5)
B25: Container cost | C25: =IFERROR(INDEX(LIST!$G$2:$G$131,MATCH(C24,LIST!$B$2:$B$131,0)),0) -> 0.021 | D25: =IFERROR(INDEX(LIST!$G$2:$G$131,MATCH(D24,LIST!$B$2:$B$131,0)),0) -> 0.0315 | E25: =IFERROR(INDEX(LIST!$G$2:$G$131,MATCH(E24,LIST!$B$2:$B$131,0)),0) -> 0.11666667
B26: Spoons (qty) | C26: 1 | D26: 2 | E26: 3
B27: Spoon cost | C27: =C26*IFERROR(INDEX(LIST!$G$2:$G$131,MATCH("SPOON",LIST!$B$2:$B$131,0)),0) -> 0.0064 | D27: =D26*IFERROR(INDEX(LIST!$G$2:$G$131,MATCH("SPOON",LIST!$B$2:$B$131,0)),0) -> 0.0128 | E27: =E26*IFERROR(INDEX(LIST!$G$2:$G$131,MATCH("SPOON",LIST!$B$2:$B$131,0)),0) -> 0.0192
B28: Bread (qty) | C28: 1 | D28: 2 | E28: 4
B29: Bread cost | C29: =C28*IFERROR(INDEX(LIST!$G$2:$G$131,MATCH("Bread",LIST!$B$2:$B$131,0)),0) -> 0.012 | D29: =D28*IFERROR(INDEX(LIST!$G$2:$G$131,MATCH("Bread",LIST!$B$2:$B$131,0)),0) -> 0.024 | E29: =E28*IFERROR(INDEX(LIST!$G$2:$G$131,MATCH("Bread",LIST!$B$2:$B$131,0)),0) -> 0.048
B30: Bag | C30: Bag Small | D30: Bag Medium | E30: Bag Large
B31: Bag cost | C31: =IFERROR(INDEX(LIST!$G$2:$G$131,MATCH(C30,LIST!$B$2:$B$131,0)),0) -> 0.02 | D31: =IFERROR(INDEX(LIST!$G$2:$G$131,MATCH(D30,LIST!$B$2:$B$131,0)),0) -> 0.03 | E31: =IFERROR(INDEX(LIST!$G$2:$G$131,MATCH(E30,LIST!$B$2:$B$131,0)),0) -> 0.04
B32: Other costs | C32: 0 | D32: 0 | E32: 0
B33: Packaging total | C33: =C25+C27+C29+C31+C32 -> 0.0594 | D33: =D25+D27+D29+D31+D32 -> 0.0983 | E33: =E25+E27+E29+E31+E32 -> 0.22386667
B34: TOTAL COST | C34: =C23+C33 -> 0.40906598 | D34: =D23+D33 -> 0.79763196 | E34: =E23+E33 -> 1.6225306
B35: Store price | C35: 1.3 | D35: 2.4 | E35: 4.6
B36: Store cost % | C36: =IF(C35=0,"",C34/C35) -> 0.31466614 | D36: =IF(D35=0,"",D34/D35) -> 0.33234665 | E36: =IF(E35=0,"",E34/E35) -> 0.35272404
B37: Delivery price | C37: 1.7 | D37: 3 | E37: 5.6
B38: Delivery cost % | C38: =IF(N(C37)=0,"",C34/C37) -> 0.24062705 | D38: =IF(N(D37)=0,"",D34/D37) -> 0.26587732 | E38: =IF(N(E37)=0,"",E34/E37) -> 0.2897376
B39: Store profit | C39: =C35-C34 -> 0.89093402 | D39: =D35-D34 -> 1.602368 | E39: =E35-E34 -> 2.9774694
B40: Delivery profit | C40: =IF(N(C37)=0,"",C37-C34) -> 1.290934 | D40: =IF(N(D37)=0,"",D37-D34) -> 2.202368 | E40: =IF(N(E37)=0,"",E37-E34) -> 3.9774694

Sheet S.Egg Bin Aqool
A1: S.Egg Bin Aqool
A2: Eggs & fool · one container takes several recipes · target 30%
A4: # | B4: Item | C4: Qty | D4: Unit | E4: Unit price | F4: Cost
A5: 1 | B5: Green Peas (S.P) | C5: 190 | D5: =IFERROR(INDEX(LIST!$F$2:$F$131,MATCH(B5,LIST!$B$2:$B$131,0)),"") -> g | E5: =IFERROR(INDEX(LIST!$G$2:$G$131,MATCH(B5,LIST!$B$2:$B$131,0)),0) -> 0.00077105263 | F5: =C5*E5 -> 0.1465
A6: 2 | B6: Egg | C6: 2 | D6: =IFERROR(INDEX(LIST!$F$2:$F$131,MATCH(B6,LIST!$B$2:$B$131,0)),"") -> pc | E6: =IFERROR(INDEX(LIST!$G$2:$G$131,MATCH(B6,LIST!$B$2:$B$131,0)),0) -> 0.035 | F6: =C6*E6 -> 0.07
A7: 3 | B7: Cheddar Cheese | C7: 10 | D7: =IFERROR(INDEX(LIST!$F$2:$F$131,MATCH(B7,LIST!$B$2:$B$131,0)),"") -> g | E7: =IFERROR(INDEX(LIST!$G$2:$G$131,MATCH(B7,LIST!$B$2:$B$131,0)),0) -> 0.0021764706 | F7: =C7*E7 -> 0.021764706
A8: 4 | B8: Onion | C8: 60 | D8: =IFERROR(INDEX(LIST!$F$2:$F$131,MATCH(B8,LIST!$B$2:$B$131,0)),"") -> g | E8: =IFERROR(INDEX(LIST!$G$2:$G$131,MATCH(B8,LIST!$B$2:$B$131,0)),0) -> 0.00045 | F8: =C8*E8 -> 0.027
A9: 5 | B9: Long Chilly | C9: 7.5 | D9: =IFERROR(INDEX(LIST!$F$2:$F$131,MATCH(B9,LIST!$B$2:$B$131,0)),"") -> g | E9: =IFERROR(INDEX(LIST!$G$2:$G$131,MATCH(B9,LIST!$B$2:$B$131,0)),0) -> 0.0011 | F9: =C9*E9 -> 0.00825
A10: 6 | B10: Tomato | C10: 80 | D10: =IFERROR(INDEX(LIST!$F$2:$F$131,MATCH(B10,LIST!$B$2:$B$131,0)),"") -> g | E10: =IFERROR(INDEX(LIST!$G$2:$G$131,MATCH(B10,LIST!$B$2:$B$131,0)),0) -> 0.0005 | F10: =C10*E10 -> 0.04
A11: 7 | B11: Potato | C11: 7.5 | D11: =IFERROR(INDEX(LIST!$F$2:$F$131,MATCH(B11,LIST!$B$2:$B$131,0)),"") -> g | E11: =IFERROR(INDEX(LIST!$G$2:$G$131,MATCH(B11,LIST!$B$2:$B$131,0)),0) -> 0.00036 | F11: =C11*E11 -> 0.0027
A12: 8 | B12: Green Capiscum | C12: 15 | D12: =IFERROR(INDEX(LIST!$F$2:$F$131,MATCH(B12,LIST!$B$2:$B$131,0)),"") -> g | E12: =IFERROR(INDEX(LIST!$G$2:$G$131,MATCH(B12,LIST!$B$2:$B$131,0)),0) -> 0.00065 | F12: =C12*E12 -> 0.00975
A13: 9 | B13: Vegetable Oil | C13: 30 | D13: =IFERROR(INDEX(LIST!$F$2:$F$131,MATCH(B13,LIST!$B$2:$B$131,0)),"") -> ml | E13: =IFERROR(INDEX(LIST!$G$2:$G$131,MATCH(B13,LIST!$B$2:$B$131,0)),0) -> 0.000594 | F13: =C13*E13 -> 0.01782
A14: 10 | B14: Tomato Paste | C14: 10 | D14: =IFERROR(INDEX(LIST!$F$2:$F$131,MATCH(B14,LIST!$B$2:$B$131,0)),"") -> g | E14: =IFERROR(INDEX(LIST!$G$2:$G$131,MATCH(B14,LIST!$B$2:$B$131,0)),0) -> 0.0006 | F14: =C14*E14 -> 0.006
A15: 11 | B15: Salt | C15: 2.5 | D15: =IFERROR(INDEX(LIST!$F$2:$F$131,MATCH(B15,LIST!$B$2:$B$131,0)),"") -> g | E15: =IFERROR(INDEX(LIST!$G$2:$G$131,MATCH(B15,LIST!$B$2:$B$131,0)),0) -> 0.000165 | F15: =C15*E15 -> 0.0004125
A16: 12 | B16: Olive Oil | C16: 7.5 | D16: =IFERROR(INDEX(LIST!$F$2:$F$131,MATCH(B16,LIST!$B$2:$B$131,0)),"") -> ml | E16: =IFERROR(INDEX(LIST!$G$2:$G$131,MATCH(B16,LIST!$B$2:$B$131,0)),0) -> 0.000308 | F16: =C16*E16 -> 0.00231
... A21: 17 | B21: Mix Masala Powder | C21: 1.25 | D21: =IFERROR(INDEX(LIST!$F$2:$F$131,MATCH(B21,LIST!$B$2:$B$131,0)),"") -> g | E21: =IFERROR(INDEX(LIST!$G$2:$G$131,MATCH(B21,LIST!$B$2:$B$131,0)),0) -> 0.00165 | F21: =C21*E21 -> 0.0020625
B22: TOTAL RECIPE COST | F22: =SUM(F5:F21) -> 0.37969871
B24: Size | C24: Small | D24: Medium | E24: Large
B25: Recipes per container | C25: 1 | D25: 2 | E25: 4
B26: Ingredient cost | C26: =$F$22*C25 -> 0.37969871 | D26: =$F$22*D25 -> 0.75939741 | E26: =$F$22*E25 -> 1.5187948
B27: Container | C27: CONTENER NO : (3) | D27: CONTENER NO : (4) | E27: CONTENER NO : (5)
B28: Container cost | C28: =IFERROR(INDEX(LIST!$G$2:$G$131,MATCH(C27,LIST!$B$2:$B$131,0)),0) -> 0.021 | D28: =IFERROR(INDEX(LIST!$G$2:$G$131,MATCH(D27,LIST!$B$2:$B$131,0)),0) -> 0.0315 | E28: =IFERROR(INDEX(LIST!$G$2:$G$131,MATCH(E27,LIST!$B$2:$B$131,0)),0) -> 0.11666667
B29: Spoons (qty) | C29: 1 | D29: 2 | E29: 3
B30: Spoon cost | C30: =C29*IFERROR(INDEX(LIST!$G$2:$G$131,MATCH("SPOON",LIST!$B$2:$B$131,0)),0) -> 0.0064 | D30: =D29*IFERROR(INDEX(LIST!$G$2:$G$131,MATCH("SPOON",LIST!$B$2:$B$131,0)),0) -> 0.0128 | E30: =E29*IFERROR(INDEX(LIST!$G$2:$G$131,MATCH("SPOON",LIST!$B$2:$B$131,0)),0) -> 0.0192
B31: Bread (qty) | C31: 1 | D31: 2 | E31: 4
B32: Bread cost | C32: =C31*IFERROR(INDEX(LIST!$G$2:$G$131,MATCH("Bread",LIST!$B$2:$B$131,0)),0) -> 0.012 | D32: =D31*IFERROR(INDEX(LIST!$G$2:$G$131,MATCH("Bread",LIST!$B$2:$B$131,0)),0) -> 0.024 | E32: =E31*IFERROR(INDEX(LIST!$G$2:$G$131,MATCH("Bread",LIST!$B$2:$B$131,0)),0) -> 0.048
B33: Bag | C33: Bag Small | D33: Bag Medium | E33: Bag Large
B34: Bag cost | C34: =IFERROR(INDEX(LIST!$G$2:$G$131,MATCH(C33,LIST!$B$2:$B$131,0)),0) -> 0.02 | D34: =IFERROR(INDEX(LIST!$G$2:$G$131,MATCH(D33,LIST!$B$2:$B$131,0)),0) -> 0.03 | E34: =IFERROR(INDEX(LIST!$G$2:$G$131,MATCH(E33,LIST!$B$2:$B$131,0)),0) -> 0.04
B35: Other costs | C35: 0 | D35: 0 | E35: 0
B36: Packaging total | C36: =C28+C30+C32+C34+C35 -> 0.0594 | D36: =D28+D30+D32+D34+D35 -> 0.0983 | E36: =E28+E30+E32+E34+E35 -> 0.22386667
B37: TOTAL COST | C37: =C26+C36 -> 0.43909871 | D37: =D26+D36 -> 0.85769741 | E37: =E26+E36 -> 1.7426615
B38: Store price | C38: 1.6 | D38: 3 | E38: 5.6
B39: Store cost % | C39: =IF(C38=0,"",C37/C38) -> 0.27443669 | D39: =IF(D38=0,"",D37/D38) -> 0.28589914 | E39: =IF(E38=0,"",E37/E38) -> 0.31118955
B40: Delivery price | C40: 2 | D40: 3.6 | E40: 6.8
B41: Delivery cost % | C41: =IF(N(C40)=0,"",C37/C40) -> 0.21954935 | D41: =IF(N(D40)=0,"",D37/D40) -> 0.23824928 | E41: =IF(N(E40)=0,"",E37/E40) -> 0.25627375
B42: Store profit | C42: =C38-C37 -> 1.1609013 | D42: =D38-D37 -> 2.1423026 | E42: =E38-E37 -> 3.8573385
B43: Delivery profit | C43: =IF(N(C40)=0,"",C40-C37) -> 1.5609013 | D43: =IF(N(D40)=0,"",D40-D37) -> 2.7423026 | E43: =IF(N(E40)=0,"",E40-E37) -> 5.0573385

Sheet Egg Shakshoka
A1: Egg Shakshoka
A2: Eggs & fool · one container takes several recipes · target 30%
A4: # | B4: Item | C4: Qty | D4: Unit | E4: Unit price | F4: Cost
A5: 1 | B5: Egg | C5: 2 | D5: =IFERROR(INDEX(LIST!$F$2:$F$131,MATCH(B5,LIST!$B$2:$B$131,0)),"") -> pc | E5: =IFERROR(INDEX(LIST!$G$2:$G$131,MATCH(B5,LIST!$B$2:$B$131,0)),0) -> 0.035 | F5: =C5*E5 -> 0.07
A6: 2 | B6: Vegetable Oil | C6: 30 | D6: =IFERROR(INDEX(LIST!$F$2:$F$131,MATCH(B6,LIST!$B$2:$B$131,0)),"") -> ml | E6: =IFERROR(INDEX(LIST!$G$2:$G$131,MATCH(B6,LIST!$B$2:$B$131,0)),0) -> 0.000594 | F6: =C6*E6 -> 0.01782
A7: 3 | B7: Tomato Paste | C7: 10 | D7: =IFERROR(INDEX(LIST!$F$2:$F$131,MATCH(B7,LIST!$B$2:$B$131,0)),"") -> g | E7: =IFERROR(INDEX(LIST!$G$2:$G$131,MATCH(B7,LIST!$B$2:$B$131,0)),0) -> 0.0006 | F7: =C7*E7 -> 0.006
A8: 4 | B8: Onion | C8: 60 | D8: =IFERROR(INDEX(LIST!$F$2:$F$131,MATCH(B8,LIST!$B$2:$B$131,0)),"") -> g | E8: =IFERROR(INDEX(LIST!$G$2:$G$131,MATCH(B8,LIST!$B$2:$B$131,0)),0) -> 0.00045 | F8: =C8*E8 -> 0.027
A9: 5 | B9: Coriander Leaves | C9: 2 | D9: =IFERROR(INDEX(LIST!$F$2:$F$131,MATCH(B9,LIST!$B$2:$B$131,0)),"") -> g | E9: =IFERROR(INDEX(LIST!$G$2:$G$131,MATCH(B9,LIST!$B$2:$B$131,0)),0) -> 0.0017272727 | F9: =C9*E9 -> 0.0034545455
A10: 6 | B10: Tomato | C10: 120 | D10: =IFERROR(INDEX(LIST!$F$2:$F$131,MATCH(B10,LIST!$B$2:$B$131,0)),"") -> g | E10: =IFERROR(INDEX(LIST!$G$2:$G$131,MATCH(B10,LIST!$B$2:$B$131,0)),0) -> 0.0005 | F10: =C10*E10 -> 0.06
A11: 7 | B11: Turmeric Powder | C11: 1.25 | D11: =IFERROR(INDEX(LIST!$F$2:$F$131,MATCH(B11,LIST!$B$2:$B$131,0)),"") -> g | E11: =IFERROR(INDEX(LIST!$G$2:$G$131,MATCH(B11,LIST!$B$2:$B$131,0)),0) -> 0.0018 | F11: =C11*E11 -> 0.00225
A12: 8 | B12: Cummin Powder | C12: 1.25 | D12: =IFERROR(INDEX(LIST!$F$2:$F$131,MATCH(B12,LIST!$B$2:$B$131,0)),"") -> g | E12: =IFERROR(INDEX(LIST!$G$2:$G$131,MATCH(B12,LIST!$B$2:$B$131,0)),0) -> 0.002818 | F12: =C12*E12 -> 0.0035225
A13: 9 | B13: Tandori Masala Powder | C13: 1.25 | D13: =IFERROR(INDEX(LIST!$F$2:$F$131,MATCH(B13,LIST!$B$2:$B$131,0)),"") -> g | E13: =IFERROR(INDEX(LIST!$G$2:$G$131,MATCH(B13,LIST!$B$2:$B$131,0)),0) -> 0.004 | F13: =C13*E13 -> 0.005
A14: 10 | B14: Curry Powder | C14: 1.25 | D14: =IFERROR(INDEX(LIST!$F$2:$F$131,MATCH(B14,LIST!$B$2:$B$131,0)),"") -> g | E14: =IFERROR(INDEX(LIST!$G$2:$G$131,MATCH(B14,LIST!$B$2:$B$131,0)),0) -> 0.00165 | F14: =C14*E14 -> 0.0020625
A15: 11 | B15: Salt | C15: 1.25 | D15: =IFERROR(INDEX(LIST!$F$2:$F$131,MATCH(B15,LIST!$B$2:$B$131,0)),"") -> g | E15: =IFERROR(INDEX(LIST!$G$2:$G$131,MATCH(B15,LIST!$B$2:$B$131,0)),0) -> 0.000165 | F15: =C15*E15 -> 0.00020625
B16: TOTAL RECIPE COST | F16: =SUM(F5:F15) -> 0.1973158
B18: Size | C18: Small | D18: Medium | E18: Large
B19: Recipes per container | C19: 1 | D19: 2 | E19: 4
B20: Ingredient cost | C20: =$F$16*C19 -> 0.1973158 | D20: =$F$16*D19 -> 0.39463159 | E20: =$F$16*E19 -> 0.78926318
B21: Container | C21: CONTENER NO : (3) | D21: CONTENER NO : (4) | E21: CONTENER NO : (5)
B22: Container cost | C22: =IFERROR(INDEX(LIST!$G$2:$G$131,MATCH(C21,LIST!$B$2:$B$131,0)),0) -> 0.021 | D22: =IFERROR(INDEX(LIST!$G$2:$G$131,MATCH(D21,LIST!$B$2:$B$131,0)),0) -> 0.0315 | E22: =IFERROR(INDEX(LIST!$G$2:$G$131,MATCH(E21,LIST!$B$2:$B$131,0)),0) -> 0.11666667
B23: Spoons (qty) | C23: 1 | D23: 2 | E23: 3
B24: Spoon cost | C24: =C23*IFERROR(INDEX(LIST!$G$2:$G$131,MATCH("SPOON",LIST!$B$2:$B$131,0)),0) -> 0.0064 | D24: =D23*IFERROR(INDEX(LIST!$G$2:$G$131,MATCH("SPOON",LIST!$B$2:$B$131,0)),0) -> 0.0128 | E24: =E23*IFERROR(INDEX(LIST!$G$2:$G$131,MATCH("SPOON",LIST!$B$2:$B$131,0)),0) -> 0.0192
B25: Bread (qty) | C25: 1 | D25: 2 | E25: 4
B26: Bread cost | C26: =C25*IFERROR(INDEX(LIST!$G$2:$G$131,MATCH("Bread",LIST!$B$2:$B$131,0)),0) -> 0.012 | D26: =D25*IFERROR(INDEX(LIST!$G$2:$G$131,MATCH("Bread",LIST!$B$2:$B$131,0)),0) -> 0.024 | E26: =E25*IFERROR(INDEX(LIST!$G$2:$G$131,MATCH("Bread",LIST!$B$2:$B$131,0)),0) -> 0.048
B27: Bag | C27: Bag Small | D27: Bag Medium | E27: Bag Large
B28: Bag cost | C28: =IFERROR(INDEX(LIST!$G$2:$G$131,MATCH(C27,LIST!$B$2:$B$131,0)),0) -> 0.02 | D28: =IFERROR(INDEX(LIST!$G$2:$G$131,MATCH(D27,LIST!$B$2:$B$131,0)),0) -> 0.03 | E28: =IFERROR(INDEX(LIST!$G$2:$G$131,MATCH(E27,LIST!$B$2:$B$131,0)),0) -> 0.04
B29: Other costs | C29: 0 | D29: 0 | E29: 0
B30: Packaging total | C30: =C22+C24+C26+C28+C29 -> 0.0594 | D30: =D22+D24+D26+D28+D29 -> 0.0983 | E30: =E22+E24+E26+E28+E29 -> 0.22386667
B31: TOTAL COST | C31: =C20+C30 -> 0.2567158 | D31: =D20+D30 -> 0.49293159 | E31: =E20+E30 -> 1.0131298
B32: Store price | C32: 1.2 | D32: 2.2 | E32: 4.2
B33: Store cost % | C33: =IF(C32=0,"",C31/C32) -> 0.21392983 | D33: =IF(D32=0,"",D31/D32) -> 0.22405981 | E33: =IF(E32=0,"",E31/E32) -> 0.24122139
B34: Delivery price | C34: 1.6 | D34: 2.8 | E34: 5
B35: Delivery cost % | C35: =IF(N(C34)=0,"",C31/C34) -> 0.16044737 | D35: =IF(N(D34)=0,"",D31/D34) -> 0.176047 | E35: =IF(N(E34)=0,"",E31/E34) -> 0.20262597
B36: Store profit | C36: =C32-C31 -> 0.9432842 | D36: =D32-D31 -> 1.7070684 | E36: =E32-E31 -> 3.1868702
B37: Delivery profit | C37: =IF(N(C34)=0,"",C34-C31) -> 1.3432842 | D37: =IF(N(D34)=0,"",D34-D31) -> 2.3070684 | E37: =IF(N(E34)=0,"",E34-E31) -> 3.9868702

Sheet Egg Vegatable
A1: Egg Vegatable
A2: Eggs & fool · one container takes several recipes · target 30%
A4: # | B4: Item | C4: Qty | D4: Unit | E4: Unit price | F4: Cost
A5: 1 | B5: Egg | C5: 2 | D5: =IFERROR(INDEX(LIST!$F$2:$F$131,MATCH(B5,LIST!$B$2:$B$131,0)),"") -> pc | E5: =IFERROR(INDEX(LIST!$G$2:$G$131,MATCH(B5,LIST!$B$2:$B$131,0)),0) -> 0.035 | F5: =C5*E5 -> 0.07
A6: 2 | B6: Vegetable Oil | C6: 15 | D6: =IFERROR(INDEX(LIST!$F$2:$F$131,MATCH(B6,LIST!$B$2:$B$131,0)),"") -> ml | E6: =IFERROR(INDEX(LIST!$G$2:$G$131,MATCH(B6,LIST!$B$2:$B$131,0)),0) -> 0.000594 | F6: =C6*E6 -> 0.00891
A7: 3 | B7: Tomato Paste | C7: 15 | D7: =IFERROR(INDEX(LIST!$F$2:$F$131,MATCH(B7,LIST!$B$2:$B$131,0)),"") -> g | E7: =IFERROR(INDEX(LIST!$G$2:$G$131,MATCH(B7,LIST!$B$2:$B$131,0)),0) -> 0.0006 | F7: =C7*E7 -> 0.009
A8: 4 | B8: Onion | C8: 60 | D8: =IFERROR(INDEX(LIST!$F$2:$F$131,MATCH(B8,LIST!$B$2:$B$131,0)),"") -> g | E8: =IFERROR(INDEX(LIST!$G$2:$G$131,MATCH(B8,LIST!$B$2:$B$131,0)),0) -> 0.00045 | F8: =C8*E8 -> 0.027
A9: 5 | B9: Potato | C9: 30 | D9: =IFERROR(INDEX(LIST!$F$2:$F$131,MATCH(B9,LIST!$B$2:$B$131,0)),"") -> g | E9: =IFERROR(INDEX(LIST!$G$2:$G$131,MATCH(B9,LIST!$B$2:$B$131,0)),0) -> 0.00036 | F9: =C9*E9 -> 0.0108
A10: 6 | B10: Green Capiscum | C10: 15 | D10: =IFERROR(INDEX(LIST!$F$2:$F$131,MATCH(B10,LIST!$B$2:$B$131,0)),"") -> g | E10: =IFERROR(INDEX(LIST!$G$2:$G$131,MATCH(B10,LIST!$B$2:$B$131,0)),0) -> 0.00065 | F10: =C10*E10 -> 0.00975
A11: 7 | B11: Coriander Leaves | C11: 2 | D11: =IFERROR(INDEX(LIST!$F$2:$F$131,MATCH(B11,LIST!$B$2:$B$131,0)),"") -> g | E11: =IFERROR(INDEX(LIST!$G$2:$G$131,MATCH(B11,LIST!$B$2:$B$131,0)),0) -> 0.0017272727 | F11: =C11*E11 -> 0.0034545455
A12: 8 | B12: Tomato | C12: 120 | D12: =IFERROR(INDEX(LIST!$F$2:$F$131,MATCH(B12,LIST!$B$2:$B$131,0)),"") -> g | E12: =IFERROR(INDEX(LIST!$G$2:$G$131,MATCH(B12,LIST!$B$2:$B$131,0)),0) -> 0.0005 | F12: =C12*E12 -> 0.06
A13: 9 | B13: Mix Masala Powder | C13: 1.2 | D13: =IFERROR(INDEX(LIST!$F$2:$F$131,MATCH(B13,LIST!$B$2:$B$131,0)),"") -> g | E13: =IFERROR(INDEX(LIST!$G$2:$G$131,MATCH(B13,LIST!$B$2:$B$131,0)),0) -> 0.00165 | F13: =C13*E13 -> 0.00198
A14: 10 | B14: Cummin Powder | C14: 1.2 | D14: =IFERROR(INDEX(LIST!$F$2:$F$131,MATCH(B14,LIST!$B$2:$B$131,0)),"") -> g | E14: =IFERROR(INDEX(LIST!$G$2:$G$131,MATCH(B14,LIST!$B$2:$B$131,0)),0) -> 0.002818 | F14: =C14*E14 -> 0.0033816
A15: 11 | B15: Tandori Masala Powder | C15: 1.2 | D15: =IFERROR(INDEX(LIST!$F$2:$F$131,MATCH(B15,LIST!$B$2:$B$131,0)),"") -> g | E15: =IFERROR(INDEX(LIST!$G$2:$G$131,MATCH(B15,LIST!$B$2:$B$131,0)),0) -> 0.004 | F15: =C15*E15 -> 0.0048
A16: 12 | B16: Turmeric Powder | C16: 1.2 | D16: =IFERROR(INDEX(LIST!$F$2:$F$131,MATCH(B16,LIST!$B$2:$B$131,0)),"") -> g | E16: =IFERROR(INDEX(LIST!$G$2:$G$131,MATCH(B16,LIST!$B$2:$B$131,0)),0) -> 0.0018 | F16: =C16*E16 -> 0.00216
... A18: 14 | B18: Salt | C18: 2.5 | D18: =IFERROR(INDEX(LIST!$F$2:$F$131,MATCH(B18,LIST!$B$2:$B$131,0)),"") -> g | E18: =IFERROR(INDEX(LIST!$G$2:$G$131,MATCH(B18,LIST!$B$2:$B$131,0)),0) -> 0.000165 | F18: =C18*E18 -> 0.0004125
B19: TOTAL RECIPE COST | F19: =SUM(F5:F18) -> 0.21362865
B21: Size | C21: Small | D21: Medium | E21: Large
B22: Recipes per container | C22: 1 | D22: 2 | E22: 4
B23: Ingredient cost | C23: =$F$19*C22 -> 0.21362865 | D23: =$F$19*D22 -> 0.42725729 | E23: =$F$19*E22 -> 0.85451458
B24: Container | C24: CONTENER NO : (3) | D24: CONTENER NO : (4) | E24: CONTENER NO : (5)
B25: Container cost | C25: =IFERROR(INDEX(LIST!$G$2:$G$131,MATCH(C24,LIST!$B$2:$B$131,0)),0) -> 0.021 | D25: =IFERROR(INDEX(LIST!$G$2:$G$131,MATCH(D24,LIST!$B$2:$B$131,0)),0) -> 0.0315 | E25: =IFERROR(INDEX(LIST!$G$2:$G$131,MATCH(E24,LIST!$B$2:$B$131,0)),0) -> 0.11666667
B26: Spoons (qty) | C26: 1 | D26: 2 | E26: 3
B27: Spoon cost | C27: =C26*IFERROR(INDEX(LIST!$G$2:$G$131,MATCH("SPOON",LIST!$B$2:$B$131,0)),0) -> 0.0064 | D27: =D26*IFERROR(INDEX(LIST!$G$2:$G$131,MATCH("SPOON",LIST!$B$2:$B$131,0)),0) -> 0.0128 | E27: =E26*IFERROR(INDEX(LIST!$G$2:$G$131,MATCH("SPOON",LIST!$B$2:$B$131,0)),0) -> 0.0192
B28: Bread (qty) | C28: 1 | D28: 2 | E28: 4
B29: Bread cost | C29: =C28*IFERROR(INDEX(LIST!$G$2:$G$131,MATCH("Bread",LIST!$B$2:$B$131,0)),0) -> 0.012 | D29: =D28*IFERROR(INDEX(LIST!$G$2:$G$131,MATCH("Bread",LIST!$B$2:$B$131,0)),0) -> 0.024 | E29: =E28*IFERROR(INDEX(LIST!$G$2:$G$131,MATCH("Bread",LIST!$B$2:$B$131,0)),0) -> 0.048
B30: Bag | C30: Bag Small | D30: Bag Medium | E30: Bag Large
B31: Bag cost | C31: =IFERROR(INDEX(LIST!$G$2:$G$131,MATCH(C30,LIST!$B$2:$B$131,0)),0) -> 0.02 | D31: =IFERROR(INDEX(LIST!$G$2:$G$131,MATCH(D30,LIST!$B$2:$B$131,0)),0) -> 0.03 | E31: =IFERROR(INDEX(LIST!$G$2:$G$131,MATCH(E30,LIST!$B$2:$B$131,0)),0) -> 0.04
B32: Other costs | C32: 0 | D32: 0 | E32: 0
B33: Packaging total | C33: =C25+C27+C29+C31+C32 -> 0.0594 | D33: =D25+D27+D29+D31+D32 -> 0.0983 | E33: =E25+E27+E29+E31+E32 -> 0.22386667
B34: TOTAL COST | C34: =C23+C33 -> 0.27302865 | D34: =D23+D33 -> 0.52555729 | E34: =E23+E33 -> 1.0783812
B35: Store price | C35: 1.2 | D35: 2.2 | E35: 4.2
B36: Store cost % | C36: =IF(C35=0,"",C34/C35) -> 0.22752387 | D36: =IF(D35=0,"",D34/D35) -> 0.23888968 | E36: =IF(E35=0,"",E34/E35) -> 0.25675744
B37: Delivery price | C37: 1.6 | D37: 2.8 | E37: 5
B38: Delivery cost % | C38: =IF(N(C37)=0,"",C34/C37) -> 0.1706429 | D38: =IF(N(D37)=0,"",D34/D37) -> 0.18769903 | E38: =IF(N(E37)=0,"",E34/E37) -> 0.21567625
B39: Store profit | C39: =C35-C34 -> 0.92697135 | D39: =D35-D34 -> 1.6744427 | E39: =E35-E34 -> 3.1216188
B40: Delivery profit | C40: =IF(N(C37)=0,"",C37-C34) -> 1.3269714 | D40: =IF(N(D37)=0,"",D37-D34) -> 2.2744427 | E40: =IF(N(E37)=0,"",E37-E34) -> 3.9216188

Sheet Egg Makhalama
A1: Egg Makhalama
A2: Eggs & fool · one container takes several recipes · target 30%
A4: # | B4: Item | C4: Qty | D4: Unit | E4: Unit price | F4: Cost
A5: 1 | B5: Minced Beef | C5: 30 | D5: =IFERROR(INDEX(LIST!$F$2:$F$131,MATCH(B5,LIST!$B$2:$B$131,0)),"") -> g | E5: =IFERROR(INDEX(LIST!$G$2:$G$131,MATCH(B5,LIST!$B$2:$B$131,0)),0) -> 0.0005975 | F5: =C5*E5 -> 0.017925
A6: 2 | B6: Egg | C6: 2 | D6: =IFERROR(INDEX(LIST!$F$2:$F$131,MATCH(B6,LIST!$B$2:$B$131,0)),"") -> pc | E6: =IFERROR(INDEX(LIST!$G$2:$G$131,MATCH(B6,LIST!$B$2:$B$131,0)),0) -> 0.035 | F6: =C6*E6 -> 0.07
A7: 3 | B7: Vegetable Oil | C7: 15 | D7: =IFERROR(INDEX(LIST!$F$2:$F$131,MATCH(B7,LIST!$B$2:$B$131,0)),"") -> ml | E7: =IFERROR(INDEX(LIST!$G$2:$G$131,MATCH(B7,LIST!$B$2:$B$131,0)),0) -> 0.000594 | F7: =C7*E7 -> 0.00891
A8: 4 | B8: Tomato Paste | C8: 5 | D8: =IFERROR(INDEX(LIST!$F$2:$F$131,MATCH(B8,LIST!$B$2:$B$131,0)),"") -> g | E8: =IFERROR(INDEX(LIST!$G$2:$G$131,MATCH(B8,LIST!$B$2:$B$131,0)),0) -> 0.0006 | F8: =C8*E8 -> 0.003
A9: 5 | B9: Onion | C9: 60 | D9: =IFERROR(INDEX(LIST!$F$2:$F$131,MATCH(B9,LIST!$B$2:$B$131,0)),"") -> g | E9: =IFERROR(INDEX(LIST!$G$2:$G$131,MATCH(B9,LIST!$B$2:$B$131,0)),0) -> 0.00045 | F9: =C9*E9 -> 0.027
A10: 6 | B10: Coriander Leaves | C10: 2 | D10: =IFERROR(INDEX(LIST!$F$2:$F$131,MATCH(B10,LIST!$B$2:$B$131,0)),"") -> g | E10: =IFERROR(INDEX(LIST!$G$2:$G$131,MATCH(B10,LIST!$B$2:$B$131,0)),0) -> 0.0017272727 | F10: =C10*E10 -> 0.0034545455
A11: 7 | B11: Tomato | C11: 120 | D11: =IFERROR(INDEX(LIST!$F$2:$F$131,MATCH(B11,LIST!$B$2:$B$131,0)),"") -> g | E11: =IFERROR(INDEX(LIST!$G$2:$G$131,MATCH(B11,LIST!$B$2:$B$131,0)),0) -> 0.0005 | F11: =C11*E11 -> 0.06
A12: 8 | B12: Green Capiscum | C12: 15 | D12: =IFERROR(INDEX(LIST!$F$2:$F$131,MATCH(B12,LIST!$B$2:$B$131,0)),"") -> g | E12: =IFERROR(INDEX(LIST!$G$2:$G$131,MATCH(B12,LIST!$B$2:$B$131,0)),0) -> 0.00065 | F12: =C12*E12 -> 0.00975
A13: 9 | B13: Turmeric Powder | C13: 1.2 | D13: =IFERROR(INDEX(LIST!$F$2:$F$131,MATCH(B13,LIST!$B$2:$B$131,0)),"") -> g | E13: =IFERROR(INDEX(LIST!$G$2:$G$131,MATCH(B13,LIST!$B$2:$B$131,0)),0) -> 0.0018 | F13: =C13*E13 -> 0.00216
A14: 10 | B14: Cummin Powder | C14: 1.2 | D14: =IFERROR(INDEX(LIST!$F$2:$F$131,MATCH(B14,LIST!$B$2:$B$131,0)),"") -> g | E14: =IFERROR(INDEX(LIST!$G$2:$G$131,MATCH(B14,LIST!$B$2:$B$131,0)),0) -> 0.002818 | F14: =C14*E14 -> 0.0033816
A15: 11 | B15: Tandori Masala Powder | C15: 1.2 | D15: =IFERROR(INDEX(LIST!$F$2:$F$131,MATCH(B15,LIST!$B$2:$B$131,0)),"") -> g | E15: =IFERROR(INDEX(LIST!$G$2:$G$131,MATCH(B15,LIST!$B$2:$B$131,0)),0) -> 0.004 | F15: =C15*E15 -> 0.0048
A16: 12 | B16: Mix Masala Powder | C16: 1.2 | D16: =IFERROR(INDEX(LIST!$F$2:$F$131,MATCH(B16,LIST!$B$2:$B$131,0)),"") -> g | E16: =IFERROR(INDEX(LIST!$G$2:$G$131,MATCH(B16,LIST!$B$2:$B$131,0)),0) -> 0.00165 | F16: =C16*E16 -> 0.00198
... A18: 14 | B18: Salt | C18: 1.2 | D18: =IFERROR(INDEX(LIST!$F$2:$F$131,MATCH(B18,LIST!$B$2:$B$131,0)),"") -> g | E18: =IFERROR(INDEX(LIST!$G$2:$G$131,MATCH(B18,LIST!$B$2:$B$131,0)),0) -> 0.000165 | F18: =C18*E18 -> 0.000198
B19: TOTAL RECIPE COST | F19: =SUM(F5:F18) -> 0.21453915
B21: Size | C21: Small | D21: Medium | E21: Large
B22: Recipes per container | C22: 1 | D22: 2 | E22: 4
B23: Ingredient cost | C23: =$F$19*C22 -> 0.21453915 | D23: =$F$19*D22 -> 0.42907829 | E23: =$F$19*E22 -> 0.85815658
B24: Container | C24: CONTENER NO : (3) | D24: CONTENER NO : (4) | E24: CONTENER NO : (5)
B25: Container cost | C25: =IFERROR(INDEX(LIST!$G$2:$G$131,MATCH(C24,LIST!$B$2:$B$131,0)),0) -> 0.021 | D25: =IFERROR(INDEX(LIST!$G$2:$G$131,MATCH(D24,LIST!$B$2:$B$131,0)),0) -> 0.0315 | E25: =IFERROR(INDEX(LIST!$G$2:$G$131,MATCH(E24,LIST!$B$2:$B$131,0)),0) -> 0.11666667
B26: Spoons (qty) | C26: 1.45 | D26: 4.5 | E26: 6
B27: Spoon cost | C27: =C26*IFERROR(INDEX(LIST!$G$2:$G$131,MATCH("SPOON",LIST!$B$2:$B$131,0)),0) -> 0.00928 | D27: =D26*IFERROR(INDEX(LIST!$G$2:$G$131,MATCH("SPOON",LIST!$B$2:$B$131,0)),0) -> 0.0288 | E27: =E26*IFERROR(INDEX(LIST!$G$2:$G$131,MATCH("SPOON",LIST!$B$2:$B$131,0)),0) -> 0.0384
B28: Bread (qty) | C28: 1 | D28: 2 | E28: 4
B29: Bread cost | C29: =C28*IFERROR(INDEX(LIST!$G$2:$G$131,MATCH("Bread",LIST!$B$2:$B$131,0)),0) -> 0.012 | D29: =D28*IFERROR(INDEX(LIST!$G$2:$G$131,MATCH("Bread",LIST!$B$2:$B$131,0)),0) -> 0.024 | E29: =E28*IFERROR(INDEX(LIST!$G$2:$G$131,MATCH("Bread",LIST!$B$2:$B$131,0)),0) -> 0.048
B30: Bag | C30: Bag Small | D30: Bag Medium | E30: Bag Large
B31: Bag cost | C31: =IFERROR(INDEX(LIST!$G$2:$G$131,MATCH(C30,LIST!$B$2:$B$131,0)),0) -> 0.02 | D31: =IFERROR(INDEX(LIST!$G$2:$G$131,MATCH(D30,LIST!$B$2:$B$131,0)),0) -> 0.03 | E31: =IFERROR(INDEX(LIST!$G$2:$G$131,MATCH(E30,LIST!$B$2:$B$131,0)),0) -> 0.04
B32: Other costs | C32: 0 | D32: 0 | E32: 0
B33: Packaging total | C33: =C25+C27+C29+C31+C32 -> 0.06228 | D33: =D25+D27+D29+D31+D32 -> 0.1143 | E33: =E25+E27+E29+E31+E32 -> 0.24306667
B34: TOTAL COST | C34: =C23+C33 -> 0.27681915 | D34: =D23+D33 -> 0.54337829 | E34: =E23+E33 -> 1.1012232
B35: Store price | C35: 1.4 | D35: 2.6 | E35: 5
B36: Store cost % | C36: =IF(C35=0,"",C34/C35) -> 0.19772796 | D36: =IF(D35=0,"",D34/D35) -> 0.20899165 | E36: =IF(E35=0,"",E34/E35) -> 0.22024465
B37: Delivery price | C37: 1.85 | D37: 3.2 | E37: 6
B38: Delivery cost % | C38: =IF(N(C37)=0,"",C34/C37) -> 0.14963197 | D38: =IF(N(D37)=0,"",D34/D37) -> 0.16980572 | E38: =IF(N(E37)=0,"",E34/E37) -> 0.18353721
B39: Store profit | C39: =C35-C34 -> 1.1231809 | D39: =D35-D34 -> 2.0566217 | E39: =E35-E34 -> 3.8987768
B40: Delivery profit | C40: =IF(N(C37)=0,"",C37-C34) -> 1.5731809 | D40: =IF(N(D37)=0,"",D37-D34) -> 2.6566217 | E40: =IF(N(E37)=0,"",E37-E34) -> 4.8987768

Sheet Egg Cheese
A1: Egg Cheese
A2: Eggs & fool · one container takes several recipes · target 30%
A4: # | B4: Item | C4: Qty | D4: Unit | E4: Unit price | F4: Cost
A5: 1 | B5: Egg | C5: 4 | D5: =IFERROR(INDEX(LIST!$F$2:$F$131,MATCH(B5,LIST!$B$2:$B$131,0)),"") -> pc | E5: =IFERROR(INDEX(LIST!$G$2:$G$131,MATCH(B5,LIST!$B$2:$B$131,0)),0) -> 0.035 | F5: =C5*E5 -> 0.14
A6: 2 | B6: Cheddar Cheese | C6: 60 | D6: =IFERROR(INDEX(LIST!$F$2:$F$131,MATCH(B6,LIST!$B$2:$B$131,0)),"") -> g | E6: =IFERROR(INDEX(LIST!$G$2:$G$131,MATCH(B6,LIST!$B$2:$B$131,0)),0) -> 0.0021764706 | F6: =C6*E6 -> 0.13058824
A7: 3 | B7: Vegetable Oil | C7: 15 | D7: =IFERROR(INDEX(LIST!$F$2:$F$131,MATCH(B7,LIST!$B$2:$B$131,0)),"") -> ml | E7: =IFERROR(INDEX(LIST!$G$2:$G$131,MATCH(B7,LIST!$B$2:$B$131,0)),0) -> 0.000594 | F7: =C7*E7 -> 0.00891
B8: TOTAL RECIPE COST | F8: =SUM(F5:F7) -> 0.27949824
B10: Size | C10: Small | D10: Medium | E10: Large
B11: Recipes per container | C11: 1 | D11: 2 | E11: 4
B12: Ingredient cost | C12: =$F$8*C11 -> 0.27949824 | D12: =$F$8*D11 -> 0.55899647 | E12: =$F$8*E11 -> 1.1179929
B13: Container | C13: CONTENER NO : (3) | D13: CONTENER NO : (4) | E13: CONTENER NO : (5)
B14: Container cost | C14: =IFERROR(INDEX(LIST!$G$2:$G$131,MATCH(C13,LIST!$B$2:$B$131,0)),0) -> 0.021 | D14: =IFERROR(INDEX(LIST!$G$2:$G$131,MATCH(D13,LIST!$B$2:$B$131,0)),0) -> 0.0315 | E14: =IFERROR(INDEX(LIST!$G$2:$G$131,MATCH(E13,LIST!$B$2:$B$131,0)),0) -> 0.11666667
B15: Spoons (qty) | C15: 1 | D15: 2 | E15: 3
B16: Spoon cost | C16: =C15*IFERROR(INDEX(LIST!$G$2:$G$131,MATCH("SPOON",LIST!$B$2:$B$131,0)),0) -> 0.0064 | D16: =D15*IFERROR(INDEX(LIST!$G$2:$G$131,MATCH("SPOON",LIST!$B$2:$B$131,0)),0) -> 0.0128 | E16: =E15*IFERROR(INDEX(LIST!$G$2:$G$131,MATCH("SPOON",LIST!$B$2:$B$131,0)),0) -> 0.0192
B17: Bread (qty) | C17: 1 | D17: 2 | E17: 4
B18: Bread cost | C18: =C17*IFERROR(INDEX(LIST!$G$2:$G$131,MATCH("Bread",LIST!$B$2:$B$131,0)),0) -> 0.012 | D18: =D17*IFERROR(INDEX(LIST!$G$2:$G$131,MATCH("Bread",LIST!$B$2:$B$131,0)),0) -> 0.024 | E18: =E17*IFERROR(INDEX(LIST!$G$2:$G$131,MATCH("Bread",LIST!$B$2:$B$131,0)),0) -> 0.048
B19: Bag | C19: Bag Small | D19: Bag Medium | E19: Bag Large
B20: Bag cost | C20: =IFERROR(INDEX(LIST!$G$2:$G$131,MATCH(C19,LIST!$B$2:$B$131,0)),0) -> 0.02 | D20: =IFERROR(INDEX(LIST!$G$2:$G$131,MATCH(D19,LIST!$B$2:$B$131,0)),0) -> 0.03 | E20: =IFERROR(INDEX(LIST!$G$2:$G$131,MATCH(E19,LIST!$B$2:$B$131,0)),0) -> 0.04
B21: Other costs | C21: 0 | D21: 0 | E21: 0
B22: Packaging total | C22: =C14+C16+C18+C20+C21 -> 0.0594 | D22: =D14+D16+D18+D20+D21 -> 0.0983 | E22: =E14+E16+E18+E20+E21 -> 0.22386667
B23: TOTAL COST | C23: =C12+C22 -> 0.33889824 | D23: =D12+D22 -> 0.65729647 | E23: =E12+E22 -> 1.3418596
B24: Store price | C24: 1.3 | D24: 2.4 | E24: 4.6
B25: Store cost % | C25: =IF(C24=0,"",C23/C24) -> 0.26069095 | D25: =IF(D24=0,"",D23/D24) -> 0.27387353 | E25: =IF(E24=0,"",E23/E24) -> 0.29170861
B26: Delivery price | C26: 1.7 | D26: 3 | E26: 5.6
B27: Delivery cost % | C27: =IF(N(C26)=0,"",C23/C26) -> 0.1993519 | D27: =IF(N(D26)=0,"",D23/D26) -> 0.21909882 | E27: =IF(N(E26)=0,"",E23/E26) -> 0.23961779
B28: Store profit | C28: =C24-C23 -> 0.96110176 | D28: =D24-D23 -> 1.7427035 | E28: =E24-E23 -> 3.2581404
B29: Delivery profit | C29: =IF(N(C26)=0,"",C26-C23) -> 1.3611018 | D29: =IF(N(D26)=0,"",D26-D23) -> 2.3427035 | E29: =IF(N(E26)=0,"",E26-E23) -> 4.2581404

Sheet Egg Fried
A1: Egg Fried
A2: Eggs & fool · one container takes several recipes · target 30%
A4: # | B4: Item | C4: Qty | D4: Unit | E4: Unit price | F4: Cost
A5: 1 | B5: Egg | C5: 4 | D5: =IFERROR(INDEX(LIST!$F$2:$F$131,MATCH(B5,LIST!$B$2:$B$131,0)),"") -> pc | E5: =IFERROR(INDEX(LIST!$G$2:$G$131,MATCH(B5,LIST!$B$2:$B$131,0)),0) -> 0.035 | F5: =C5*E5 -> 0.14
A6: 2 | B6: Vegetable Oil | C6: 30 | D6: =IFERROR(INDEX(LIST!$F$2:$F$131,MATCH(B6,LIST!$B$2:$B$131,0)),"") -> ml | E6: =IFERROR(INDEX(LIST!$G$2:$G$131,MATCH(B6,LIST!$B$2:$B$131,0)),0) -> 0.000594 | F6: =C6*E6 -> 0.01782
B7: TOTAL RECIPE COST | F7: =SUM(F5:F6) -> 0.15782
B9: Size | C9: Small | D9: Medium | E9: Large
B10: Recipes per container | C10: 1 | D10: 2 | E10: 4
B11: Ingredient cost | C11: =$F$7*C10 -> 0.15782 | D11: =$F$7*D10 -> 0.31564 | E11: =$F$7*E10 -> 0.63128
B12: Container | C12: CONTENER NO : (3) | D12: CONTENER NO : (4) | E12: CONTENER NO : (5)
B13: Container cost | C13: =IFERROR(INDEX(LIST!$G$2:$G$131,MATCH(C12,LIST!$B$2:$B$131,0)),0) -> 0.021 | D13: =IFERROR(INDEX(LIST!$G$2:$G$131,MATCH(D12,LIST!$B$2:$B$131,0)),0) -> 0.0315 | E13: =IFERROR(INDEX(LIST!$G$2:$G$131,MATCH(E12,LIST!$B$2:$B$131,0)),0) -> 0.11666667
B14: Spoons (qty) | C14: 1 | D14: 2 | E14: 3
B15: Spoon cost | C15: =C14*IFERROR(INDEX(LIST!$G$2:$G$131,MATCH("SPOON",LIST!$B$2:$B$131,0)),0) -> 0.0064 | D15: =D14*IFERROR(INDEX(LIST!$G$2:$G$131,MATCH("SPOON",LIST!$B$2:$B$131,0)),0) -> 0.0128 | E15: =E14*IFERROR(INDEX(LIST!$G$2:$G$131,MATCH("SPOON",LIST!$B$2:$B$131,0)),0) -> 0.0192
B16: Bread (qty) | C16: 1 | D16: 2 | E16: 4
B17: Bread cost | C17: =C16*IFERROR(INDEX(LIST!$G$2:$G$131,MATCH("Bread",LIST!$B$2:$B$131,0)),0) -> 0.012 | D17: =D16*IFERROR(INDEX(LIST!$G$2:$G$131,MATCH("Bread",LIST!$B$2:$B$131,0)),0) -> 0.024 | E17: =E16*IFERROR(INDEX(LIST!$G$2:$G$131,MATCH("Bread",LIST!$B$2:$B$131,0)),0) -> 0.048
B18: Bag | C18: Bag Small | D18: Bag Medium | E18: Bag Large
B19: Bag cost | C19: =IFERROR(INDEX(LIST!$G$2:$G$131,MATCH(C18,LIST!$B$2:$B$131,0)),0) -> 0.02 | D19: =IFERROR(INDEX(LIST!$G$2:$G$131,MATCH(D18,LIST!$B$2:$B$131,0)),0) -> 0.03 | E19: =IFERROR(INDEX(LIST!$G$2:$G$131,MATCH(E18,LIST!$B$2:$B$131,0)),0) -> 0.04
B20: Other costs | C20: 0 | D20: 0 | E20: 0
B21: Packaging total | C21: =C13+C15+C17+C19+C20 -> 0.0594 | D21: =D13+D15+D17+D19+D20 -> 0.0983 | E21: =E13+E15+E17+E19+E20 -> 0.22386667
B22: TOTAL COST | C22: =C11+C21 -> 0.21722 | D22: =D11+D21 -> 0.41394 | E22: =E11+E21 -> 0.85514667
B23: Store price | C23: 0.9 | D23: 1.7 | E23: 3.3
B24: Store cost % | C24: =IF(C23=0,"",C22/C23) -> 0.24135556 | D24: =IF(D23=0,"",D22/D23) -> 0.24349412 | E24: =IF(E23=0,"",E22/E23) -> 0.25913535
B25: Delivery price | C25: 1.2 | D25: 2.2 | E25: 3.8
B26: Delivery cost % | C26: =IF(N(C25)=0,"",C22/C25) -> 0.18101667 | D26: =IF(N(D25)=0,"",D22/D25) -> 0.18815455 | E26: =IF(N(E25)=0,"",E22/E25) -> 0.2250386
B27: Store profit | C27: =C23-C22 -> 0.68278 | D27: =D23-D22 -> 1.28606 | E27: =E23-E22 -> 2.4448533
B28: Delivery profit | C28: =IF(N(C25)=0,"",C25-C22) -> 0.98278 | D28: =IF(N(D25)=0,"",D25-D22) -> 1.78606 | E28: =IF(N(E25)=0,"",E25-E22) -> 2.9448533

Sheet Egg Eyoon
A1: Egg Eyoon
A2: Eggs & fool · one container takes several recipes · target 30%
A4: # | B4: Item | C4: Qty | D4: Unit | E4: Unit price | F4: Cost
A5: 1 | B5: Egg | C5: 4 | D5: =IFERROR(INDEX(LIST!$F$2:$F$131,MATCH(B5,LIST!$B$2:$B$131,0)),"") -> pc | E5: =IFERROR(INDEX(LIST!$G$2:$G$131,MATCH(B5,LIST!$B$2:$B$131,0)),0) -> 0.035 | F5: =C5*E5 -> 0.14
A6: 2 | B6: Vegetable Oil | C6: 30 | D6: =IFERROR(INDEX(LIST!$F$2:$F$131,MATCH(B6,LIST!$B$2:$B$131,0)),"") -> ml | E6: =IFERROR(INDEX(LIST!$G$2:$G$131,MATCH(B6,LIST!$B$2:$B$131,0)),0) -> 0.000594 | F6: =C6*E6 -> 0.01782
B7: TOTAL RECIPE COST | F7: =SUM(F5:F6) -> 0.15782
B9: Size | C9: Small | D9: Medium | E9: Large
B10: Recipes per container | C10: 1 | D10: 2 | E10: 4
B11: Ingredient cost | C11: =$F$7*C10 -> 0.15782 | D11: =$F$7*D10 -> 0.31564 | E11: =$F$7*E10 -> 0.63128
B12: Container | C12: CONTENER NO : (3) | D12: CONTENER NO : (4) | E12: CONTENER NO : (5)
B13: Container cost | C13: =IFERROR(INDEX(LIST!$G$2:$G$131,MATCH(C12,LIST!$B$2:$B$131,0)),0) -> 0.021 | D13: =IFERROR(INDEX(LIST!$G$2:$G$131,MATCH(D12,LIST!$B$2:$B$131,0)),0) -> 0.0315 | E13: =IFERROR(INDEX(LIST!$G$2:$G$131,MATCH(E12,LIST!$B$2:$B$131,0)),0) -> 0.11666667
B14: Spoons (qty) | C14: 1 | D14: 2 | E14: 3
B15: Spoon cost | C15: =C14*IFERROR(INDEX(LIST!$G$2:$G$131,MATCH("SPOON",LIST!$B$2:$B$131,0)),0) -> 0.0064 | D15: =D14*IFERROR(INDEX(LIST!$G$2:$G$131,MATCH("SPOON",LIST!$B$2:$B$131,0)),0) -> 0.0128 | E15: =E14*IFERROR(INDEX(LIST!$G$2:$G$131,MATCH("SPOON",LIST!$B$2:$B$131,0)),0) -> 0.0192
B16: Bread (qty) | C16: 1 | D16: 2 | E16: 4
B17: Bread cost | C17: =C16*IFERROR(INDEX(LIST!$G$2:$G$131,MATCH("Bread",LIST!$B$2:$B$131,0)),0) -> 0.012 | D17: =D16*IFERROR(INDEX(LIST!$G$2:$G$131,MATCH("Bread",LIST!$B$2:$B$131,0)),0) -> 0.024 | E17: =E16*IFERROR(INDEX(LIST!$G$2:$G$131,MATCH("Bread",LIST!$B$2:$B$131,0)),0) -> 0.048
B18: Bag | C18: Bag Small | D18: Bag Medium | E18: Bag Large
B19: Bag cost | C19: =IFERROR(INDEX(LIST!$G$2:$G$131,MATCH(C18,LIST!$B$2:$B$131,0)),0) -> 0.02 | D19: =IFERROR(INDEX(LIST!$G$2:$G$131,MATCH(D18,LIST!$B$2:$B$131,0)),0) -> 0.03 | E19: =IFERROR(INDEX(LIST!$G$2:$G$131,MATCH(E18,LIST!$B$2:$B$131,0)),0) -> 0.04
B20: Other costs | C20: 0 | D20: 0 | E20: 0
B21: Packaging total | C21: =C13+C15+C17+C19+C20 -> 0.0594 | D21: =D13+D15+D17+D19+D20 -> 0.0983 | E21: =E13+E15+E17+E19+E20 -> 0.22386667
B22: TOTAL COST | C22: =C11+C21 -> 0.21722 | D22: =D11+D21 -> 0.41394 | E22: =E11+E21 -> 0.85514667
B23: Store price | C23: 0.9 | D23: 1.7 | E23: 3.3
B24: Store cost % | C24: =IF(C23=0,"",C22/C23) -> 0.24135556 | D24: =IF(D23=0,"",D22/D23) -> 0.24349412 | E24: =IF(E23=0,"",E22/E23) -> 0.25913535
B25: Delivery price | C25: 1.2 | D25: 2.2 | E25: 3.8
B26: Delivery cost % | C26: =IF(N(C25)=0,"",C22/C25) -> 0.18101667 | D26: =IF(N(D25)=0,"",D22/D25) -> 0.18815455 | E26: =IF(N(E25)=0,"",E22/E25) -> 0.2250386
B27: Store profit | C27: =C23-C22 -> 0.68278 | D27: =D23-D22 -> 1.28606 | E27: =E23-E22 -> 2.4448533
B28: Delivery profit | C28: =IF(N(C25)=0,"",C25-C22) -> 0.98278 | D28: =IF(N(D25)=0,"",D25-D22) -> 1.78606 | E28: =IF(N(E25)=0,"",E25-E22) -> 2.9448533

Sheet Egg & Fasolya
A1: Egg & Fasolya
A2: Eggs & fool · one container takes several recipes · target 30%
A4: # | B4: Item | C4: Qty | D4: Unit | E4: Unit price | F4: Cost
A5: 1 | B5: Baked Beans | C5: 190 | D5: =IFERROR(INDEX(LIST!$F$2:$F$131,MATCH(B5,LIST!$B$2:$B$131,0)),"") -> g | E5: =IFERROR(INDEX(LIST!$G$2:$G$131,MATCH(B5,LIST!$B$2:$B$131,0)),0) -> 0.00094736842 | F5: =C5*E5 -> 0.18
A6: 2 | B6: Egg | C6: 2 | D6: =IFERROR(INDEX(LIST!$F$2:$F$131,MATCH(B6,LIST!$B$2:$B$131,0)),"") -> pc | E6: =IFERROR(INDEX(LIST!$G$2:$G$131,MATCH(B6,LIST!$B$2:$B$131,0)),0) -> 0.035 | F6: =C6*E6 -> 0.07
A7: 3 | B7: Cheddar Cheese | C7: 10 | D7: =IFERROR(INDEX(LIST!$F$2:$F$131,MATCH(B7,LIST!$B$2:$B$131,0)),"") -> g | E7: =IFERROR(INDEX(LIST!$G$2:$G$131,MATCH(B7,LIST!$B$2:$B$131,0)),0) -> 0.0021764706 | F7: =C7*E7 -> 0.021764706
A8: 4 | B8: Tahina | C8: 15 | D8: =IFERROR(INDEX(LIST!$F$2:$F$131,MATCH(B8,LIST!$B$2:$B$131,0)),"") -> g | E8: =IFERROR(INDEX(LIST!$G$2:$G$131,MATCH(B8,LIST!$B$2:$B$131,0)),0) -> 0.0009696 | F8: =C8*E8 -> 0.014544
A9: 5 | B9: Vegetable Oil | C9: 30 | D9: =IFERROR(INDEX(LIST!$F$2:$F$131,MATCH(B9,LIST!$B$2:$B$131,0)),"") -> ml | E9: =IFERROR(INDEX(LIST!$G$2:$G$131,MATCH(B9,LIST!$B$2:$B$131,0)),0) -> 0.000594 | F9: =C9*E9 -> 0.01782
A10: 6 | B10: Onion | C10: 60 | D10: =IFERROR(INDEX(LIST!$F$2:$F$131,MATCH(B10,LIST!$B$2:$B$131,0)),"") -> g | E10: =IFERROR(INDEX(LIST!$G$2:$G$131,MATCH(B10,LIST!$B$2:$B$131,0)),0) -> 0.00045 | F10: =C10*E10 -> 0.027
A11: 7 | B11: Tomato | C11: 120 | D11: =IFERROR(INDEX(LIST!$F$2:$F$131,MATCH(B11,LIST!$B$2:$B$131,0)),"") -> g | E11: =IFERROR(INDEX(LIST!$G$2:$G$131,MATCH(B11,LIST!$B$2:$B$131,0)),0) -> 0.0005 | F11: =C11*E11 -> 0.06
A12: 8 | B12: Coriander Leaves | C12: 1 | D12: =IFERROR(INDEX(LIST!$F$2:$F$131,MATCH(B12,LIST!$B$2:$B$131,0)),"") -> g | E12: =IFERROR(INDEX(LIST!$G$2:$G$131,MATCH(B12,LIST!$B$2:$B$131,0)),0) -> 0.0017272727 | F12: =C12*E12 -> 0.0017272727
A13: 9 | B13: Green Capiscum | C13: 10 | D13: =IFERROR(INDEX(LIST!$F$2:$F$131,MATCH(B13,LIST!$B$2:$B$131,0)),"") -> g | E13: =IFERROR(INDEX(LIST!$G$2:$G$131,MATCH(B13,LIST!$B$2:$B$131,0)),0) -> 0.00065 | F13: =C13*E13 -> 0.0065
A14: 10 | B14: Mix Masala Powder | C14: 1.25 | D14: =IFERROR(INDEX(LIST!$F$2:$F$131,MATCH(B14,LIST!$B$2:$B$131,0)),"") -> g | E14: =IFERROR(INDEX(LIST!$G$2:$G$131,MATCH(B14,LIST!$B$2:$B$131,0)),0) -> 0.00165 | F14: =C14*E14 -> 0.0020625
A15: 11 | B15: Turmeric Powder | C15: 1.25 | D15: =IFERROR(INDEX(LIST!$F$2:$F$131,MATCH(B15,LIST!$B$2:$B$131,0)),"") -> g | E15: =IFERROR(INDEX(LIST!$G$2:$G$131,MATCH(B15,LIST!$B$2:$B$131,0)),0) -> 0.0018 | F15: =C15*E15 -> 0.00225
A16: 12 | B16: Cummin Powder | C16: 1.25 | D16: =IFERROR(INDEX(LIST!$F$2:$F$131,MATCH(B16,LIST!$B$2:$B$131,0)),"") -> g | E16: =IFERROR(INDEX(LIST!$G$2:$G$131,MATCH(B16,LIST!$B$2:$B$131,0)),0) -> 0.002818 | F16: =C16*E16 -> 0.0035225
... A19: 15 | B19: Salt | C19: 2.5 | D19: =IFERROR(INDEX(LIST!$F$2:$F$131,MATCH(B19,LIST!$B$2:$B$131,0)),"") -> g | E19: =IFERROR(INDEX(LIST!$G$2:$G$131,MATCH(B19,LIST!$B$2:$B$131,0)),0) -> 0.000165 | F19: =C19*E19 -> 0.0004125
B20: TOTAL RECIPE COST | F20: =SUM(F5:F19) -> 0.41966598
B22: Size | C22: Small | D22: Medium | E22: Large
B23: Recipes per container | C23: 1 | D23: 2 | E23: 4
B24: Ingredient cost | C24: =$F$20*C23 -> 0.41966598 | D24: =$F$20*D23 -> 0.83933196 | E24: =$F$20*E23 -> 1.6786639
B25: Container | C25: CONTENER NO : (3) | D25: CONTENER NO : (4) | E25: CONTENER NO : (5)
B26: Container cost | C26: =IFERROR(INDEX(LIST!$G$2:$G$131,MATCH(C25,LIST!$B$2:$B$131,0)),0) -> 0.021 | D26: =IFERROR(INDEX(LIST!$G$2:$G$131,MATCH(D25,LIST!$B$2:$B$131,0)),0) -> 0.0315 | E26: =IFERROR(INDEX(LIST!$G$2:$G$131,MATCH(E25,LIST!$B$2:$B$131,0)),0) -> 0.11666667
B27: Spoons (qty) | C27: 1 | D27: 2 | E27: 3
B28: Spoon cost | C28: =C27*IFERROR(INDEX(LIST!$G$2:$G$131,MATCH("SPOON",LIST!$B$2:$B$131,0)),0) -> 0.0064 | D28: =D27*IFERROR(INDEX(LIST!$G$2:$G$131,MATCH("SPOON",LIST!$B$2:$B$131,0)),0) -> 0.0128 | E28: =E27*IFERROR(INDEX(LIST!$G$2:$G$131,MATCH("SPOON",LIST!$B$2:$B$131,0)),0) -> 0.0192
B29: Bread (qty) | C29: 1 | D29: 2 | E29: 4
B30: Bread cost | C30: =C29*IFERROR(INDEX(LIST!$G$2:$G$131,MATCH("Bread",LIST!$B$2:$B$131,0)),0) -> 0.012 | D30: =D29*IFERROR(INDEX(LIST!$G$2:$G$131,MATCH("Bread",LIST!$B$2:$B$131,0)),0) -> 0.024 | E30: =E29*IFERROR(INDEX(LIST!$G$2:$G$131,MATCH("Bread",LIST!$B$2:$B$131,0)),0) -> 0.048
B31: Bag | C31: Bag Small | D31: Bag Medium | E31: Bag Large
B32: Bag cost | C32: =IFERROR(INDEX(LIST!$G$2:$G$131,MATCH(C31,LIST!$B$2:$B$131,0)),0) -> 0.02 | D32: =IFERROR(INDEX(LIST!$G$2:$G$131,MATCH(D31,LIST!$B$2:$B$131,0)),0) -> 0.03 | E32: =IFERROR(INDEX(LIST!$G$2:$G$131,MATCH(E31,LIST!$B$2:$B$131,0)),0) -> 0.04
B33: Other costs | C33: 0 | D33: 0 | E33: 0
B34: Packaging total | C34: =C26+C28+C30+C32+C33 -> 0.0594 | D34: =D26+D28+D30+D32+D33 -> 0.0983 | E34: =E26+E28+E30+E32+E33 -> 0.22386667
B35: TOTAL COST | C35: =C24+C34 -> 0.47906598 | D35: =D24+D34 -> 0.93763196 | E35: =E24+E34 -> 1.9025306
B36: Store price | C36: 1.6 | D36: 3 | E36: 5.6
B37: Store cost % | C37: =IF(C36=0,"",C35/C36) -> 0.29941624 | D37: =IF(D36=0,"",D35/D36) -> 0.31254399 | E37: =IF(E36=0,"",E35/E36) -> 0.3397376
B38: Delivery price | C38: 2 | D38: 3.6 | E38: 6.8
B39: Delivery cost % | C39: =IF(N(C38)=0,"",C35/C38) -> 0.23953299 | D39: =IF(N(D38)=0,"",D35/D38) -> 0.26045332 | E39: =IF(N(E38)=0,"",E35/E38) -> 0.27978391
B40: Store profit | C40: =C36-C35 -> 1.120934 | D40: =D36-D35 -> 2.062368 | E40: =E36-E35 -> 3.6974694
B41: Delivery profit | C41: =IF(N(C38)=0,"",C38-C35) -> 1.520934 | D41: =IF(N(D38)=0,"",D38-D35) -> 2.662368 | E41: =IF(N(E38)=0,"",E38-E35) -> 4.8974694

Sheet Egg & Tomato
A1: Egg & Tomato
A2: Eggs & fool · one container takes several recipes · target 30%
A4: # | B4: Item | C4: Qty | D4: Unit | E4: Unit price | F4: Cost
A5: 1 | B5: Egg | C5: 2 | D5: =IFERROR(INDEX(LIST!$F$2:$F$131,MATCH(B5,LIST!$B$2:$B$131,0)),"") -> pc | E5: =IFERROR(INDEX(LIST!$G$2:$G$131,MATCH(B5,LIST!$B$2:$B$131,0)),0) -> 0.035 | F5: =C5*E5 -> 0.07
A6: 2 | B6: Vegetable Oil | C6: 30 | D6: =IFERROR(INDEX(LIST!$F$2:$F$131,MATCH(B6,LIST!$B$2:$B$131,0)),"") -> ml | E6: =IFERROR(INDEX(LIST!$G$2:$G$131,MATCH(B6,LIST!$B$2:$B$131,0)),0) -> 0.000594 | F6: =C6*E6 -> 0.01782
A7: 3 | B7: Tomato Paste | C7: 15 | D7: =IFERROR(INDEX(LIST!$F$2:$F$131,MATCH(B7,LIST!$B$2:$B$131,0)),"") -> g | E7: =IFERROR(INDEX(LIST!$G$2:$G$131,MATCH(B7,LIST!$B$2:$B$131,0)),0) -> 0.0006 | F7: =C7*E7 -> 0.009
A8: 4 | B8: Tomato | C8: 240 | D8: =IFERROR(INDEX(LIST!$F$2:$F$131,MATCH(B8,LIST!$B$2:$B$131,0)),"") -> g | E8: =IFERROR(INDEX(LIST!$G$2:$G$131,MATCH(B8,LIST!$B$2:$B$131,0)),0) -> 0.0005 | F8: =C8*E8 -> 0.12
A9: 5 | B9: Mix Masala Powder | C9: 1.25 | D9: =IFERROR(INDEX(LIST!$F$2:$F$131,MATCH(B9,LIST!$B$2:$B$131,0)),"") -> g | E9: =IFERROR(INDEX(LIST!$G$2:$G$131,MATCH(B9,LIST!$B$2:$B$131,0)),0) -> 0.00165 | F9: =C9*E9 -> 0.0020625
A10: 6 | B10: Cummin Powder | C10: 1.25 | D10: =IFERROR(INDEX(LIST!$F$2:$F$131,MATCH(B10,LIST!$B$2:$B$131,0)),"") -> g | E10: =IFERROR(INDEX(LIST!$G$2:$G$131,MATCH(B10,LIST!$B$2:$B$131,0)),0) -> 0.002818 | F10: =C10*E10 -> 0.0035225
A11: 7 | B11: Tandori Masala Powder | C11: 1.25 | D11: =IFERROR(INDEX(LIST!$F$2:$F$131,MATCH(B11,LIST!$B$2:$B$131,0)),"") -> g | E11: =IFERROR(INDEX(LIST!$G$2:$G$131,MATCH(B11,LIST!$B$2:$B$131,0)),0) -> 0.004 | F11: =C11*E11 -> 0.005
A12: 8 | B12: Black Pepper Powder | C12: 1.25 | D12: =IFERROR(INDEX(LIST!$F$2:$F$131,MATCH(B12,LIST!$B$2:$B$131,0)),"") -> g | E12: =IFERROR(INDEX(LIST!$G$2:$G$131,MATCH(B12,LIST!$B$2:$B$131,0)),0) -> 0.002272 | F12: =C12*E12 -> 0.00284
A13: 9 | B13: Salt | C13: 2.5 | D13: =IFERROR(INDEX(LIST!$F$2:$F$131,MATCH(B13,LIST!$B$2:$B$131,0)),"") -> g | E13: =IFERROR(INDEX(LIST!$G$2:$G$131,MATCH(B13,LIST!$B$2:$B$131,0)),0) -> 0.000165 | F13: =C13*E13 -> 0.0004125
B14: TOTAL RECIPE COST | F14: =SUM(F5:F13) -> 0.2306575
B16: Size | C16: Small | D16: Medium | E16: Large
B17: Recipes per container | C17: 1 | D17: 2 | E17: 4
B18: Ingredient cost | C18: =$F$14*C17 -> 0.2306575 | D18: =$F$14*D17 -> 0.461315 | E18: =$F$14*E17 -> 0.92263
B19: Container | C19: CONTENER NO : (3) | D19: CONTENER NO : (4) | E19: CONTENER NO : (5)
B20: Container cost | C20: =IFERROR(INDEX(LIST!$G$2:$G$131,MATCH(C19,LIST!$B$2:$B$131,0)),0) -> 0.021 | D20: =IFERROR(INDEX(LIST!$G$2:$G$131,MATCH(D19,LIST!$B$2:$B$131,0)),0) -> 0.0315 | E20: =IFERROR(INDEX(LIST!$G$2:$G$131,MATCH(E19,LIST!$B$2:$B$131,0)),0) -> 0.11666667
B21: Spoons (qty) | C21: 1 | D21: 2 | E21: 3
B22: Spoon cost | C22: =C21*IFERROR(INDEX(LIST!$G$2:$G$131,MATCH("SPOON",LIST!$B$2:$B$131,0)),0) -> 0.0064 | D22: =D21*IFERROR(INDEX(LIST!$G$2:$G$131,MATCH("SPOON",LIST!$B$2:$B$131,0)),0) -> 0.0128 | E22: =E21*IFERROR(INDEX(LIST!$G$2:$G$131,MATCH("SPOON",LIST!$B$2:$B$131,0)),0) -> 0.0192
B23: Bread (qty) | C23: 1 | D23: 2 | E23: 4
B24: Bread cost | C24: =C23*IFERROR(INDEX(LIST!$G$2:$G$131,MATCH("Bread",LIST!$B$2:$B$131,0)),0) -> 0.012 | D24: =D23*IFERROR(INDEX(LIST!$G$2:$G$131,MATCH("Bread",LIST!$B$2:$B$131,0)),0) -> 0.024 | E24: =E23*IFERROR(INDEX(LIST!$G$2:$G$131,MATCH("Bread",LIST!$B$2:$B$131,0)),0) -> 0.048
B25: Bag | C25: Bag Small | D25: Bag Medium | E25: Bag Large
B26: Bag cost | C26: =IFERROR(INDEX(LIST!$G$2:$G$131,MATCH(C25,LIST!$B$2:$B$131,0)),0) -> 0.02 | D26: =IFERROR(INDEX(LIST!$G$2:$G$131,MATCH(D25,LIST!$B$2:$B$131,0)),0) -> 0.03 | E26: =IFERROR(INDEX(LIST!$G$2:$G$131,MATCH(E25,LIST!$B$2:$B$131,0)),0) -> 0.04
B27: Other costs | C27: 0 | D27: 0 | E27: 0
B28: Packaging total | C28: =C20+C22+C24+C26+C27 -> 0.0594 | D28: =D20+D22+D24+D26+D27 -> 0.0983 | E28: =E20+E22+E24+E26+E27 -> 0.22386667
B29: TOTAL COST | C29: =C18+C28 -> 0.2900575 | D29: =D18+D28 -> 0.559615 | E29: =E18+E28 -> 1.1464967
B30: Store price | C30: 1.2 | D30: 2.2 | E30: 4.2
B31: Store cost % | C31: =IF(C30=0,"",C29/C30) -> 0.24171458 | D31: =IF(D30=0,"",D29/D30) -> 0.25437045 | E31: =IF(E30=0,"",E29/E30) -> 0.2729754
B32: Delivery price | C32: 1.6 | D32: 2.8 | E32: 5
B33: Delivery cost % | C33: =IF(N(C32)=0,"",C29/C32) -> 0.18128594 | D33: =IF(N(D32)=0,"",D29/D32) -> 0.1998625 | E33: =IF(N(E32)=0,"",E29/E32) -> 0.22929933
B34: Store profit | C34: =C30-C29 -> 0.9099425 | D34: =D30-D29 -> 1.640385 | E34: =E30-E29 -> 3.0535033
B35: Delivery profit | C35: =IF(N(C32)=0,"",C32-C29) -> 1.3099425 | D35: =IF(N(D32)=0,"",D32-D29) -> 2.240385 | E35: =IF(N(E32)=0,"",E32-E29) -> 3.8535033

Sheet Fool
A1: Fool
A2: Eggs & fool · one container takes several recipes · target 30%
A4: # | B4: Item | C4: Qty | D4: Unit | E4: Unit price | F4: Cost
A5: 1 | B5: Fool | C5: 190 | D5: =IFERROR(INDEX(LIST!$F$2:$F$131,MATCH(B5,LIST!$B$2:$B$131,0)),"") -> g | E5: =IFERROR(INDEX(LIST!$G$2:$G$131,MATCH(B5,LIST!$B$2:$B$131,0)),0) -> 0.0010177778 | F5: =C5*E5 -> 0.19337778
A6: 2 | B6: Cheddar Cheese | C6: 10 | D6: =IFERROR(INDEX(LIST!$F$2:$F$131,MATCH(B6,LIST!$B$2:$B$131,0)),"") -> g | E6: =IFERROR(INDEX(LIST!$G$2:$G$131,MATCH(B6,LIST!$B$2:$B$131,0)),0) -> 0.0021764706 | F6: =C6*E6 -> 0.021764706
A7: 3 | B7: Tahina | C7: 15 | D7: =IFERROR(INDEX(LIST!$F$2:$F$131,MATCH(B7,LIST!$B$2:$B$131,0)),"") -> g | E7: =IFERROR(INDEX(LIST!$G$2:$G$131,MATCH(B7,LIST!$B$2:$B$131,0)),0) -> 0.0009696 | F7: =C7*E7 -> 0.014544
A8: 4 | B8: Vegetable Oil | C8: 30 | D8: =IFERROR(INDEX(LIST!$F$2:$F$131,MATCH(B8,LIST!$B$2:$B$131,0)),"") -> ml | E8: =IFERROR(INDEX(LIST!$G$2:$G$131,MATCH(B8,LIST!$B$2:$B$131,0)),0) -> 0.000594 | F8: =C8*E8 -> 0.01782
A9: 5 | B9: Onion | C9: 60 | D9: =IFERROR(INDEX(LIST!$F$2:$F$131,MATCH(B9,LIST!$B$2:$B$131,0)),"") -> g | E9: =IFERROR(INDEX(LIST!$G$2:$G$131,MATCH(B9,LIST!$B$2:$B$131,0)),0) -> 0.00045 | F9: =C9*E9 -> 0.027
A10: 6 | B10: Tomato | C10: 120 | D10: =IFERROR(INDEX(LIST!$F$2:$F$131,MATCH(B10,LIST!$B$2:$B$131,0)),"") -> g | E10: =IFERROR(INDEX(LIST!$G$2:$G$131,MATCH(B10,LIST!$B$2:$B$131,0)),0) -> 0.0005 | F10: =C10*E10 -> 0.06
A11: 7 | B11: Coriander Leaves | C11: 1 | D11: =IFERROR(INDEX(LIST!$F$2:$F$131,MATCH(B11,LIST!$B$2:$B$131,0)),"") -> g | E11: =IFERROR(INDEX(LIST!$G$2:$G$131,MATCH(B11,LIST!$B$2:$B$131,0)),0) -> 0.0017272727 | F11: =C11*E11 -> 0.0017272727
A12: 8 | B12: Green Capiscum | C12: 10 | D12: =IFERROR(INDEX(LIST!$F$2:$F$131,MATCH(B12,LIST!$B$2:$B$131,0)),"") -> g | E12: =IFERROR(INDEX(LIST!$G$2:$G$131,MATCH(B12,LIST!$B$2:$B$131,0)),0) -> 0.00065 | F12: =C12*E12 -> 0.0065
A13: 9 | B13: Mix Masala Powder | C13: 1.25 | D13: =IFERROR(INDEX(LIST!$F$2:$F$131,MATCH(B13,LIST!$B$2:$B$131,0)),"") -> g | E13: =IFERROR(INDEX(LIST!$G$2:$G$131,MATCH(B13,LIST!$B$2:$B$131,0)),0) -> 0.00165 | F13: =C13*E13 -> 0.0020625
A14: 10 | B14: Turmeric Powder | C14: 1.25 | D14: =IFERROR(INDEX(LIST!$F$2:$F$131,MATCH(B14,LIST!$B$2:$B$131,0)),"") -> g | E14: =IFERROR(INDEX(LIST!$G$2:$G$131,MATCH(B14,LIST!$B$2:$B$131,0)),0) -> 0.0018 | F14: =C14*E14 -> 0.00225
A15: 11 | B15: Cummin Powder | C15: 1.25 | D15: =IFERROR(INDEX(LIST!$F$2:$F$131,MATCH(B15,LIST!$B$2:$B$131,0)),"") -> g | E15: =IFERROR(INDEX(LIST!$G$2:$G$131,MATCH(B15,LIST!$B$2:$B$131,0)),0) -> 0.002818 | F15: =C15*E15 -> 0.0035225
A16: 12 | B16: Tandori Masala Powder | C16: 2.5 | D16: =IFERROR(INDEX(LIST!$F$2:$F$131,MATCH(B16,LIST!$B$2:$B$131,0)),"") -> g | E16: =IFERROR(INDEX(LIST!$G$2:$G$131,MATCH(B16,LIST!$B$2:$B$131,0)),0) -> 0.004 | F16: =C16*E16 -> 0.01
... A18: 14 | B18: Salt | C18: 2.5 | D18: =IFERROR(INDEX(LIST!$F$2:$F$131,MATCH(B18,LIST!$B$2:$B$131,0)),"") -> g | E18: =IFERROR(INDEX(LIST!$G$2:$G$131,MATCH(B18,LIST!$B$2:$B$131,0)),0) -> 0.000165 | F18: =C18*E18 -> 0.0004125
B19: TOTAL RECIPE COST | F19: =SUM(F5:F18) -> 0.36304376
B21: Size | C21: Small | D21: Medium | E21: Large
B22: Recipes per container | C22: 1 | D22: 2 | E22: 4
B23: Ingredient cost | C23: =$F$19*C22 -> 0.36304376 | D23: =$F$19*D22 -> 0.72608751 | E23: =$F$19*E22 -> 1.452175
B24: Container | C24: CONTENER NO : (3) | D24: CONTENER NO : (4) | E24: CONTENER NO : (5)
B25: Container cost | C25: =IFERROR(INDEX(LIST!$G$2:$G$131,MATCH(C24,LIST!$B$2:$B$131,0)),0) -> 0.021 | D25: =IFERROR(INDEX(LIST!$G$2:$G$131,MATCH(D24,LIST!$B$2:$B$131,0)),0) -> 0.0315 | E25: =IFERROR(INDEX(LIST!$G$2:$G$131,MATCH(E24,LIST!$B$2:$B$131,0)),0) -> 0.11666667
B26: Spoons (qty) | C26: 1 | D26: 2 | E26: 3
B27: Spoon cost | C27: =C26*IFERROR(INDEX(LIST!$G$2:$G$131,MATCH("SPOON",LIST!$B$2:$B$131,0)),0) -> 0.0064 | D27: =D26*IFERROR(INDEX(LIST!$G$2:$G$131,MATCH("SPOON",LIST!$B$2:$B$131,0)),0) -> 0.0128 | E27: =E26*IFERROR(INDEX(LIST!$G$2:$G$131,MATCH("SPOON",LIST!$B$2:$B$131,0)),0) -> 0.0192
B28: Bread (qty) | C28: 1 | D28: 2 | E28: 4
B29: Bread cost | C29: =C28*IFERROR(INDEX(LIST!$G$2:$G$131,MATCH("Bread",LIST!$B$2:$B$131,0)),0) -> 0.012 | D29: =D28*IFERROR(INDEX(LIST!$G$2:$G$131,MATCH("Bread",LIST!$B$2:$B$131,0)),0) -> 0.024 | E29: =E28*IFERROR(INDEX(LIST!$G$2:$G$131,MATCH("Bread",LIST!$B$2:$B$131,0)),0) -> 0.048
B30: Bag | C30: Bag Small | D30: Bag Medium | E30: Bag Large
B31: Bag cost | C31: =IFERROR(INDEX(LIST!$G$2:$G$131,MATCH(C30,LIST!$B$2:$B$131,0)),0) -> 0.02 | D31: =IFERROR(INDEX(LIST!$G$2:$G$131,MATCH(D30,LIST!$B$2:$B$131,0)),0) -> 0.03 | E31: =IFERROR(INDEX(LIST!$G$2:$G$131,MATCH(E30,LIST!$B$2:$B$131,0)),0) -> 0.04
B32: Other costs | C32: 0 | D32: 0 | E32: 0
B33: Packaging total | C33: =C25+C27+C29+C31+C32 -> 0.0594 | D33: =D25+D27+D29+D31+D32 -> 0.0983 | E33: =E25+E27+E29+E31+E32 -> 0.22386667
B34: TOTAL COST | C34: =C23+C33 -> 0.42244376 | D34: =D23+D33 -> 0.82438751 | E34: =E23+E33 -> 1.6760417
B35: Store price | C35: 1.4 | D35: 2.6 | E35: 5
B36: Store cost % | C36: =IF(C35=0,"",C34/C35) -> 0.30174554 | D36: =IF(D35=0,"",D34/D35) -> 0.31707212 | E36: =IF(E35=0,"",E34/E35) -> 0.33520834
B37: Delivery price | C37: 1.7 | D37: 3 | E37: 5.6
B38: Delivery cost % | C38: =IF(N(C37)=0,"",C34/C37) -> 0.24849633 | D38: =IF(N(D37)=0,"",D34/D37) -> 0.27479584 | E38: =IF(N(E37)=0,"",E34/E37) -> 0.29929316
B39: Store profit | C39: =C35-C34 -> 0.97755624 | D39: =D35-D34 -> 1.7756125 | E39: =E35-E34 -> 3.3239583
B40: Delivery profit | C40: =IF(N(C37)=0,"",C37-C34) -> 1.2775562 | D40: =IF(N(D37)=0,"",D37-D34) -> 2.1756125 | E40: =IF(N(E37)=0,"",E37-E34) -> 3.9239583

Sheet Rice & Chicken
A1: Rice & Chicken
A2: Traditional · one recipe fills several containers · target 30%
A4: # | B4: Item | C4: Qty | D4: Unit | E4: Unit price | F4: Cost
A5: 1 | B5: Rice 1121 | C5: 1000 | D5: =IFERROR(INDEX(LIST!$F$2:$F$131,MATCH(B5,LIST!$B$2:$B$131,0)),"") -> g | E5: =IFERROR(INDEX(LIST!$G$2:$G$131,MATCH(B5,LIST!$B$2:$B$131,0)),0) -> 0.000575 | F5: =C5*E5 -> 0.575
A6: 2 | B6: Vegetable Oil | C6: 60 | D6: =IFERROR(INDEX(LIST!$F$2:$F$131,MATCH(B6,LIST!$B$2:$B$131,0)),"") -> ml | E6: =IFERROR(INDEX(LIST!$G$2:$G$131,MATCH(B6,LIST!$B$2:$B$131,0)),0) -> 0.000594 | F6: =C6*E6 -> 0.03564
A7: 3 | B7: Magi | C7: 1 | D7: =IFERROR(INDEX(LIST!$F$2:$F$131,MATCH(B7,LIST!$B$2:$B$131,0)),"") -> pc | E7: =IFERROR(INDEX(LIST!$G$2:$G$131,MATCH(B7,LIST!$B$2:$B$131,0)),0) -> 0.083 | F7: =C7*E7 -> 0.083
A8: 4 | B8: Salt | C8: 15 | D8: =IFERROR(INDEX(LIST!$F$2:$F$131,MATCH(B8,LIST!$B$2:$B$131,0)),"") -> g | E8: =IFERROR(INDEX(LIST!$G$2:$G$131,MATCH(B8,LIST!$B$2:$B$131,0)),0) -> 0.000165 | F8: =C8*E8 -> 0.002475
A9: 5 | B9: Raison | C9: 50 | D9: =IFERROR(INDEX(LIST!$F$2:$F$131,MATCH(B9,LIST!$B$2:$B$131,0)),"") -> g | E9: =IFERROR(INDEX(LIST!$G$2:$G$131,MATCH(B9,LIST!$B$2:$B$131,0)),0) -> 0.00175 | F9: =C9*E9 -> 0.0875
A10: 6 | B10: Food Colour Red | C10: 1 | D10: =IFERROR(INDEX(LIST!$F$2:$F$131,MATCH(B10,LIST!$B$2:$B$131,0)),"") -> g | E10: =IFERROR(INDEX(LIST!$G$2:$G$131,MATCH(B10,LIST!$B$2:$B$131,0)),0) -> 0.004 | F10: =C10*E10 -> 0.004
A11: 7 | B11: Food Colour Yellow | C11: 1 | D11: =IFERROR(INDEX(LIST!$F$2:$F$131,MATCH(B11,LIST!$B$2:$B$131,0)),"") -> g | E11: =IFERROR(INDEX(LIST!$G$2:$G$131,MATCH(B11,LIST!$B$2:$B$131,0)),0) -> 0.004 | F11: =C11*E11 -> 0.004
A12: 8 | B12: Full Chicken | C12: 1000 | D12: =IFERROR(INDEX(LIST!$F$2:$F$131,MATCH(B12,LIST!$B$2:$B$131,0)),"") -> g | E12: =IFERROR(INDEX(LIST!$G$2:$G$131,MATCH(B12,LIST!$B$2:$B$131,0)),0) -> 0.001363 | F12: =C12*E12 -> 1.363
A13: 9 | B13: Onion | C13: 200 | D13: =IFERROR(INDEX(LIST!$F$2:$F$131,MATCH(B13,LIST!$B$2:$B$131,0)),"") -> g | E13: =IFERROR(INDEX(LIST!$G$2:$G$131,MATCH(B13,LIST!$B$2:$B$131,0)),0) -> 0.00045 | F13: =C13*E13 -> 0.09
A14: 10 | B14: HASHOO | C14: 100 | D14: =IFERROR(INDEX(LIST!$F$2:$F$131,MATCH(B14,LIST!$B$2:$B$131,0)),"") -> g | E14: =IFERROR(INDEX(LIST!$G$2:$G$131,MATCH(B14,LIST!$B$2:$B$131,0)),0) -> 0 | F14: =C14*E14 -> 0
A15: 11 | B15: MABOOJ + DAQOOS | C15: 0.05 | D15: =IFERROR(INDEX(LIST!$F$2:$F$131,MATCH(B15,LIST!$B$2:$B$131,0)),"") -> g | E15: =IFERROR(INDEX(LIST!$G$2:$G$131,MATCH(B15,LIST!$B$2:$B$131,0)),0) -> 0 | F15: =C15*E15 -> 0
A16: 12 | B16: Garlic Peeled | C16: 20 | D16: =IFERROR(INDEX(LIST!$F$2:$F$131,MATCH(B16,LIST!$B$2:$B$131,0)),"") -> g | E16: =IFERROR(INDEX(LIST!$G$2:$G$131,MATCH(B16,LIST!$B$2:$B$131,0)),0) -> 0.0015 | F16: =C16*E16 -> 0.03
... A21: 17 | B21: Cinamon Stick | C21: 5 | D21: =IFERROR(INDEX(LIST!$F$2:$F$131,MATCH(B21,LIST!$B$2:$B$131,0)),"") -> g | E21: =IFERROR(INDEX(LIST!$G$2:$G$131,MATCH(B21,LIST!$B$2:$B$131,0)),0) -> 0.0023636 | F21: =C21*E21 -> 0.011818
B22: TOTAL RECIPE COST | F22: =SUM(F5:F21) -> 2.3429402
B24: Size | C24: Small | D24: Medium | E24: Large
B25: Containers per recipe | C25: 5 | D25: 3 | E25: 1.5
B26: Ingredient cost | C26: =IF(C25=0,0,$F$22/C25) -> 0.46858804 | D26: =IF(D25=0,0,$F$22/D25) -> 0.78098007 | E26: =IF(E25=0,0,$F$22/E25) -> 1.5619601
B27: Container | C27: Alluminium Container S | D27: Alluminium Container M | E27: Alluminium Container L
B28: Container cost | C28: =IFERROR(INDEX(LIST!$G$2:$G$131,MATCH(C27,LIST!$B$2:$B$131,0)),0) -> 0.0024 | D28: =IFERROR(INDEX(LIST!$G$2:$G$131,MATCH(D27,LIST!$B$2:$B$131,0)),0) -> 0.006 | E28: =IFERROR(INDEX(LIST!$G$2:$G$131,MATCH(E27,LIST!$B$2:$B$131,0)),0) -> 0.006
B29: Spoons (qty) | C29: 1 | D29: 3 | E29: 4
B30: Spoon cost | C30: =C29*IFERROR(INDEX(LIST!$G$2:$G$131,MATCH("SPOON",LIST!$B$2:$B$131,0)),0) -> 0.0064 | D30: =D29*IFERROR(INDEX(LIST!$G$2:$G$131,MATCH("SPOON",LIST!$B$2:$B$131,0)),0) -> 0.0192 | E30: =E29*IFERROR(INDEX(LIST!$G$2:$G$131,MATCH("SPOON",LIST!$B$2:$B$131,0)),0) -> 0.0256
B31: Bread (qty) | C31: 0 | D31: 0 | E31: 0
B32: Bread cost | C32: =C31*IFERROR(INDEX(LIST!$G$2:$G$131,MATCH("Bread",LIST!$B$2:$B$131,0)),0) -> 0 | D32: =D31*IFERROR(INDEX(LIST!$G$2:$G$131,MATCH("Bread",LIST!$B$2:$B$131,0)),0) -> 0 | E32: =E31*IFERROR(INDEX(LIST!$G$2:$G$131,MATCH("Bread",LIST!$B$2:$B$131,0)),0) -> 0
B33: Bag | D33: Bag Medium | E33: Bag Large
B34: Bag cost | C34: =IFERROR(INDEX(LIST!$G$2:$G$131,MATCH(C33,LIST!$B$2:$B$131,0)),0) -> 0 | D34: =IFERROR(INDEX(LIST!$G$2:$G$131,MATCH(D33,LIST!$B$2:$B$131,0)),0) -> 0.03 | E34: =IFERROR(INDEX(LIST!$G$2:$G$131,MATCH(E33,LIST!$B$2:$B$131,0)),0) -> 0.04
B35: Other costs | C35: 0.016 | D35: 0.048 | E35: 0.1109
B36: Packaging total | C36: =C28+C30+C32+C34+C35 -> 0.0248 | D36: =D28+D30+D32+D34+D35 -> 0.1032 | E36: =E28+E30+E32+E34+E35 -> 0.1825
B37: TOTAL COST | C37: =C26+C36 -> 0.49338804 | D37: =D26+D36 -> 0.88418007 | E37: =E26+E36 -> 1.7444601
B38: Store price | C38: 1.2 | D38: 2.3 | E38: 4.4
B39: Store cost % | C39: =IF(C38=0,"",C37/C38) -> 0.4111567 | D39: =IF(D38=0,"",D37/D38) -> 0.38442612 | E39: =IF(E38=0,"",E37/E38) -> 0.39646821
B40: Delivery price | C40: 1.2 | D40: 2.3 | E40: 4.4
B41: Delivery cost % | C41: =IF(N(C40)=0,"",C37/C40) -> 0.4111567 | D41: =IF(N(D40)=0,"",D37/D40) -> 0.38442612 | E41: =IF(N(E40)=0,"",E37/E40) -> 0.39646821
B42: Store profit | C42: =C38-C37 -> 0.70661196 | D42: =D38-D37 -> 1.4158199 | E42: =E38-E37 -> 2.6555399
B43: Delivery profit | C43: =IF(N(C40)=0,"",C40-C37) -> 0.70661196 | D43: =IF(N(D40)=0,"",D40-D37) -> 1.4158199 | E43: =IF(N(E40)=0,"",E40-E37) -> 2.6555399

Sheet Black Eye Beans
A1: Black Eye Beans
A2: Traditional · one recipe fills several containers · target 30%
A4: # | B4: Item | C4: Qty | D4: Unit | E4: Unit price | F4: Cost
A5: 1 | B5: Black Eye Beans | C5: 500 | D5: =IFERROR(INDEX(LIST!$F$2:$F$131,MATCH(B5,LIST!$B$2:$B$131,0)),"") -> g | E5: =IFERROR(INDEX(LIST!$G$2:$G$131,MATCH(B5,LIST!$B$2:$B$131,0)),0) -> 0.00073 | F5: =C5*E5 -> 0.365
A6: 2 | B6: Baking Powder | C6: 0 | D6: =IFERROR(INDEX(LIST!$F$2:$F$131,MATCH(B6,LIST!$B$2:$B$131,0)),"") -> g | E6: =IFERROR(INDEX(LIST!$G$2:$G$131,MATCH(B6,LIST!$B$2:$B$131,0)),0) -> 0.0035113636 | F6: =C6*E6 -> 0
A7: 3 | B7: Salt | C7: 22.5 | D7: =IFERROR(INDEX(LIST!$F$2:$F$131,MATCH(B7,LIST!$B$2:$B$131,0)),"") -> g | E7: =IFERROR(INDEX(LIST!$G$2:$G$131,MATCH(B7,LIST!$B$2:$B$131,0)),0) -> 0.000165 | F7: =C7*E7 -> 0.0037125
B8: TOTAL RECIPE COST | F8: =SUM(F5:F7) -> 0.3687125
B10: Size | C10: Single | D10: Small | E10: Medium | F10: Large
B11: Containers per recipe | C11: 8 | D11: 6 | E11: 3 | F11: 1.5
B12: Ingredient cost | C12: =IF(C11=0,0,$F$8/C11) -> 0.046089062 | D12: =IF(D11=0,0,$F$8/D11) -> 0.061452083 | E12: =IF(E11=0,0,$F$8/E11) -> 0.12290417 | F12: =IF(F11=0,0,$F$8/F11) -> 0.24580833
B13: Container | C13: CONTENER NO : (1) | D13: CONTENER NO : (3) | E13: CONTENER NO : (4) | F13: CONTENER NO : (5)
B14: Container cost | C14: =IFERROR(INDEX(LIST!$G$2:$G$131,MATCH(C13,LIST!$B$2:$B$131,0)),0) -> 0.025 | D14: =IFERROR(INDEX(LIST!$G$2:$G$131,MATCH(D13,LIST!$B$2:$B$131,0)),0) -> 0.021 | E14: =IFERROR(INDEX(LIST!$G$2:$G$131,MATCH(E13,LIST!$B$2:$B$131,0)),0) -> 0.0315 | F14: =IFERROR(INDEX(LIST!$G$2:$G$131,MATCH(F13,LIST!$B$2:$B$131,0)),0) -> 0.11666667
B15: Spoons (qty) | C15: 1 | D15: 1 | E15: 2 | F15: 3
B16: Spoon cost | C16: =C15*IFERROR(INDEX(LIST!$G$2:$G$131,MATCH("SPOON",LIST!$B$2:$B$131,0)),0) -> 0.0064 | D16: =D15*IFERROR(INDEX(LIST!$G$2:$G$131,MATCH("SPOON",LIST!$B$2:$B$131,0)),0) -> 0.0064 | E16: =E15*IFERROR(INDEX(LIST!$G$2:$G$131,MATCH("SPOON",LIST!$B$2:$B$131,0)),0) -> 0.0128 | F16: =F15*IFERROR(INDEX(LIST!$G$2:$G$131,MATCH("SPOON",LIST!$B$2:$B$131,0)),0) -> 0.0192
B17: Bread (qty) | C17: 0 | D17: 0 | E17: 0 | F17: 0
B18: Bread cost | C18: =C17*IFERROR(INDEX(LIST!$G$2:$G$131,MATCH("Bread",LIST!$B$2:$B$131,0)),0) -> 0 | D18: =D17*IFERROR(INDEX(LIST!$G$2:$G$131,MATCH("Bread",LIST!$B$2:$B$131,0)),0) -> 0 | E18: =E17*IFERROR(INDEX(LIST!$G$2:$G$131,MATCH("Bread",LIST!$B$2:$B$131,0)),0) -> 0 | F18: =F17*IFERROR(INDEX(LIST!$G$2:$G$131,MATCH("Bread",LIST!$B$2:$B$131,0)),0) -> 0
B19: Bag | C19: Bag XS | D19: Bag Small | E19: Bag Medium | F19: Bag Large
B20: Bag cost | C20: =IFERROR(INDEX(LIST!$G$2:$G$131,MATCH(C19,LIST!$B$2:$B$131,0)),0) -> 0.01 | D20: =IFERROR(INDEX(LIST!$G$2:$G$131,MATCH(D19,LIST!$B$2:$B$131,0)),0) -> 0.02 | E20: =IFERROR(INDEX(LIST!$G$2:$G$131,MATCH(E19,LIST!$B$2:$B$131,0)),0) -> 0.03 | F20: =IFERROR(INDEX(LIST!$G$2:$G$131,MATCH(F19,LIST!$B$2:$B$131,0)),0) -> 0.04
B21: Other costs | C21: 0 | D21: 0 | E21: 0 | F21: 0
B22: Packaging total | C22: =C14+C16+C18+C20+C21 -> 0.0414 | D22: =D14+D16+D18+D20+D21 -> 0.0474 | E22: =E14+E16+E18+E20+E21 -> 0.0743 | F22: =F14+F16+F18+F20+F21 -> 0.17586667
B23: TOTAL COST | C23: =C12+C22 -> 0.087489063 | D23: =D12+D22 -> 0.10885208 | E23: =E12+E22 -> 0.19720417 | F23: =F12+F22 -> 0.421675
B24: Store price | C24: 0.4 | D24: 0.6 | E24: 1 | F24: 1.8
B25: Store cost % | C25: =IF(C24=0,"",C23/C24) -> 0.21872266 | D25: =IF(D24=0,"",D23/D24) -> 0.18142014 | E25: =IF(E24=0,"",E23/E24) -> 0.19720417 | F25: =IF(F24=0,"",F23/F24) -> 0.23426389
B26: Delivery price | C26: 0.4 | D26: 0.75 | E26: 1.3 | F26: 2.2
B27: Delivery cost % | C27: =IF(N(C26)=0,"",C23/C26) -> 0.21872266 | D27: =IF(N(D26)=0,"",D23/D26) -> 0.14513611 | E27: =IF(N(E26)=0,"",E23/E26) -> 0.15169551 | F27: =IF(N(F26)=0,"",F23/F26) -> 0.19167045
B28: Store profit | C28: =C24-C23 -> 0.31251094 | D28: =D24-D23 -> 0.49114792 | E28: =E24-E23 -> 0.80279583 | F28: =F24-F23 -> 1.378325
B29: Delivery profit | C29: =IF(N(C26)=0,"",C26-C23) -> 0.31251094 | D29: =IF(N(D26)=0,"",D26-D23) -> 0.64114792 | E29: =IF(N(E26)=0,"",E26-E23) -> 1.1027958 | F29: =IF(N(F26)=0,"",F26-F23) -> 1.778325

Sheet Nakhi
A1: Nakhi
A2: Traditional · one recipe fills several containers · target 30%
A4: # | B4: Item | C4: Qty | D4: Unit | E4: Unit price | F4: Cost
A5: 1 | B5: ChickPeas | C5: 1000 | D5: =IFERROR(INDEX(LIST!$F$2:$F$131,MATCH(B5,LIST!$B$2:$B$131,0)),"") -> g | E5: =IFERROR(INDEX(LIST!$G$2:$G$131,MATCH(B5,LIST!$B$2:$B$131,0)),0) -> 0.00066 | F5: =C5*E5 -> 0.66
A6: 2 | B6: Salt | C6: 45 | D6: =IFERROR(INDEX(LIST!$F$2:$F$131,MATCH(B6,LIST!$B$2:$B$131,0)),"") -> g | E6: =IFERROR(INDEX(LIST!$G$2:$G$131,MATCH(B6,LIST!$B$2:$B$131,0)),0) -> 0.000165 | F6: =C6*E6 -> 0.007425
A7: 3 | B7: Baking Powder | C7: 2.5 | D7: =IFERROR(INDEX(LIST!$F$2:$F$131,MATCH(B7,LIST!$B$2:$B$131,0)),"") -> g | E7: =IFERROR(INDEX(LIST!$G$2:$G$131,MATCH(B7,LIST!$B$2:$B$131,0)),0) -> 0.0035113636 | F7: =C7*E7 -> 0.0087784091
A8: 4 | B8: Kuwaiti Powder | C8: 1.25 | D8: =IFERROR(INDEX(LIST!$F$2:$F$131,MATCH(B8,LIST!$B$2:$B$131,0)),"") -> g | E8: =IFERROR(INDEX(LIST!$G$2:$G$131,MATCH(B8,LIST!$B$2:$B$131,0)),0) -> 0.00375 | F8: =C8*E8 -> 0.0046875
B9: TOTAL RECIPE COST | F9: =SUM(F5:F8) -> 0.68089091
B11: Size | C11: Single | D11: Small | E11: Medium | F11: Large
B12: Containers per recipe | C12: 16 | D12: 11 | E12: 5 | F12: 3
B13: Ingredient cost | C13: =IF(C12=0,0,$F$9/C12) -> 0.042555682 | D13: =IF(D12=0,0,$F$9/D12) -> 0.061899174 | E13: =IF(E12=0,0,$F$9/E12) -> 0.13617818 | F13: =IF(F12=0,0,$F$9/F12) -> 0.22696364
B14: Container | C14: CONTENER NO : (1) | D14: CONTENER NO : (3) | E14: CONTENER NO : (4) | F14: CONTENER NO : (5)
B15: Container cost | C15: =IFERROR(INDEX(LIST!$G$2:$G$131,MATCH(C14,LIST!$B$2:$B$131,0)),0) -> 0.025 | D15: =IFERROR(INDEX(LIST!$G$2:$G$131,MATCH(D14,LIST!$B$2:$B$131,0)),0) -> 0.021 | E15: =IFERROR(INDEX(LIST!$G$2:$G$131,MATCH(E14,LIST!$B$2:$B$131,0)),0) -> 0.0315 | F15: =IFERROR(INDEX(LIST!$G$2:$G$131,MATCH(F14,LIST!$B$2:$B$131,0)),0) -> 0.11666667
B16: Spoons (qty) | C16: 1 | D16: 1 | E16: 2 | F16: 3
B17: Spoon cost | C17: =C16*IFERROR(INDEX(LIST!$G$2:$G$131,MATCH("SPOON",LIST!$B$2:$B$131,0)),0) -> 0.0064 | D17: =D16*IFERROR(INDEX(LIST!$G$2:$G$131,MATCH("SPOON",LIST!$B$2:$B$131,0)),0) -> 0.0064 | E17: =E16*IFERROR(INDEX(LIST!$G$2:$G$131,MATCH("SPOON",LIST!$B$2:$B$131,0)),0) -> 0.0128 | F17: =F16*IFERROR(INDEX(LIST!$G$2:$G$131,MATCH("SPOON",LIST!$B$2:$B$131,0)),0) -> 0.0192
B18: Bread (qty) | C18: 0 | D18: 0 | E18: 0 | F18: 0
B19: Bread cost | C19: =C18*IFERROR(INDEX(LIST!$G$2:$G$131,MATCH("Bread",LIST!$B$2:$B$131,0)),0) -> 0 | D19: =D18*IFERROR(INDEX(LIST!$G$2:$G$131,MATCH("Bread",LIST!$B$2:$B$131,0)),0) -> 0 | E19: =E18*IFERROR(INDEX(LIST!$G$2:$G$131,MATCH("Bread",LIST!$B$2:$B$131,0)),0) -> 0 | F19: =F18*IFERROR(INDEX(LIST!$G$2:$G$131,MATCH("Bread",LIST!$B$2:$B$131,0)),0) -> 0
B20: Bag | C20: Bag XS | D20: Bag Small | E20: Bag Medium | F20: Bag Large
B21: Bag cost | C21: =IFERROR(INDEX(LIST!$G$2:$G$131,MATCH(C20,LIST!$B$2:$B$131,0)),0) -> 0.01 | D21: =IFERROR(INDEX(LIST!$G$2:$G$131,MATCH(D20,LIST!$B$2:$B$131,0)),0) -> 0.02 | E21: =IFERROR(INDEX(LIST!$G$2:$G$131,MATCH(E20,LIST!$B$2:$B$131,0)),0) -> 0.03 | F21: =IFERROR(INDEX(LIST!$G$2:$G$131,MATCH(F20,LIST!$B$2:$B$131,0)),0) -> 0.04
B22: Other costs | C22: 0 | D22: 0 | E22: 0 | F22: 0
B23: Packaging total | C23: =C15+C17+C19+C21+C22 -> 0.0414 | D23: =D15+D17+D19+D21+D22 -> 0.0474 | E23: =E15+E17+E19+E21+E22 -> 0.0743 | F23: =F15+F17+F19+F21+F22 -> 0.17586667
B24: TOTAL COST | C24: =C13+C23 -> 0.083955682 | D24: =D13+D23 -> 0.10929917 | E24: =E13+E23 -> 0.21047818 | F24: =F13+F23 -> 0.4028303
B25: Store price | C25: 0.4 | D25: 0.6 | E25: 1 | F25: 1.8
B26: Store cost % | C26: =IF(C25=0,"",C24/C25) -> 0.2098892 | D26: =IF(D25=0,"",D24/D25) -> 0.18216529 | E26: =IF(E25=0,"",E24/E25) -> 0.21047818 | F26: =IF(F25=0,"",F24/F25) -> 0.22379461
B27: Delivery price | C27: 0.4 | D27: 0.75 | E27: 1.2 | F27: 2.2
B28: Delivery cost % | C28: =IF(N(C27)=0,"",C24/C27) -> 0.2098892 | D28: =IF(N(D27)=0,"",D24/D27) -> 0.14573223 | E28: =IF(N(E27)=0,"",E24/E27) -> 0.17539848 | F28: =IF(N(F27)=0,"",F24/F27) -> 0.18310468
B29: Store profit | C29: =C25-C24 -> 0.31604432 | D29: =D25-D24 -> 0.49070083 | E29: =E25-E24 -> 0.78952182 | F29: =F25-F24 -> 1.3971697
B30: Delivery profit | C30: =IF(N(C27)=0,"",C27-C24) -> 0.31604432 | D30: =IF(N(D27)=0,"",D27-D24) -> 0.64070083 | E30: =IF(N(E27)=0,"",E27-E24) -> 0.98952182 | F30: =IF(N(F27)=0,"",F27-F24) -> 1.7971697

Sheet Dall
A1: Dall
A2: Traditional · one recipe fills several containers · target 30%
A4: # | B4: Item | C4: Qty | D4: Unit | E4: Unit price | F4: Cost
A5: 1 | B5: Masoor Daal | C5: 1000 | D5: =IFERROR(INDEX(LIST!$F$2:$F$131,MATCH(B5,LIST!$B$2:$B$131,0)),"") -> g | E5: =IFERROR(INDEX(LIST!$G$2:$G$131,MATCH(B5,LIST!$B$2:$B$131,0)),0) -> 0.000454 | F5: =C5*E5 -> 0.454
A6: 2 | B6: Minced Beef | C6: 150 | D6: =IFERROR(INDEX(LIST!$F$2:$F$131,MATCH(B6,LIST!$B$2:$B$131,0)),"") -> g | E6: =IFERROR(INDEX(LIST!$G$2:$G$131,MATCH(B6,LIST!$B$2:$B$131,0)),0) -> 0.0005975 | F6: =C6*E6 -> 0.089625
A7: 3 | B7: Onion | C7: 150 | D7: =IFERROR(INDEX(LIST!$F$2:$F$131,MATCH(B7,LIST!$B$2:$B$131,0)),"") -> g | E7: =IFERROR(INDEX(LIST!$G$2:$G$131,MATCH(B7,LIST!$B$2:$B$131,0)),0) -> 0.00045 | F7: =C7*E7 -> 0.0675
A8: 4 | B8: Coriander Leaves | C8: 45 | D8: =IFERROR(INDEX(LIST!$F$2:$F$131,MATCH(B8,LIST!$B$2:$B$131,0)),"") -> g | E8: =IFERROR(INDEX(LIST!$G$2:$G$131,MATCH(B8,LIST!$B$2:$B$131,0)),0) -> 0.0017272727 | F8: =C8*E8 -> 0.077727273
A9: 5 | B9: Dill Leaves | C9: 45 | D9: =IFERROR(INDEX(LIST!$F$2:$F$131,MATCH(B9,LIST!$B$2:$B$131,0)),"") -> g | E9: =IFERROR(INDEX(LIST!$G$2:$G$131,MATCH(B9,LIST!$B$2:$B$131,0)),0) -> 0.0015 | F9: =C9*E9 -> 0.0675
A10: 6 | B10: Potato | C10: 350 | D10: =IFERROR(INDEX(LIST!$F$2:$F$131,MATCH(B10,LIST!$B$2:$B$131,0)),"") -> g | E10: =IFERROR(INDEX(LIST!$G$2:$G$131,MATCH(B10,LIST!$B$2:$B$131,0)),0) -> 0.00036 | F10: =C10*E10 -> 0.126
A11: 7 | B11: Green Chilly | C11: 7.5 | D11: =IFERROR(INDEX(LIST!$F$2:$F$131,MATCH(B11,LIST!$B$2:$B$131,0)),"") -> g | E11: =IFERROR(INDEX(LIST!$G$2:$G$131,MATCH(B11,LIST!$B$2:$B$131,0)),0) -> 0.0008 | F11: =C11*E11 -> 0.006
A12: 8 | B12: Ginger + Garlic Mix | C12: 15 | D12: =IFERROR(INDEX(LIST!$F$2:$F$131,MATCH(B12,LIST!$B$2:$B$131,0)),"") -> g | E12: =IFERROR(INDEX(LIST!$G$2:$G$131,MATCH(B12,LIST!$B$2:$B$131,0)),0) -> 0.0012 | F12: =C12*E12 -> 0.018
A13: 9 | B13: Tomato | C13: 350 | D13: =IFERROR(INDEX(LIST!$F$2:$F$131,MATCH(B13,LIST!$B$2:$B$131,0)),"") -> g | E13: =IFERROR(INDEX(LIST!$G$2:$G$131,MATCH(B13,LIST!$B$2:$B$131,0)),0) -> 0.0005 | F13: =C13*E13 -> 0.175
A14: 10 | B14: Coriander Powder | C14: 5 | D14: =IFERROR(INDEX(LIST!$F$2:$F$131,MATCH(B14,LIST!$B$2:$B$131,0)),"") -> g | E14: =IFERROR(INDEX(LIST!$G$2:$G$131,MATCH(B14,LIST!$B$2:$B$131,0)),0) -> 0.0018 | F14: =C14*E14 -> 0.009
A15: 11 | B15: Vegetable Oil | C15: 135 | D15: =IFERROR(INDEX(LIST!$F$2:$F$131,MATCH(B15,LIST!$B$2:$B$131,0)),"") -> ml | E15: =IFERROR(INDEX(LIST!$G$2:$G$131,MATCH(B15,LIST!$B$2:$B$131,0)),0) -> 0.000594 | F15: =C15*E15 -> 0.08019
A16: 12 | B16: Tomato Paste | C16: 20 | D16: =IFERROR(INDEX(LIST!$F$2:$F$131,MATCH(B16,LIST!$B$2:$B$131,0)),"") -> g | E16: =IFERROR(INDEX(LIST!$G$2:$G$131,MATCH(B16,LIST!$B$2:$B$131,0)),0) -> 0.0006 | F16: =C16*E16 -> 0.012
... A21: 17 | B21: Tandori Masala Powder | C21: 1.5 | D21: =IFERROR(INDEX(LIST!$F$2:$F$131,MATCH(B21,LIST!$B$2:$B$131,0)),"") -> g | E21: =IFERROR(INDEX(LIST!$G$2:$G$131,MATCH(B21,LIST!$B$2:$B$131,0)),0) -> 0.004 | F21: =C21*E21 -> 0.006
B22: TOTAL RECIPE COST | F22: =SUM(F5:F21) -> 1.2556523
B24: Size | C24: Single | D24: Small | E24: Medium | F24: Large
B25: Containers per recipe | C25: 17 | D25: 12 | E25: 8 | F25: 4
B26: Ingredient cost | C26: =IF(C25=0,0,$F$22/C25) -> 0.073861898 | D26: =IF(D25=0,0,$F$22/D25) -> 0.10463769 | E26: =IF(E25=0,0,$F$22/E25) -> 0.15695653 | F26: =IF(F25=0,0,$F$22/F25) -> 0.31391307
B27: Container | C27: CONTENER NO : (1) | D27: CONTENER NO : (3) | E27: CONTENER NO : (4) | F27: CONTENER NO : (5)
B28: Container cost | C28: =IFERROR(INDEX(LIST!$G$2:$G$131,MATCH(C27,LIST!$B$2:$B$131,0)),0) -> 0.025 | D28: =IFERROR(INDEX(LIST!$G$2:$G$131,MATCH(D27,LIST!$B$2:$B$131,0)),0) -> 0.021 | E28: =IFERROR(INDEX(LIST!$G$2:$G$131,MATCH(E27,LIST!$B$2:$B$131,0)),0) -> 0.0315 | F28: =IFERROR(INDEX(LIST!$G$2:$G$131,MATCH(F27,LIST!$B$2:$B$131,0)),0) -> 0.11666667
B29: Spoons (qty) | C29: 1 | D29: 1 | E29: 2 | F29: 3
B30: Spoon cost | C30: =C29*IFERROR(INDEX(LIST!$G$2:$G$131,MATCH("SPOON",LIST!$B$2:$B$131,0)),0) -> 0.0064 | D30: =D29*IFERROR(INDEX(LIST!$G$2:$G$131,MATCH("SPOON",LIST!$B$2:$B$131,0)),0) -> 0.0064 | E30: =E29*IFERROR(INDEX(LIST!$G$2:$G$131,MATCH("SPOON",LIST!$B$2:$B$131,0)),0) -> 0.0128 | F30: =F29*IFERROR(INDEX(LIST!$G$2:$G$131,MATCH("SPOON",LIST!$B$2:$B$131,0)),0) -> 0.0192
B31: Bread (qty) | C31: 0.5 | D31: 1 | E31: 2 | F31: 4
B32: Bread cost | C32: =C31*IFERROR(INDEX(LIST!$G$2:$G$131,MATCH("Bread",LIST!$B$2:$B$131,0)),0) -> 0.006 | D32: =D31*IFERROR(INDEX(LIST!$G$2:$G$131,MATCH("Bread",LIST!$B$2:$B$131,0)),0) -> 0.012 | E32: =E31*IFERROR(INDEX(LIST!$G$2:$G$131,MATCH("Bread",LIST!$B$2:$B$131,0)),0) -> 0.024 | F32: =F31*IFERROR(INDEX(LIST!$G$2:$G$131,MATCH("Bread",LIST!$B$2:$B$131,0)),0) -> 0.048
B33: Bag | C33: Bag XS | D33: Bag Small | E33: Bag Medium | F33: Bag Large
B34: Bag cost | C34: =IFERROR(INDEX(LIST!$G$2:$G$131,MATCH(C33,LIST!$B$2:$B$131,0)),0) -> 0.01 | D34: =IFERROR(INDEX(LIST!$G$2:$G$131,MATCH(D33,LIST!$B$2:$B$131,0)),0) -> 0.02 | E34: =IFERROR(INDEX(LIST!$G$2:$G$131,MATCH(E33,LIST!$B$2:$B$131,0)),0) -> 0.03 | F34: =IFERROR(INDEX(LIST!$G$2:$G$131,MATCH(F33,LIST!$B$2:$B$131,0)),0) -> 0.04
B35: Other costs | C35: 0 | D35: 0 | E35: 0 | F35: 0
B36: Packaging total | C36: =C28+C30+C32+C34+C35 -> 0.0474 | D36: =D28+D30+D32+D34+D35 -> 0.0594 | E36: =E28+E30+E32+E34+E35 -> 0.0983 | F36: =F28+F30+F32+F34+F35 -> 0.22386667
B37: TOTAL COST | C37: =C26+C36 -> 0.1212619 | D37: =D26+D36 -> 0.16403769 | E37: =E26+E36 -> 0.25525653 | F37: =F26+F36 -> 0.53777973
B38: Store price | C38: 0.6 | D38: 1 | E38: 1.6 | F38: 2.9
B39: Store cost % | C39: =IF(C38=0,"",C37/C38) -> 0.20210316 | D39: =IF(D38=0,"",D37/D38) -> 0.16403769 | E39: =IF(E38=0,"",E37/E38) -> 0.15953533 | F39: =IF(F38=0,"",F37/F38) -> 0.18544129
B40: Delivery price | C40: 0.6 | D40: 1.35 | E40: 2.2 | F40: 3.8
B41: Delivery cost % | C41: =IF(N(C40)=0,"",C37/C40) -> 0.20210316 | D41: =IF(N(D40)=0,"",D37/D40) -> 0.1215094 | E41: =IF(N(E40)=0,"",E37/E40) -> 0.1160257 | F41: =IF(N(F40)=0,"",F37/F40) -> 0.14152098
B42: Store profit | C42: =C38-C37 -> 0.4787381 | D42: =D38-D37 -> 0.83596231 | E42: =E38-E37 -> 1.3447435 | F42: =F38-F37 -> 2.3622203
B43: Delivery profit | C43: =IF(N(C40)=0,"",C40-C37) -> 0.4787381 | D43: =IF(N(D40)=0,"",D40-D37) -> 1.1859623 | E43: =IF(N(E40)=0,"",E40-E37) -> 1.9447435 | F43: =IF(N(F40)=0,"",F40-F37) -> 3.2622203

Sheet Bajela
A1: Bajela
A2: Traditional · one recipe fills several containers · target 30%
A4: # | B4: Item | C4: Qty | D4: Unit | E4: Unit price | F4: Cost
A5: 1 | B5: Bagela | C5: 1000 | D5: =IFERROR(INDEX(LIST!$F$2:$F$131,MATCH(B5,LIST!$B$2:$B$131,0)),"") -> g | E5: =IFERROR(INDEX(LIST!$G$2:$G$131,MATCH(B5,LIST!$B$2:$B$131,0)),0) -> 0.00155 | F5: =C5*E5 -> 1.55
A6: 2 | B6: Salt | C6: 45 | D6: =IFERROR(INDEX(LIST!$F$2:$F$131,MATCH(B6,LIST!$B$2:$B$131,0)),"") -> g | E6: =IFERROR(INDEX(LIST!$G$2:$G$131,MATCH(B6,LIST!$B$2:$B$131,0)),0) -> 0.000165 | F6: =C6*E6 -> 0.007425
A7: 3 | B7: Baking Powder | C7: 2.5 | D7: =IFERROR(INDEX(LIST!$F$2:$F$131,MATCH(B7,LIST!$B$2:$B$131,0)),"") -> g | E7: =IFERROR(INDEX(LIST!$G$2:$G$131,MATCH(B7,LIST!$B$2:$B$131,0)),0) -> 0.0035113636 | F7: =C7*E7 -> 0.0087784091
A8: 4 | B8: Kuwaiti Powder | C8: 1.25 | D8: =IFERROR(INDEX(LIST!$F$2:$F$131,MATCH(B8,LIST!$B$2:$B$131,0)),"") -> g | E8: =IFERROR(INDEX(LIST!$G$2:$G$131,MATCH(B8,LIST!$B$2:$B$131,0)),0) -> 0.00375 | F8: =C8*E8 -> 0.0046875
B9: TOTAL RECIPE COST | F9: =SUM(F5:F8) -> 1.5708909
B11: Size | C11: Single | D11: Small | E11: Medium | F11: Large
B12: Containers per recipe | C12: 15 | D12: 9 | E12: 6 | F12: 3
B13: Ingredient cost | C13: =IF(C12=0,0,$F$9/C12) -> 0.10472606 | D13: =IF(D12=0,0,$F$9/D12) -> 0.17454343 | E13: =IF(E12=0,0,$F$9/E12) -> 0.26181515 | F13: =IF(F12=0,0,$F$9/F12) -> 0.5236303
B14: Container | C14: CONTENER NO : (1) | D14: CONTENER NO : (3) | E14: CONTENER NO : (4) | F14: CONTENER NO : (5)
B15: Container cost | C15: =IFERROR(INDEX(LIST!$G$2:$G$131,MATCH(C14,LIST!$B$2:$B$131,0)),0) -> 0.025 | D15: =IFERROR(INDEX(LIST!$G$2:$G$131,MATCH(D14,LIST!$B$2:$B$131,0)),0) -> 0.021 | E15: =IFERROR(INDEX(LIST!$G$2:$G$131,MATCH(E14,LIST!$B$2:$B$131,0)),0) -> 0.0315 | F15: =IFERROR(INDEX(LIST!$G$2:$G$131,MATCH(F14,LIST!$B$2:$B$131,0)),0) -> 0.11666667
B16: Spoons (qty) | C16: 1 | D16: 1 | E16: 2 | F16: 3
B17: Spoon cost | C17: =C16*IFERROR(INDEX(LIST!$G$2:$G$131,MATCH("SPOON",LIST!$B$2:$B$131,0)),0) -> 0.0064 | D17: =D16*IFERROR(INDEX(LIST!$G$2:$G$131,MATCH("SPOON",LIST!$B$2:$B$131,0)),0) -> 0.0064 | E17: =E16*IFERROR(INDEX(LIST!$G$2:$G$131,MATCH("SPOON",LIST!$B$2:$B$131,0)),0) -> 0.0128 | F17: =F16*IFERROR(INDEX(LIST!$G$2:$G$131,MATCH("SPOON",LIST!$B$2:$B$131,0)),0) -> 0.0192
B18: Bread (qty) | C18: 0 | D18: 0 | E18: 0 | F18: 0
B19: Bread cost | C19: =C18*IFERROR(INDEX(LIST!$G$2:$G$131,MATCH("Bread",LIST!$B$2:$B$131,0)),0) -> 0 | D19: =D18*IFERROR(INDEX(LIST!$G$2:$G$131,MATCH("Bread",LIST!$B$2:$B$131,0)),0) -> 0 | E19: =E18*IFERROR(INDEX(LIST!$G$2:$G$131,MATCH("Bread",LIST!$B$2:$B$131,0)),0) -> 0 | F19: =F18*IFERROR(INDEX(LIST!$G$2:$G$131,MATCH("Bread",LIST!$B$2:$B$131,0)),0) -> 0
B20: Bag | C20: Bag XS | D20: Bag Small | E20: Bag Medium | F20: Bag Large
B21: Bag cost | C21: =IFERROR(INDEX(LIST!$G$2:$G$131,MATCH(C20,LIST!$B$2:$B$131,0)),0) -> 0.01 | D21: =IFERROR(INDEX(LIST!$G$2:$G$131,MATCH(D20,LIST!$B$2:$B$131,0)),0) -> 0.02 | E21: =IFERROR(INDEX(LIST!$G$2:$G$131,MATCH(E20,LIST!$B$2:$B$131,0)),0) -> 0.03 | F21: =IFERROR(INDEX(LIST!$G$2:$G$131,MATCH(F20,LIST!$B$2:$B$131,0)),0) -> 0.04
B22: Other costs | C22: 0 | D22: 0 | E22: 0 | F22: 0
B23: Packaging total | C23: =C15+C17+C19+C21+C22 -> 0.0414 | D23: =D15+D17+D19+D21+D22 -> 0.0474 | E23: =E15+E17+E19+E21+E22 -> 0.0743 | F23: =F15+F17+F19+F21+F22 -> 0.17586667
B24: TOTAL COST | C24: =C13+C23 -> 0.14612606 | D24: =D13+D23 -> 0.22194343 | E24: =E13+E23 -> 0.33611515 | F24: =F13+F23 -> 0.69949697
B25: Store price | C25: 0.4 | D25: 0.6 | E25: 1 | F25: 1.9
B26: Store cost % | C26: =IF(C25=0,"",C24/C25) -> 0.36531515 | D26: =IF(D25=0,"",D24/D25) -> 0.36990572 | E26: =IF(E25=0,"",E24/E25) -> 0.33611515 | F26: =IF(F25=0,"",F24/F25) -> 0.3681563
B27: Delivery price | C27: 0.4 | D27: 0.75 | E27: 1.2 | F27: 2.2
B28: Delivery cost % | C28: =IF(N(C27)=0,"",C24/C27) -> 0.36531515 | D28: =IF(N(D27)=0,"",D24/D27) -> 0.29592458 | E28: =IF(N(E27)=0,"",E24/E27) -> 0.28009596 | F28: =IF(N(F27)=0,"",F24/F27) -> 0.31795317
B29: Store profit | C29: =C25-C24 -> 0.25387394 | D29: =D25-D24 -> 0.37805657 | E29: =E25-E24 -> 0.66388485 | F29: =F25-F24 -> 1.200503
B30: Delivery profit | C30: =IF(N(C27)=0,"",C27-C24) -> 0.25387394 | D30: =IF(N(D27)=0,"",D27-D24) -> 0.52805657 | E30: =IF(N(E27)=0,"",E27-E24) -> 0.86388485 | F30: =IF(N(F27)=0,"",F27-F24) -> 1.500503

Sheet Harees
A1: Harees
A2: Traditional · one recipe fills several containers · target 30%
A4: # | B4: Item | C4: Qty | D4: Unit | E4: Unit price | F4: Cost
A5: 1 | B5: Harees | C5: 1000 | D5: =IFERROR(INDEX(LIST!$F$2:$F$131,MATCH(B5,LIST!$B$2:$B$131,0)),"") -> g | E5: =IFERROR(INDEX(LIST!$G$2:$G$131,MATCH(B5,LIST!$B$2:$B$131,0)),0) -> 0.00045 | F5: =C5*E5 -> 0.45
A6: 2 | B6: Beef Slice | C6: 900 | D6: =IFERROR(INDEX(LIST!$F$2:$F$131,MATCH(B6,LIST!$B$2:$B$131,0)),"") -> g | E6: =IFERROR(INDEX(LIST!$G$2:$G$131,MATCH(B6,LIST!$B$2:$B$131,0)),0) -> 0.0029288889 | F6: =C6*E6 -> 2.636
A7: 3 | B7: Salt | C7: 30 | D7: =IFERROR(INDEX(LIST!$F$2:$F$131,MATCH(B7,LIST!$B$2:$B$131,0)),"") -> g | E7: =IFERROR(INDEX(LIST!$G$2:$G$131,MATCH(B7,LIST!$B$2:$B$131,0)),0) -> 0.000165 | F7: =C7*E7 -> 0.00495
A8: 4 | B8: Tomato | C8: 250 | D8: =IFERROR(INDEX(LIST!$F$2:$F$131,MATCH(B8,LIST!$B$2:$B$131,0)),"") -> g | E8: =IFERROR(INDEX(LIST!$G$2:$G$131,MATCH(B8,LIST!$B$2:$B$131,0)),0) -> 0.0005 | F8: =C8*E8 -> 0.125
A9: 5 | B9: Aseel Ghee | C9: 150 | D9: =IFERROR(INDEX(LIST!$F$2:$F$131,MATCH(B9,LIST!$B$2:$B$131,0)),"") -> ml | E9: =IFERROR(INDEX(LIST!$G$2:$G$131,MATCH(B9,LIST!$B$2:$B$131,0)),0) -> 0.001232 | F9: =C9*E9 -> 0.1848
B10: TOTAL RECIPE COST | F10: =SUM(F5:F9) -> 3.40075
B12: Size | C12: Single | D12: Small | E12: Medium | F12: Large
B13: Containers per recipe | C13: 16 | D13: 12 | E13: 6 | F13: 3.5
B14: Ingredient cost | C14: =IF(C13=0,0,$F$10/C13) -> 0.21254687 | D14: =IF(D13=0,0,$F$10/D13) -> 0.28339583 | E14: =IF(E13=0,0,$F$10/E13) -> 0.56679167 | F14: =IF(F13=0,0,$F$10/F13) -> 0.97164286
B15: Container | C15: CONTENER NO : (1) | D15: CONTENER NO : (3) | E15: CONTENER NO : (4) | F15: CONTENER NO : (5)
B16: Container cost | C16: =IFERROR(INDEX(LIST!$G$2:$G$131,MATCH(C15,LIST!$B$2:$B$131,0)),0) -> 0.025 | D16: =IFERROR(INDEX(LIST!$G$2:$G$131,MATCH(D15,LIST!$B$2:$B$131,0)),0) -> 0.021 | E16: =IFERROR(INDEX(LIST!$G$2:$G$131,MATCH(E15,LIST!$B$2:$B$131,0)),0) -> 0.0315 | F16: =IFERROR(INDEX(LIST!$G$2:$G$131,MATCH(F15,LIST!$B$2:$B$131,0)),0) -> 0.11666667
B17: Spoons (qty) | C17: 1 | D17: 1 | E17: 2 | F17: 3
B18: Spoon cost | C18: =C17*IFERROR(INDEX(LIST!$G$2:$G$131,MATCH("SPOON",LIST!$B$2:$B$131,0)),0) -> 0.0064 | D18: =D17*IFERROR(INDEX(LIST!$G$2:$G$131,MATCH("SPOON",LIST!$B$2:$B$131,0)),0) -> 0.0064 | E18: =E17*IFERROR(INDEX(LIST!$G$2:$G$131,MATCH("SPOON",LIST!$B$2:$B$131,0)),0) -> 0.0128 | F18: =F17*IFERROR(INDEX(LIST!$G$2:$G$131,MATCH("SPOON",LIST!$B$2:$B$131,0)),0) -> 0.0192
B19: Bread (qty) | C19: 0 | D19: 0 | E19: 0 | F19: 0
B20: Bread cost | C20: =C19*IFERROR(INDEX(LIST!$G$2:$G$131,MATCH("Bread",LIST!$B$2:$B$131,0)),0) -> 0 | D20: =D19*IFERROR(INDEX(LIST!$G$2:$G$131,MATCH("Bread",LIST!$B$2:$B$131,0)),0) -> 0 | E20: =E19*IFERROR(INDEX(LIST!$G$2:$G$131,MATCH("Bread",LIST!$B$2:$B$131,0)),0) -> 0 | F20: =F19*IFERROR(INDEX(LIST!$G$2:$G$131,MATCH("Bread",LIST!$B$2:$B$131,0)),0) -> 0
B21: Bag | C21: Bag XS | D21: Bag XS | E21: Bag Medium | F21: Bag Medium
B22: Bag cost | C22: =IFERROR(INDEX(LIST!$G$2:$G$131,MATCH(C21,LIST!$B$2:$B$131,0)),0) -> 0.01 | D22: =IFERROR(INDEX(LIST!$G$2:$G$131,MATCH(D21,LIST!$B$2:$B$131,0)),0) -> 0.01 | E22: =IFERROR(INDEX(LIST!$G$2:$G$131,MATCH(E21,LIST!$B$2:$B$131,0)),0) -> 0.03 | F22: =IFERROR(INDEX(LIST!$G$2:$G$131,MATCH(F21,LIST!$B$2:$B$131,0)),0) -> 0.03
B23: Other costs | C23: 0 | D23: 0 | E23: 0 | F23: 0
B24: Packaging total | C24: =C16+C18+C20+C22+C23 -> 0.0414 | D24: =D16+D18+D20+D22+D23 -> 0.0374 | E24: =E16+E18+E20+E22+E23 -> 0.0743 | F24: =F16+F18+F20+F22+F23 -> 0.16586667
B25: TOTAL COST | C25: =C14+C24 -> 0.25394688 | D25: =D14+D24 -> 0.32079583 | E25: =E14+E24 -> 0.64109167 | F25: =F14+F24 -> 1.1375095
B26: Store price | C26: 0.6 | D26: 1 | E26: 1.6 | F26: 2.9
B27: Store cost % | C27: =IF(C26=0,"",C25/C26) -> 0.42324479 | D27: =IF(D26=0,"",D25/D26) -> 0.32079583 | E27: =IF(E26=0,"",E25/E26) -> 0.40068229 | F27: =IF(F26=0,"",F25/F26) -> 0.39224466
B28: Delivery price | C28: 0.6 | D28: 1.35 | E28: 2.4 | F28: 4.4
B29: Delivery cost % | C29: =IF(N(C28)=0,"",C25/C28) -> 0.42324479 | D29: =IF(N(D28)=0,"",D25/D28) -> 0.23762654 | E29: =IF(N(E28)=0,"",E25/E28) -> 0.26712153 | F29: =IF(N(F28)=0,"",F25/F28) -> 0.25852489
B30: Store profit | C30: =C26-C25 -> 0.34605313 | D30: =D26-D25 -> 0.67920417 | E30: =E26-E25 -> 0.95890833 | F30: =F26-F25 -> 1.7624905
B31: Delivery profit | C31: =IF(N(C28)=0,"",C28-C25) -> 0.34605313 | D31: =IF(N(D28)=0,"",D28-D25) -> 1.0292042 | E31: =IF(N(E28)=0,"",E28-E25) -> 1.7589083 | F31: =IF(N(F28)=0,"",F28-F25) -> 3.2624905

Sheet Jareesh
A1: Jareesh
A2: Traditional · one recipe fills several containers · target 30%
A4: # | B4: Item | C4: Qty | D4: Unit | E4: Unit price | F4: Cost
A5: 1 | B5: Qeema Meat | C5: 500 | D5: =IFERROR(INDEX(LIST!$F$2:$F$131,MATCH(B5,LIST!$B$2:$B$131,0)),"") -> g | E5: =IFERROR(INDEX(LIST!$G$2:$G$131,MATCH(B5,LIST!$B$2:$B$131,0)),0) -> 0.0022 | F5: =C5*E5 -> 1.1
A6: 2 | B6: Jareesh | C6: 1000 | D6: =IFERROR(INDEX(LIST!$F$2:$F$131,MATCH(B6,LIST!$B$2:$B$131,0)),"") -> g | E6: =IFERROR(INDEX(LIST!$G$2:$G$131,MATCH(B6,LIST!$B$2:$B$131,0)),0) -> 0 | F6: =C6*E6 -> 0
A7: 3 | B7: Vegetable Oil | C7: 250 | D7: =IFERROR(INDEX(LIST!$F$2:$F$131,MATCH(B7,LIST!$B$2:$B$131,0)),"") -> ml | E7: =IFERROR(INDEX(LIST!$G$2:$G$131,MATCH(B7,LIST!$B$2:$B$131,0)),0) -> 0.000594 | F7: =C7*E7 -> 0.1485
A8: 4 | B8: Tomato Paste | C8: 480 | D8: =IFERROR(INDEX(LIST!$F$2:$F$131,MATCH(B8,LIST!$B$2:$B$131,0)),"") -> g | E8: =IFERROR(INDEX(LIST!$G$2:$G$131,MATCH(B8,LIST!$B$2:$B$131,0)),0) -> 0.0006 | F8: =C8*E8 -> 0.288
A9: 5 | B9: Onion | C9: 300 | D9: =IFERROR(INDEX(LIST!$F$2:$F$131,MATCH(B9,LIST!$B$2:$B$131,0)),"") -> g | E9: =IFERROR(INDEX(LIST!$G$2:$G$131,MATCH(B9,LIST!$B$2:$B$131,0)),0) -> 0.00045 | F9: =C9*E9 -> 0.135
A10: 6 | B10: Green Chilly | C10: 5 | D10: =IFERROR(INDEX(LIST!$F$2:$F$131,MATCH(B10,LIST!$B$2:$B$131,0)),"") -> g | E10: =IFERROR(INDEX(LIST!$G$2:$G$131,MATCH(B10,LIST!$B$2:$B$131,0)),0) -> 0.0008 | F10: =C10*E10 -> 0.004
A11: 7 | B11: Garlic Peeled | C11: 15 | D11: =IFERROR(INDEX(LIST!$F$2:$F$131,MATCH(B11,LIST!$B$2:$B$131,0)),"") -> g | E11: =IFERROR(INDEX(LIST!$G$2:$G$131,MATCH(B11,LIST!$B$2:$B$131,0)),0) -> 0.0015 | F11: =C11*E11 -> 0.0225
A12: 8 | B12: Tomato | C12: 500 | D12: =IFERROR(INDEX(LIST!$F$2:$F$131,MATCH(B12,LIST!$B$2:$B$131,0)),"") -> g | E12: =IFERROR(INDEX(LIST!$G$2:$G$131,MATCH(B12,LIST!$B$2:$B$131,0)),0) -> 0.0005 | F12: =C12*E12 -> 0.25
A13: 9 | B13: Cummin Powder | C13: 15 | D13: =IFERROR(INDEX(LIST!$F$2:$F$131,MATCH(B13,LIST!$B$2:$B$131,0)),"") -> g | E13: =IFERROR(INDEX(LIST!$G$2:$G$131,MATCH(B13,LIST!$B$2:$B$131,0)),0) -> 0.002818 | F13: =C13*E13 -> 0.04227
A14: 10 | B14: Mix Masala Powder | C14: 5 | D14: =IFERROR(INDEX(LIST!$F$2:$F$131,MATCH(B14,LIST!$B$2:$B$131,0)),"") -> g | E14: =IFERROR(INDEX(LIST!$G$2:$G$131,MATCH(B14,LIST!$B$2:$B$131,0)),0) -> 0.00165 | F14: =C14*E14 -> 0.00825
A15: 11 | B15: Black Lemone Powdre | C15: 2.5 | D15: =IFERROR(INDEX(LIST!$F$2:$F$131,MATCH(B15,LIST!$B$2:$B$131,0)),"") -> g | E15: =IFERROR(INDEX(LIST!$G$2:$G$131,MATCH(B15,LIST!$B$2:$B$131,0)),0) -> 0.00462 | F15: =C15*E15 -> 0.01155
A16: 12 | B16: Cinamon Powder | C16: 2.5 | D16: =IFERROR(INDEX(LIST!$F$2:$F$131,MATCH(B16,LIST!$B$2:$B$131,0)),"") -> g | E16: =IFERROR(INDEX(LIST!$G$2:$G$131,MATCH(B16,LIST!$B$2:$B$131,0)),0) -> 0.0026454 | F16: =C16*E16 -> 0.0066135
A17: 13 | B17: Salt | C17: 30 | D17: =IFERROR(INDEX(LIST!$F$2:$F$131,MATCH(B17,LIST!$B$2:$B$131,0)),"") -> g | E17: =IFERROR(INDEX(LIST!$G$2:$G$131,MATCH(B17,LIST!$B$2:$B$131,0)),0) -> 0.000165 | F17: =C17*E17 -> 0.00495
B18: TOTAL RECIPE COST | F18: =SUM(F5:F17) -> 2.0216335
B20: Size | C20: Small | D20: Medium | E20: Large
B21: Containers per recipe | C21: 15 | D21: 8 | E21: 3
B22: Ingredient cost | C22: =IF(C21=0,0,$F$18/C21) -> 0.13477557 | D22: =IF(D21=0,0,$F$18/D21) -> 0.25270419 | E22: =IF(E21=0,0,$F$18/E21) -> 0.67387783
B23: Container | C23: CONTENER NO : (3) | D23: CONTENER NO : (4) | E23: CONTENER NO : (5)
B24: Container cost | C24: =IFERROR(INDEX(LIST!$G$2:$G$131,MATCH(C23,LIST!$B$2:$B$131,0)),0) -> 0.021 | D24: =IFERROR(INDEX(LIST!$G$2:$G$131,MATCH(D23,LIST!$B$2:$B$131,0)),0) -> 0.0315 | E24: =IFERROR(INDEX(LIST!$G$2:$G$131,MATCH(E23,LIST!$B$2:$B$131,0)),0) -> 0.11666667
B25: Spoons (qty) | C25: 1.45 | D25: 4.5 | E25: 6
B26: Spoon cost | C26: =C25*IFERROR(INDEX(LIST!$G$2:$G$131,MATCH("SPOON",LIST!$B$2:$B$131,0)),0) -> 0.00928 | D26: =D25*IFERROR(INDEX(LIST!$G$2:$G$131,MATCH("SPOON",LIST!$B$2:$B$131,0)),0) -> 0.0288 | E26: =E25*IFERROR(INDEX(LIST!$G$2:$G$131,MATCH("SPOON",LIST!$B$2:$B$131,0)),0) -> 0.0384
B27: Bread (qty) | C27: 0 | D27: 0 | E27: 0
B28: Bread cost | C28: =C27*IFERROR(INDEX(LIST!$G$2:$G$131,MATCH("Bread",LIST!$B$2:$B$131,0)),0) -> 0 | D28: =D27*IFERROR(INDEX(LIST!$G$2:$G$131,MATCH("Bread",LIST!$B$2:$B$131,0)),0) -> 0 | E28: =E27*IFERROR(INDEX(LIST!$G$2:$G$131,MATCH("Bread",LIST!$B$2:$B$131,0)),0) -> 0
B29: Bag | C29: Bag Small | D29: Bag Medium | E29: Bag Large
B30: Bag cost | C30: =IFERROR(INDEX(LIST!$G$2:$G$131,MATCH(C29,LIST!$B$2:$B$131,0)),0) -> 0.02 | D30: =IFERROR(INDEX(LIST!$G$2:$G$131,MATCH(D29,LIST!$B$2:$B$131,0)),0) -> 0.03 | E30: =IFERROR(INDEX(LIST!$G$2:$G$131,MATCH(E29,LIST!$B$2:$B$131,0)),0) -> 0.04
B31: Other costs | C31: 0 | D31: 0 | E31: 0
B32: Packaging total | C32: =C24+C26+C28+C30+C31 -> 0.05028 | D32: =D24+D26+D28+D30+D31 -> 0.0903 | E32: =E24+E26+E28+E30+E31 -> 0.19506667
B33: TOTAL COST | C33: =C22+C32 -> 0.18505557 | D33: =D22+D32 -> 0.34300419 | E33: =E22+E32 -> 0.8689445
B34: Store price | C34: 1 | D34: 1.6 | E34: 2.9
B35: Store cost % | C35: =IF(C34=0,"",C33/C34) -> 0.18505557 | D35: =IF(D34=0,"",D33/D34) -> 0.21437762 | E35: =IF(E34=0,"",E33/E34) -> 0.29963603
B36: Delivery price | C36: 1 | D36: 1.6 | E36: 2.9
B37: Delivery cost % | C37: =IF(N(C36)=0,"",C33/C36) -> 0.18505557 | D37: =IF(N(D36)=0,"",D33/D36) -> 0.21437762 | E37: =IF(N(E36)=0,"",E33/E36) -> 0.29963603
B38: Store profit | C38: =C34-C33 -> 0.81494443 | D38: =D34-D33 -> 1.2569958 | E38: =E34-E33 -> 2.0310555
B39: Delivery profit | C39: =IF(N(C36)=0,"",C36-C33) -> 0.81494443 | D39: =IF(N(D36)=0,"",D36-D33) -> 1.2569958 | E39: =IF(N(E36)=0,"",E36-E33) -> 2.0310555

Sheet Shilla
A1: Shilla
A2: Traditional · one recipe fills several containers · target 30%
A4: # | B4: Item | C4: Qty | D4: Unit | E4: Unit price | F4: Cost
A5: 1 | B5: White Kidney Beans | C5: 175 | D5: =IFERROR(INDEX(LIST!$F$2:$F$131,MATCH(B5,LIST!$B$2:$B$131,0)),"") -> g | E5: =IFERROR(INDEX(LIST!$G$2:$G$131,MATCH(B5,LIST!$B$2:$B$131,0)),0) -> 0.000818 | F5: =C5*E5 -> 0.14315
A6: 2 | B6: Black Eye Beans | C6: 175 | D6: =IFERROR(INDEX(LIST!$F$2:$F$131,MATCH(B6,LIST!$B$2:$B$131,0)),"") -> g | E6: =IFERROR(INDEX(LIST!$G$2:$G$131,MATCH(B6,LIST!$B$2:$B$131,0)),0) -> 0.00073 | F6: =C6*E6 -> 0.12775
A7: 3 | B7: Moong Dal | C7: 175 | D7: =IFERROR(INDEX(LIST!$F$2:$F$131,MATCH(B7,LIST!$B$2:$B$131,0)),"") -> g | E7: =IFERROR(INDEX(LIST!$G$2:$G$131,MATCH(B7,LIST!$B$2:$B$131,0)),0) -> 0.000668 | F7: =C7*E7 -> 0.1169
A8: 4 | B8: Green lentils | C8: 175 | D8: =IFERROR(INDEX(LIST!$F$2:$F$131,MATCH(B8,LIST!$B$2:$B$131,0)),"") -> g | E8: =IFERROR(INDEX(LIST!$G$2:$G$131,MATCH(B8,LIST!$B$2:$B$131,0)),0) -> 0.0004 | F8: =C8*E8 -> 0.07
A9: 5 | B9: Harees | C9: 175 | D9: =IFERROR(INDEX(LIST!$F$2:$F$131,MATCH(B9,LIST!$B$2:$B$131,0)),"") -> g | E9: =IFERROR(INDEX(LIST!$G$2:$G$131,MATCH(B9,LIST!$B$2:$B$131,0)),0) -> 0.00045 | F9: =C9*E9 -> 0.07875
A10: 6 | B10: Rice Broken | C10: 175 | D10: =IFERROR(INDEX(LIST!$F$2:$F$131,MATCH(B10,LIST!$B$2:$B$131,0)),"") -> g | E10: =IFERROR(INDEX(LIST!$G$2:$G$131,MATCH(B10,LIST!$B$2:$B$131,0)),0) -> 0.0003 | F10: =C10*E10 -> 0.0525
A11: 7 | B11: ChickPeas | C11: 175 | D11: =IFERROR(INDEX(LIST!$F$2:$F$131,MATCH(B11,LIST!$B$2:$B$131,0)),"") -> g | E11: =IFERROR(INDEX(LIST!$G$2:$G$131,MATCH(B11,LIST!$B$2:$B$131,0)),0) -> 0.00066 | F11: =C11*E11 -> 0.1155
A12: 8 | B12: Dill Leaves | C12: 60 | D12: =IFERROR(INDEX(LIST!$F$2:$F$131,MATCH(B12,LIST!$B$2:$B$131,0)),"") -> g | E12: =IFERROR(INDEX(LIST!$G$2:$G$131,MATCH(B12,LIST!$B$2:$B$131,0)),0) -> 0.0015 | F12: =C12*E12 -> 0.09
A13: 9 | B13: Coriander Leaves | C13: 55 | D13: =IFERROR(INDEX(LIST!$F$2:$F$131,MATCH(B13,LIST!$B$2:$B$131,0)),"") -> g | E13: =IFERROR(INDEX(LIST!$G$2:$G$131,MATCH(B13,LIST!$B$2:$B$131,0)),0) -> 0.0017272727 | F13: =C13*E13 -> 0.095
A14: 10 | B14: Bagal Leaves | C14: 50 | D14: =IFERROR(INDEX(LIST!$F$2:$F$131,MATCH(B14,LIST!$B$2:$B$131,0)),"") -> g | E14: =IFERROR(INDEX(LIST!$G$2:$G$131,MATCH(B14,LIST!$B$2:$B$131,0)),0) -> 0.0008 | F14: =C14*E14 -> 0.04
A15: 11 | B15: Parsely Leaves | C15: 55 | D15: =IFERROR(INDEX(LIST!$F$2:$F$131,MATCH(B15,LIST!$B$2:$B$131,0)),"") -> g | E15: =IFERROR(INDEX(LIST!$G$2:$G$131,MATCH(B15,LIST!$B$2:$B$131,0)),0) -> 0.0018181818 | F15: =C15*E15 -> 0.1
A16: 12 | B16: Spinach Leaves | C16: 100 | D16: =IFERROR(INDEX(LIST!$F$2:$F$131,MATCH(B16,LIST!$B$2:$B$131,0)),"") -> g | E16: =IFERROR(INDEX(LIST!$G$2:$G$131,MATCH(B16,LIST!$B$2:$B$131,0)),0) -> 0.0008 | F16: =C16*E16 -> 0.08
... A22: 18 | B22: Turmeric Powder | C22: 22 | D22: =IFERROR(INDEX(LIST!$F$2:$F$131,MATCH(B22,LIST!$B$2:$B$131,0)),"") -> g | E22: =IFERROR(INDEX(LIST!$G$2:$G$131,MATCH(B22,LIST!$B$2:$B$131,0)),0) -> 0.0018 | F22: =C22*E22 -> 0.0396
B23: TOTAL RECIPE COST | F23: =SUM(F5:F22) -> 1.382401
B25: Size | C25: Single | D25: Small | E25: Medium | F25: Large
B26: Containers per recipe | C26: 18 | D26: 11 | E26: 7 | F26: 4
B27: Ingredient cost | C27: =IF(C26=0,0,$F$23/C26) -> 0.076800056 | D27: =IF(D26=0,0,$F$23/D26) -> 0.12567282 | E27: =IF(E26=0,0,$F$23/E26) -> 0.19748586 | F27: =IF(F26=0,0,$F$23/F26) -> 0.34560025
B28: Container | C28: CONTENER NO : (1) | D28: CONTENER NO : (3) | E28: CONTENER NO : (4) | F28: CONTENER NO : (5)
B29: Container cost | C29: =IFERROR(INDEX(LIST!$G$2:$G$131,MATCH(C28,LIST!$B$2:$B$131,0)),0) -> 0.025 | D29: =IFERROR(INDEX(LIST!$G$2:$G$131,MATCH(D28,LIST!$B$2:$B$131,0)),0) -> 0.021 | E29: =IFERROR(INDEX(LIST!$G$2:$G$131,MATCH(E28,LIST!$B$2:$B$131,0)),0) -> 0.0315 | F29: =IFERROR(INDEX(LIST!$G$2:$G$131,MATCH(F28,LIST!$B$2:$B$131,0)),0) -> 0.11666667
B30: Spoons (qty) | C30: 1 | D30: 1 | E30: 2 | F30: 3
B31: Spoon cost | C31: =C30*IFERROR(INDEX(LIST!$G$2:$G$131,MATCH("SPOON",LIST!$B$2:$B$131,0)),0) -> 0.0064 | D31: =D30*IFERROR(INDEX(LIST!$G$2:$G$131,MATCH("SPOON",LIST!$B$2:$B$131,0)),0) -> 0.0064 | E31: =E30*IFERROR(INDEX(LIST!$G$2:$G$131,MATCH("SPOON",LIST!$B$2:$B$131,0)),0) -> 0.0128 | F31: =F30*IFERROR(INDEX(LIST!$G$2:$G$131,MATCH("SPOON",LIST!$B$2:$B$131,0)),0) -> 0.0192
B32: Bread (qty) | C32: 0 | D32: 0 | E32: 0 | F32: 0
B33: Bread cost | C33: =C32*IFERROR(INDEX(LIST!$G$2:$G$131,MATCH("Bread",LIST!$B$2:$B$131,0)),0) -> 0 | D33: =D32*IFERROR(INDEX(LIST!$G$2:$G$131,MATCH("Bread",LIST!$B$2:$B$131,0)),0) -> 0 | E33: =E32*IFERROR(INDEX(LIST!$G$2:$G$131,MATCH("Bread",LIST!$B$2:$B$131,0)),0) -> 0 | F33: =F32*IFERROR(INDEX(LIST!$G$2:$G$131,MATCH("Bread",LIST!$B$2:$B$131,0)),0) -> 0
B34: Bag | C34: Bag XS | D34: Bag Small | E34: Bag Medium | F34: Bag Large
B35: Bag cost | C35: =IFERROR(INDEX(LIST!$G$2:$G$131,MATCH(C34,LIST!$B$2:$B$131,0)),0) -> 0.01 | D35: =IFERROR(INDEX(LIST!$G$2:$G$131,MATCH(D34,LIST!$B$2:$B$131,0)),0) -> 0.02 | E35: =IFERROR(INDEX(LIST!$G$2:$G$131,MATCH(E34,LIST!$B$2:$B$131,0)),0) -> 0.03 | F35: =IFERROR(INDEX(LIST!$G$2:$G$131,MATCH(F34,LIST!$B$2:$B$131,0)),0) -> 0.04
B36: Other costs | C36: 0 | D36: 0 | E36: 0 | F36: 0
B37: Packaging total | C37: =C29+C31+C33+C35+C36 -> 0.0414 | D37: =D29+D31+D33+D35+D36 -> 0.0474 | E37: =E29+E31+E33+E35+E36 -> 0.0743 | F37: =F29+F31+F33+F35+F36 -> 0.17586667
B38: TOTAL COST | C38: =C27+C37 -> 0.11820006 | D38: =D27+D37 -> 0.17307282 | E38: =E27+E37 -> 0.27178586 | F38: =F27+F37 -> 0.52146692
B39: Store price | C39: 0.6 | D39: 1 | E39: 1.6 | F39: 2.9
B40: Store cost % | C40: =IF(C39=0,"",C38/C39) -> 0.19700009 | D40: =IF(D39=0,"",D38/D39) -> 0.17307282 | E40: =IF(E39=0,"",E38/E39) -> 0.16986616 | F40: =IF(F39=0,"",F38/F39) -> 0.17981618
B41: Delivery price | C41: 0.6 | D41: 1.35 | E41: 2.2 | F41: 3.8
B42: Delivery cost % | C42: =IF(N(C41)=0,"",C38/C41) -> 0.19700009 | D42: =IF(N(D41)=0,"",D38/D41) -> 0.12820209 | E42: =IF(N(E41)=0,"",E38/E41) -> 0.12353903 | F42: =IF(N(F41)=0,"",F38/F41) -> 0.13722814
B43: Store profit | C43: =C39-C38 -> 0.48179994 | D43: =D39-D38 -> 0.82692718 | E43: =E39-E38 -> 1.3282141 | F43: =F39-F38 -> 2.3785331
B44: Delivery profit | C44: =IF(N(C41)=0,"",C41-C38) -> 0.48179994 | D44: =IF(N(D41)=0,"",D41-D38) -> 1.1769272 | E44: =IF(N(E41)=0,"",E41-E38) -> 1.9282141 | F44: =IF(N(F41)=0,"",F41-F38) -> 3.2785331

Sheet Madrooba
A1: Madrooba
A2: Traditional · one recipe fills several containers · target 30%
A4: # | B4: Item | C4: Qty | D4: Unit | E4: Unit price | F4: Cost
A5: 1 | B5: Chicken Breast | C5: 500 | D5: =IFERROR(INDEX(LIST!$F$2:$F$131,MATCH(B5,LIST!$B$2:$B$131,0)),"") -> g | E5: =IFERROR(INDEX(LIST!$G$2:$G$131,MATCH(B5,LIST!$B$2:$B$131,0)),0) -> 0.0015 | F5: =C5*E5 -> 0.75
A6: 2 | B6: Rice Broken | C6: 1000 | D6: =IFERROR(INDEX(LIST!$F$2:$F$131,MATCH(B6,LIST!$B$2:$B$131,0)),"") -> g | E6: =IFERROR(INDEX(LIST!$G$2:$G$131,MATCH(B6,LIST!$B$2:$B$131,0)),0) -> 0.0003 | F6: =C6*E6 -> 0.3
A7: 3 | B7: Onion | C7: 300 | D7: =IFERROR(INDEX(LIST!$F$2:$F$131,MATCH(B7,LIST!$B$2:$B$131,0)),"") -> g | E7: =IFERROR(INDEX(LIST!$G$2:$G$131,MATCH(B7,LIST!$B$2:$B$131,0)),0) -> 0.00045 | F7: =C7*E7 -> 0.135
A8: 4 | B8: Tomato Paste | C8: 1000 | D8: =IFERROR(INDEX(LIST!$F$2:$F$131,MATCH(B8,LIST!$B$2:$B$131,0)),"") -> g | E8: =IFERROR(INDEX(LIST!$G$2:$G$131,MATCH(B8,LIST!$B$2:$B$131,0)),0) -> 0.0006 | F8: =C8*E8 -> 0.6
A9: 5 | B9: Green Capiscum | C9: 50 | D9: =IFERROR(INDEX(LIST!$F$2:$F$131,MATCH(B9,LIST!$B$2:$B$131,0)),"") -> g | E9: =IFERROR(INDEX(LIST!$G$2:$G$131,MATCH(B9,LIST!$B$2:$B$131,0)),0) -> 0.00065 | F9: =C9*E9 -> 0.0325
A10: 6 | B10: Ginger + Garlic Mix | C10: 45 | D10: =IFERROR(INDEX(LIST!$F$2:$F$131,MATCH(B10,LIST!$B$2:$B$131,0)),"") -> g | E10: =IFERROR(INDEX(LIST!$G$2:$G$131,MATCH(B10,LIST!$B$2:$B$131,0)),0) -> 0.0012 | F10: =C10*E10 -> 0.054
A11: 7 | B11: Green Chilly | C11: 10 | D11: =IFERROR(INDEX(LIST!$F$2:$F$131,MATCH(B11,LIST!$B$2:$B$131,0)),"") -> g | E11: =IFERROR(INDEX(LIST!$G$2:$G$131,MATCH(B11,LIST!$B$2:$B$131,0)),0) -> 0.0008 | F11: =C11*E11 -> 0.008
A12: 8 | B12: Spinach Leaves | C12: 200 | D12: =IFERROR(INDEX(LIST!$F$2:$F$131,MATCH(B12,LIST!$B$2:$B$131,0)),"") -> g | E12: =IFERROR(INDEX(LIST!$G$2:$G$131,MATCH(B12,LIST!$B$2:$B$131,0)),0) -> 0.0008 | F12: =C12*E12 -> 0.16
A13: 9 | B13: Bagal Leaves | C13: 200 | D13: =IFERROR(INDEX(LIST!$F$2:$F$131,MATCH(B13,LIST!$B$2:$B$131,0)),"") -> g | E13: =IFERROR(INDEX(LIST!$G$2:$G$131,MATCH(B13,LIST!$B$2:$B$131,0)),0) -> 0.0008 | F13: =C13*E13 -> 0.16
A14: 10 | B14: Coriander Leaves | C14: 200 | D14: =IFERROR(INDEX(LIST!$F$2:$F$131,MATCH(B14,LIST!$B$2:$B$131,0)),"") -> g | E14: =IFERROR(INDEX(LIST!$G$2:$G$131,MATCH(B14,LIST!$B$2:$B$131,0)),0) -> 0.0017272727 | F14: =C14*E14 -> 0.34545455
A15: 11 | B15: Dill Leaves | C15: 200 | D15: =IFERROR(INDEX(LIST!$F$2:$F$131,MATCH(B15,LIST!$B$2:$B$131,0)),"") -> g | E15: =IFERROR(INDEX(LIST!$G$2:$G$131,MATCH(B15,LIST!$B$2:$B$131,0)),0) -> 0.0015 | F15: =C15*E15 -> 0.3
A16: 12 | B16: Vegetable Oil | C16: 100 | D16: =IFERROR(INDEX(LIST!$F$2:$F$131,MATCH(B16,LIST!$B$2:$B$131,0)),"") -> ml | E16: =IFERROR(INDEX(LIST!$G$2:$G$131,MATCH(B16,LIST!$B$2:$B$131,0)),0) -> 0.000594 | F16: =C16*E16 -> 0.0594
... A25: 21 | B25: Salt | C25: 22.5 | D25: =IFERROR(INDEX(LIST!$F$2:$F$131,MATCH(B25,LIST!$B$2:$B$131,0)),"") -> g | E25: =IFERROR(INDEX(LIST!$G$2:$G$131,MATCH(B25,LIST!$B$2:$B$131,0)),0) -> 0.000165 | F25: =C25*E25 -> 0.0037125
B26: TOTAL RECIPE COST | F26: =SUM(F5:F25) -> 3.185617
B28: Size | C28: Single | D28: Small | E28: Medium | F28: Large
B29: Containers per recipe | C29: 28 | D29: 16 | E29: 8 | F29: 4
B30: Ingredient cost | C30: =IF(C29=0,0,$F$26/C29) -> 0.11377204 | D30: =IF(D29=0,0,$F$26/D29) -> 0.19910107 | E30: =IF(E29=0,0,$F$26/E29) -> 0.39820213 | F30: =IF(F29=0,0,$F$26/F29) -> 0.79640426
B31: Container | C31: CONTENER NO : (1) | D31: CONTENER NO : (3) | E31: CONTENER NO : (4) | F31: CONTENER NO : (5)
B32: Container cost | C32: =IFERROR(INDEX(LIST!$G$2:$G$131,MATCH(C31,LIST!$B$2:$B$131,0)),0) -> 0.025 | D32: =IFERROR(INDEX(LIST!$G$2:$G$131,MATCH(D31,LIST!$B$2:$B$131,0)),0) -> 0.021 | E32: =IFERROR(INDEX(LIST!$G$2:$G$131,MATCH(E31,LIST!$B$2:$B$131,0)),0) -> 0.0315 | F32: =IFERROR(INDEX(LIST!$G$2:$G$131,MATCH(F31,LIST!$B$2:$B$131,0)),0) -> 0.11666667
B33: Spoons (qty) | C33: 1 | D33: 1 | E33: 2 | F33: 3
B34: Spoon cost | C34: =C33*IFERROR(INDEX(LIST!$G$2:$G$131,MATCH("SPOON",LIST!$B$2:$B$131,0)),0) -> 0.0064 | D34: =D33*IFERROR(INDEX(LIST!$G$2:$G$131,MATCH("SPOON",LIST!$B$2:$B$131,0)),0) -> 0.0064 | E34: =E33*IFERROR(INDEX(LIST!$G$2:$G$131,MATCH("SPOON",LIST!$B$2:$B$131,0)),0) -> 0.0128 | F34: =F33*IFERROR(INDEX(LIST!$G$2:$G$131,MATCH("SPOON",LIST!$B$2:$B$131,0)),0) -> 0.0192
B35: Bread (qty) | C35: 0.5 | D35: 1 | E35: 2 | F35: 4
B36: Bread cost | C36: =C35*IFERROR(INDEX(LIST!$G$2:$G$131,MATCH("Bread",LIST!$B$2:$B$131,0)),0) -> 0.006 | D36: =D35*IFERROR(INDEX(LIST!$G$2:$G$131,MATCH("Bread",LIST!$B$2:$B$131,0)),0) -> 0.012 | E36: =E35*IFERROR(INDEX(LIST!$G$2:$G$131,MATCH("Bread",LIST!$B$2:$B$131,0)),0) -> 0.024 | F36: =F35*IFERROR(INDEX(LIST!$G$2:$G$131,MATCH("Bread",LIST!$B$2:$B$131,0)),0) -> 0.048
B37: Bag | C37: Bag XS | D37: Bag Small | E37: Bag Medium | F37: Bag Large
B38: Bag cost | C38: =IFERROR(INDEX(LIST!$G$2:$G$131,MATCH(C37,LIST!$B$2:$B$131,0)),0) -> 0.01 | D38: =IFERROR(INDEX(LIST!$G$2:$G$131,MATCH(D37,LIST!$B$2:$B$131,0)),0) -> 0.02 | E38: =IFERROR(INDEX(LIST!$G$2:$G$131,MATCH(E37,LIST!$B$2:$B$131,0)),0) -> 0.03 | F38: =IFERROR(INDEX(LIST!$G$2:$G$131,MATCH(F37,LIST!$B$2:$B$131,0)),0) -> 0.04
B39: Other costs | C39: 0 | D39: 0 | E39: 0 | F39: 0
B40: Packaging total | C40: =C32+C34+C36+C38+C39 -> 0.0474 | D40: =D32+D34+D36+D38+D39 -> 0.0594 | E40: =E32+E34+E36+E38+E39 -> 0.0983 | F40: =F32+F34+F36+F38+F39 -> 0.22386667
B41: TOTAL COST | C41: =C30+C40 -> 0.16117204 | D41: =D30+D40 -> 0.25850107 | E41: =E30+E40 -> 0.49650213 | F41: =F30+F40 -> 1.0202709
B42: Store price | C42: 0.6 | D42: 1.1 | E42: 1.8 | F42: 3.2
B43: Store cost % | C43: =IF(C42=0,"",C41/C42) -> 0.26862006 | D43: =IF(D42=0,"",D41/D42) -> 0.23500097 | E43: =IF(E42=0,"",E41/E42) -> 0.27583452 | F43: =IF(F42=0,"",F41/F42) -> 0.31883467
B44: Delivery price | C44: 0.6 | D44: 1.35 | E44: 2.4 | F44: 4.4
B45: Delivery cost % | C45: =IF(N(C44)=0,"",C41/C44) -> 0.26862006 | D45: =IF(N(D44)=0,"",D41/D44) -> 0.19148227 | E45: =IF(N(E44)=0,"",E41/E44) -> 0.20687589 | F45: =IF(N(F44)=0,"",F41/F44) -> 0.23187976
B46: Store profit | C46: =C42-C41 -> 0.43882796 | D46: =D42-D41 -> 0.84149893 | E46: =E42-E41 -> 1.3034979 | F46: =F42-F41 -> 2.1797291
B47: Delivery profit | C47: =IF(N(C44)=0,"",C44-C41) -> 0.43882796 | D47: =IF(N(D44)=0,"",D44-D41) -> 1.0914989 | E47: =IF(N(E44)=0,"",E44-E41) -> 1.9034979 | F47: =IF(N(F44)=0,"",F44-F41) -> 3.3797291

Sheet Beef Liver
A1: Beef Liver
A2: Main dishes · one recipe fills several containers · target 30%
A4: # | B4: Item | C4: Qty | D4: Unit | E4: Unit price | F4: Cost
A5: 1 | B5: Beef Liver | C5: 1000 | D5: =IFERROR(INDEX(LIST!$F$2:$F$131,MATCH(B5,LIST!$B$2:$B$131,0)),"") -> g | E5: =IFERROR(INDEX(LIST!$G$2:$G$131,MATCH(B5,LIST!$B$2:$B$131,0)),0) -> 0.001409 | F5: =C5*E5 -> 1.409
A6: 2 | B6: Lemon | C6: 50 | D6: =IFERROR(INDEX(LIST!$F$2:$F$131,MATCH(B6,LIST!$B$2:$B$131,0)),"") -> g | E6: =IFERROR(INDEX(LIST!$G$2:$G$131,MATCH(B6,LIST!$B$2:$B$131,0)),0) -> 0.001 | F6: =C6*E6 -> 0.05
A7: 3 | B7: Long Chilly | C7: 15 | D7: =IFERROR(INDEX(LIST!$F$2:$F$131,MATCH(B7,LIST!$B$2:$B$131,0)),"") -> g | E7: =IFERROR(INDEX(LIST!$G$2:$G$131,MATCH(B7,LIST!$B$2:$B$131,0)),0) -> 0.0011 | F7: =C7*E7 -> 0.0165
A8: 4 | B8: Onion | C8: 240 | D8: =IFERROR(INDEX(LIST!$F$2:$F$131,MATCH(B8,LIST!$B$2:$B$131,0)),"") -> g | E8: =IFERROR(INDEX(LIST!$G$2:$G$131,MATCH(B8,LIST!$B$2:$B$131,0)),0) -> 0.00045 | F8: =C8*E8 -> 0.108
A9: 5 | B9: Green Capiscum | C9: 90 | D9: =IFERROR(INDEX(LIST!$F$2:$F$131,MATCH(B9,LIST!$B$2:$B$131,0)),"") -> g | E9: =IFERROR(INDEX(LIST!$G$2:$G$131,MATCH(B9,LIST!$B$2:$B$131,0)),0) -> 0.00065 | F9: =C9*E9 -> 0.0585
A10: 6 | B10: Tomato | C10: 720 | D10: =IFERROR(INDEX(LIST!$F$2:$F$131,MATCH(B10,LIST!$B$2:$B$131,0)),"") -> g | E10: =IFERROR(INDEX(LIST!$G$2:$G$131,MATCH(B10,LIST!$B$2:$B$131,0)),0) -> 0.0005 | F10: =C10*E10 -> 0.36
A11: 7 | B11: Garlic Peeled | C11: 15 | D11: =IFERROR(INDEX(LIST!$F$2:$F$131,MATCH(B11,LIST!$B$2:$B$131,0)),"") -> g | E11: =IFERROR(INDEX(LIST!$G$2:$G$131,MATCH(B11,LIST!$B$2:$B$131,0)),0) -> 0.0015 | F11: =C11*E11 -> 0.0225
A12: 8 | B12: Coriander Leaves | C12: 5 | D12: =IFERROR(INDEX(LIST!$F$2:$F$131,MATCH(B12,LIST!$B$2:$B$131,0)),"") -> g | E12: =IFERROR(INDEX(LIST!$G$2:$G$131,MATCH(B12,LIST!$B$2:$B$131,0)),0) -> 0.0017272727 | F12: =C12*E12 -> 0.0086363636
A13: 9 | B13: Vegetable Oil | C13: 180 | D13: =IFERROR(INDEX(LIST!$F$2:$F$131,MATCH(B13,LIST!$B$2:$B$131,0)),"") -> ml | E13: =IFERROR(INDEX(LIST!$G$2:$G$131,MATCH(B13,LIST!$B$2:$B$131,0)),0) -> 0.000594 | F13: =C13*E13 -> 0.10692
A14: 10 | B14: Salt | C14: 10 | D14: =IFERROR(INDEX(LIST!$F$2:$F$131,MATCH(B14,LIST!$B$2:$B$131,0)),"") -> g | E14: =IFERROR(INDEX(LIST!$G$2:$G$131,MATCH(B14,LIST!$B$2:$B$131,0)),0) -> 0.000165 | F14: =C14*E14 -> 0.00165
A15: 11 | B15: Cummin Powder | C15: 15 | D15: =IFERROR(INDEX(LIST!$F$2:$F$131,MATCH(B15,LIST!$B$2:$B$131,0)),"") -> g | E15: =IFERROR(INDEX(LIST!$G$2:$G$131,MATCH(B15,LIST!$B$2:$B$131,0)),0) -> 0.002818 | F15: =C15*E15 -> 0.04227
A16: 12 | B16: Black Pepper Powder | C16: 10 | D16: =IFERROR(INDEX(LIST!$F$2:$F$131,MATCH(B16,LIST!$B$2:$B$131,0)),"") -> g | E16: =IFERROR(INDEX(LIST!$G$2:$G$131,MATCH(B16,LIST!$B$2:$B$131,0)),0) -> 0.002272 | F16: =C16*E16 -> 0.02272
... A18: 14 | B18: Mix Masala Powder | C18: 15 | D18: =IFERROR(INDEX(LIST!$F$2:$F$131,MATCH(B18,LIST!$B$2:$B$131,0)),"") -> g | E18: =IFERROR(INDEX(LIST!$G$2:$G$131,MATCH(B18,LIST!$B$2:$B$131,0)),0) -> 0.00165 | F18: =C18*E18 -> 0.02475
B19: TOTAL RECIPE COST | F19: =SUM(F5:F18) -> 2.2914464
B21: Size | C21: Small | D21: Medium | E21: Large
B22: Containers per recipe | C22: 5 | D22: 2.5 | E22: 1.5
B23: Ingredient cost | C23: =IF(C22=0,0,$F$19/C22) -> 0.45828927 | D23: =IF(D22=0,0,$F$19/D22) -> 0.91657855 | E23: =IF(E22=0,0,$F$19/E22) -> 1.5276309
B24: Container | C24: CONTENER NO : (3) | D24: CONTENER NO : (4) | E24: CONTENER NO : (5)
B25: Container cost | C25: =IFERROR(INDEX(LIST!$G$2:$G$131,MATCH(C24,LIST!$B$2:$B$131,0)),0) -> 0.021 | D25: =IFERROR(INDEX(LIST!$G$2:$G$131,MATCH(D24,LIST!$B$2:$B$131,0)),0) -> 0.0315 | E25: =IFERROR(INDEX(LIST!$G$2:$G$131,MATCH(E24,LIST!$B$2:$B$131,0)),0) -> 0.11666667
B26: Spoons (qty) | C26: 1 | D26: 2 | E26: 3
B27: Spoon cost | C27: =C26*IFERROR(INDEX(LIST!$G$2:$G$131,MATCH("SPOON",LIST!$B$2:$B$131,0)),0) -> 0.0064 | D27: =D26*IFERROR(INDEX(LIST!$G$2:$G$131,MATCH("SPOON",LIST!$B$2:$B$131,0)),0) -> 0.0128 | E27: =E26*IFERROR(INDEX(LIST!$G$2:$G$131,MATCH("SPOON",LIST!$B$2:$B$131,0)),0) -> 0.0192
B28: Bread (qty) | C28: 0.667 | D28: 2 | E28: 4
B29: Bread cost | C29: =C28*IFERROR(INDEX(LIST!$G$2:$G$131,MATCH("Bread",LIST!$B$2:$B$131,0)),0) -> 0.008004 | D29: =D28*IFERROR(INDEX(LIST!$G$2:$G$131,MATCH("Bread",LIST!$B$2:$B$131,0)),0) -> 0.024 | E29: =E28*IFERROR(INDEX(LIST!$G$2:$G$131,MATCH("Bread",LIST!$B$2:$B$131,0)),0) -> 0.048
B30: Bag | C30: Bag Small | D30: Bag Medium | E30: Bag Large
B31: Bag cost | C31: =IFERROR(INDEX(LIST!$G$2:$G$131,MATCH(C30,LIST!$B$2:$B$131,0)),0) -> 0.02 | D31: =IFERROR(INDEX(LIST!$G$2:$G$131,MATCH(D30,LIST!$B$2:$B$131,0)),0) -> 0.03 | E31: =IFERROR(INDEX(LIST!$G$2:$G$131,MATCH(E30,LIST!$B$2:$B$131,0)),0) -> 0.04
B32: Other costs | C32: 0 | D32: 0 | E32: 0
B33: Packaging total | C33: =C25+C27+C29+C31+C32 -> 0.055404 | D33: =D25+D27+D29+D31+D32 -> 0.0983 | E33: =E25+E27+E29+E31+E32 -> 0.22386667
B34: TOTAL COST | C34: =C23+C33 -> 0.51369327 | D34: =D23+D33 -> 1.0148785 | E34: =E23+E33 -> 1.7514976
B35: Store price | C35: 1.8 | D35: 3.4 | E35: 6.2
B36: Store cost % | C36: =IF(C35=0,"",C34/C35) -> 0.28538515 | D36: =IF(D35=0,"",D34/D35) -> 0.29849369 | E36: =IF(E35=0,"",E34/E35) -> 0.28249961
B37: Delivery price | C37: 2.2 | D37: 4 | E37: 7.5
B38: Delivery cost % | C38: =IF(N(C37)=0,"",C34/C37) -> 0.23349694 | D38: =IF(N(D37)=0,"",D34/D37) -> 0.25371964 | E38: =IF(N(E37)=0,"",E34/E37) -> 0.23353301
B39: Store profit | C39: =C35-C34 -> 1.2863067 | D39: =D35-D34 -> 2.3851215 | E39: =E35-E34 -> 4.4485024
B40: Delivery profit | C40: =IF(N(C37)=0,"",C37-C34) -> 1.6863067 | D40: =IF(N(D37)=0,"",D37-D34) -> 2.9851215 | E40: =IF(N(E37)=0,"",E37-E34) -> 5.7485024

Sheet Chicken Liver
A1: Chicken Liver
A2: Main dishes · one recipe fills several containers · target 30%
A4: # | B4: Item | C4: Qty | D4: Unit | E4: Unit price | F4: Cost
A5: 1 | B5: Chicken Liver | C5: 450 | D5: =IFERROR(INDEX(LIST!$F$2:$F$131,MATCH(B5,LIST!$B$2:$B$131,0)),"") -> g | E5: =IFERROR(INDEX(LIST!$G$2:$G$131,MATCH(B5,LIST!$B$2:$B$131,0)),0) -> 0.00085777778 | F5: =C5*E5 -> 0.386
A6: 2 | B6: Green Chilly | C6: 10 | D6: =IFERROR(INDEX(LIST!$F$2:$F$131,MATCH(B6,LIST!$B$2:$B$131,0)),"") -> g | E6: =IFERROR(INDEX(LIST!$G$2:$G$131,MATCH(B6,LIST!$B$2:$B$131,0)),0) -> 0.0008 | F6: =C6*E6 -> 0.008
A7: 3 | B7: Green Capiscum | C7: 45 | D7: =IFERROR(INDEX(LIST!$F$2:$F$131,MATCH(B7,LIST!$B$2:$B$131,0)),"") -> g | E7: =IFERROR(INDEX(LIST!$G$2:$G$131,MATCH(B7,LIST!$B$2:$B$131,0)),0) -> 0.00065 | F7: =C7*E7 -> 0.02925
A8: 4 | B8: Potato | C8: 480 | D8: =IFERROR(INDEX(LIST!$F$2:$F$131,MATCH(B8,LIST!$B$2:$B$131,0)),"") -> g | E8: =IFERROR(INDEX(LIST!$G$2:$G$131,MATCH(B8,LIST!$B$2:$B$131,0)),0) -> 0.00036 | F8: =C8*E8 -> 0.1728
A9: 5 | B9: Eggplant | C9: 240 | D9: =IFERROR(INDEX(LIST!$F$2:$F$131,MATCH(B9,LIST!$B$2:$B$131,0)),"") -> g | E9: =IFERROR(INDEX(LIST!$G$2:$G$131,MATCH(B9,LIST!$B$2:$B$131,0)),0) -> 0.00055 | F9: =C9*E9 -> 0.132
A10: 6 | B10: Tomato | C10: 240 | D10: =IFERROR(INDEX(LIST!$F$2:$F$131,MATCH(B10,LIST!$B$2:$B$131,0)),"") -> g | E10: =IFERROR(INDEX(LIST!$G$2:$G$131,MATCH(B10,LIST!$B$2:$B$131,0)),0) -> 0.0005 | F10: =C10*E10 -> 0.12
A11: 7 | B11: Onion | C11: 180 | D11: =IFERROR(INDEX(LIST!$F$2:$F$131,MATCH(B11,LIST!$B$2:$B$131,0)),"") -> g | E11: =IFERROR(INDEX(LIST!$G$2:$G$131,MATCH(B11,LIST!$B$2:$B$131,0)),0) -> 0.00045 | F11: =C11*E11 -> 0.081
A12: 8 | B12: Vegetable Oil | C12: 60 | D12: =IFERROR(INDEX(LIST!$F$2:$F$131,MATCH(B12,LIST!$B$2:$B$131,0)),"") -> ml | E12: =IFERROR(INDEX(LIST!$G$2:$G$131,MATCH(B12,LIST!$B$2:$B$131,0)),0) -> 0.000594 | F12: =C12*E12 -> 0.03564
A13: 9 | B13: Annar Sause | C13: 30 | D13: =IFERROR(INDEX(LIST!$F$2:$F$131,MATCH(B13,LIST!$B$2:$B$131,0)),"") -> g | E13: =IFERROR(INDEX(LIST!$G$2:$G$131,MATCH(B13,LIST!$B$2:$B$131,0)),0) -> 0.00075 | F13: =C13*E13 -> 0.0225
A14: 10 | B14: Tahina | C14: 30 | D14: =IFERROR(INDEX(LIST!$F$2:$F$131,MATCH(B14,LIST!$B$2:$B$131,0)),"") -> g | E14: =IFERROR(INDEX(LIST!$G$2:$G$131,MATCH(B14,LIST!$B$2:$B$131,0)),0) -> 0.0009696 | F14: =C14*E14 -> 0.029088
A15: 11 | B15: Vinger | C15: 30 | D15: =IFERROR(INDEX(LIST!$F$2:$F$131,MATCH(B15,LIST!$B$2:$B$131,0)),"") -> g | E15: =IFERROR(INDEX(LIST!$G$2:$G$131,MATCH(B15,LIST!$B$2:$B$131,0)),0) -> 0.00016666667 | F15: =C15*E15 -> 0.005
A16: 12 | B16: Olive Oil | C16: 30 | D16: =IFERROR(INDEX(LIST!$F$2:$F$131,MATCH(B16,LIST!$B$2:$B$131,0)),"") -> ml | E16: =IFERROR(INDEX(LIST!$G$2:$G$131,MATCH(B16,LIST!$B$2:$B$131,0)),0) -> 0.000308 | F16: =C16*E16 -> 0.00924
... A24: 20 | B24: Cummin Powder | C24: 2.5 | D24: =IFERROR(INDEX(LIST!$F$2:$F$131,MATCH(B24,LIST!$B$2:$B$131,0)),"") -> g | E24: =IFERROR(INDEX(LIST!$G$2:$G$131,MATCH(B24,LIST!$B$2:$B$131,0)),0) -> 0.002818 | F24: =C24*E24 -> 0.007045
B25: TOTAL RECIPE COST | F25: =SUM(F5:F24) -> 1.099843
B27: Size | C27: Small | D27: Medium | E27: Large
B28: Containers per recipe | C28: 2 | D28: 1 | E28: 0.5
B29: Ingredient cost | C29: =IF(C28=0,0,$F$25/C28) -> 0.5499215 | D29: =IF(D28=0,0,$F$25/D28) -> 1.099843 | E29: =IF(E28=0,0,$F$25/E28) -> 2.199686
B30: Container | C30: CONTENER NO : (3) | D30: CONTENER NO : (4) | E30: CONTENER NO : (5)
B31: Container cost | C31: =IFERROR(INDEX(LIST!$G$2:$G$131,MATCH(C30,LIST!$B$2:$B$131,0)),0) -> 0.021 | D31: =IFERROR(INDEX(LIST!$G$2:$G$131,MATCH(D30,LIST!$B$2:$B$131,0)),0) -> 0.0315 | E31: =IFERROR(INDEX(LIST!$G$2:$G$131,MATCH(E30,LIST!$B$2:$B$131,0)),0) -> 0.11666667
B32: Spoons (qty) | C32: 1 | D32: 2 | E32: 3
B33: Spoon cost | C33: =C32*IFERROR(INDEX(LIST!$G$2:$G$131,MATCH("SPOON",LIST!$B$2:$B$131,0)),0) -> 0.0064 | D33: =D32*IFERROR(INDEX(LIST!$G$2:$G$131,MATCH("SPOON",LIST!$B$2:$B$131,0)),0) -> 0.0128 | E33: =E32*IFERROR(INDEX(LIST!$G$2:$G$131,MATCH("SPOON",LIST!$B$2:$B$131,0)),0) -> 0.0192
B34: Bread (qty) | C34: 0.667 | D34: 2 | E34: 2
B35: Bread cost | C35: =C34*IFERROR(INDEX(LIST!$G$2:$G$131,MATCH("Bread",LIST!$B$2:$B$131,0)),0) -> 0.008004 | D35: =D34*IFERROR(INDEX(LIST!$G$2:$G$131,MATCH("Bread",LIST!$B$2:$B$131,0)),0) -> 0.024 | E35: =E34*IFERROR(INDEX(LIST!$G$2:$G$131,MATCH("Bread",LIST!$B$2:$B$131,0)),0) -> 0.024
B36: Bag | C36: Bag Small | D36: Bag Medium | E36: Bag Medium
B37: Bag cost | C37: =IFERROR(INDEX(LIST!$G$2:$G$131,MATCH(C36,LIST!$B$2:$B$131,0)),0) -> 0.02 | D37: =IFERROR(INDEX(LIST!$G$2:$G$131,MATCH(D36,LIST!$B$2:$B$131,0)),0) -> 0.03 | E37: =IFERROR(INDEX(LIST!$G$2:$G$131,MATCH(E36,LIST!$B$2:$B$131,0)),0) -> 0.03
B38: Other costs | C38: 0 | D38: 0 | E38: 0
B39: Packaging total | C39: =C31+C33+C35+C37+C38 -> 0.055404 | D39: =D31+D33+D35+D37+D38 -> 0.0983 | E39: =E31+E33+E35+E37+E38 -> 0.18986667
B40: TOTAL COST | C40: =C29+C39 -> 0.6053255 | D40: =D29+D39 -> 1.198143 | E40: =E29+E39 -> 2.3895527
B41: Store price | C41: 2 | D41: 3.6 | E41: 6.8
B42: Store cost % | C42: =IF(C41=0,"",C40/C41) -> 0.30266275 | D42: =IF(D41=0,"",D40/D41) -> 0.3328175 | E42: =IF(E41=0,"",E40/E41) -> 0.3514048
B43: Delivery price | C43: 2.2 | D43: 4 | E43: 7.5
B44: Delivery cost % | C44: =IF(N(C43)=0,"",C40/C43) -> 0.27514795 | D44: =IF(N(D43)=0,"",D40/D43) -> 0.29953575 | E44: =IF(N(E43)=0,"",E40/E43) -> 0.31860702
B45: Store profit | C45: =C41-C40 -> 1.3946745 | D45: =D41-D40 -> 2.401857 | E45: =E41-E40 -> 4.4104473
B46: Delivery profit | C46: =IF(N(C43)=0,"",C43-C40) -> 1.5946745 | D46: =IF(N(D43)=0,"",D43-D40) -> 2.801857 | E46: =IF(N(E43)=0,"",E43-E40) -> 5.1104473

Sheet Qeema Meat
A1: Qeema Meat
A2: Main dishes · one recipe fills several containers · target 30%
A4: # | B4: Item | C4: Qty | D4: Unit | E4: Unit price | F4: Cost
A5: 1 | B5: Qeema Meat | C5: 2000 | D5: =IFERROR(INDEX(LIST!$F$2:$F$131,MATCH(B5,LIST!$B$2:$B$131,0)),"") -> g | E5: =IFERROR(INDEX(LIST!$G$2:$G$131,MATCH(B5,LIST!$B$2:$B$131,0)),0) -> 0.0022 | F5: =C5*E5 -> 4.4
A6: 2 | B6: Onion | C6: 500 | D6: =IFERROR(INDEX(LIST!$F$2:$F$131,MATCH(B6,LIST!$B$2:$B$131,0)),"") -> g | E6: =IFERROR(INDEX(LIST!$G$2:$G$131,MATCH(B6,LIST!$B$2:$B$131,0)),0) -> 0.00045 | F6: =C6*E6 -> 0.225
A7: 3 | B7: Potato | C7: 1000 | D7: =IFERROR(INDEX(LIST!$F$2:$F$131,MATCH(B7,LIST!$B$2:$B$131,0)),"") -> g | E7: =IFERROR(INDEX(LIST!$G$2:$G$131,MATCH(B7,LIST!$B$2:$B$131,0)),0) -> 0.00036 | F7: =C7*E7 -> 0.36
A8: 4 | B8: Vegetable Oil | C8: 300 | D8: =IFERROR(INDEX(LIST!$F$2:$F$131,MATCH(B8,LIST!$B$2:$B$131,0)),"") -> ml | E8: =IFERROR(INDEX(LIST!$G$2:$G$131,MATCH(B8,LIST!$B$2:$B$131,0)),0) -> 0.000594 | F8: =C8*E8 -> 0.1782
A9: 5 | B9: Tomato Paste | C9: 240 | D9: =IFERROR(INDEX(LIST!$F$2:$F$131,MATCH(B9,LIST!$B$2:$B$131,0)),"") -> g | E9: =IFERROR(INDEX(LIST!$G$2:$G$131,MATCH(B9,LIST!$B$2:$B$131,0)),0) -> 0.0006 | F9: =C9*E9 -> 0.144
A10: 6 | B10: Salt | C10: 15 | D10: =IFERROR(INDEX(LIST!$F$2:$F$131,MATCH(B10,LIST!$B$2:$B$131,0)),"") -> g | E10: =IFERROR(INDEX(LIST!$G$2:$G$131,MATCH(B10,LIST!$B$2:$B$131,0)),0) -> 0.000165 | F10: =C10*E10 -> 0.002475
A11: 7 | B11: Green Peas Tin | C11: 0 | D11: =IFERROR(INDEX(LIST!$F$2:$F$131,MATCH(B11,LIST!$B$2:$B$131,0)),"") -> g | E11: =IFERROR(INDEX(LIST!$G$2:$G$131,MATCH(B11,LIST!$B$2:$B$131,0)),0) -> 0.00083684211 | F11: =C11*E11 -> 0
A12: 8 | B12: Chana Dal | C12: 0 | D12: =IFERROR(INDEX(LIST!$F$2:$F$131,MATCH(B12,LIST!$B$2:$B$131,0)),"") -> g | E12: =IFERROR(INDEX(LIST!$G$2:$G$131,MATCH(B12,LIST!$B$2:$B$131,0)),0) -> 0.000581 | F12: =C12*E12 -> 0
A13: 9 | B13: Black Lemone Whole | C13: 2 | D13: =IFERROR(INDEX(LIST!$F$2:$F$131,MATCH(B13,LIST!$B$2:$B$131,0)),"") -> g | E13: =IFERROR(INDEX(LIST!$G$2:$G$131,MATCH(B13,LIST!$B$2:$B$131,0)),0) -> 0.00176 | F13: =C13*E13 -> 0.00352
A14: 10 | B14: Mix Masala Powder | C14: 15 | D14: =IFERROR(INDEX(LIST!$F$2:$F$131,MATCH(B14,LIST!$B$2:$B$131,0)),"") -> g | E14: =IFERROR(INDEX(LIST!$G$2:$G$131,MATCH(B14,LIST!$B$2:$B$131,0)),0) -> 0.00165 | F14: =C14*E14 -> 0.02475
A15: 11 | B15: Cummin Powder | C15: 15 | D15: =IFERROR(INDEX(LIST!$F$2:$F$131,MATCH(B15,LIST!$B$2:$B$131,0)),"") -> g | E15: =IFERROR(INDEX(LIST!$G$2:$G$131,MATCH(B15,LIST!$B$2:$B$131,0)),0) -> 0.002818 | F15: =C15*E15 -> 0.04227
A16: 12 | B16: Coriander Powder | C16: 15 | D16: =IFERROR(INDEX(LIST!$F$2:$F$131,MATCH(B16,LIST!$B$2:$B$131,0)),"") -> g | E16: =IFERROR(INDEX(LIST!$G$2:$G$131,MATCH(B16,LIST!$B$2:$B$131,0)),0) -> 0.0018 | F16: =C16*E16 -> 0.027
... A19: 15 | B19: Turmeric Powder | C19: 15 | D19: =IFERROR(INDEX(LIST!$F$2:$F$131,MATCH(B19,LIST!$B$2:$B$131,0)),"") -> g | E19: =IFERROR(INDEX(LIST!$G$2:$G$131,MATCH(B19,LIST!$B$2:$B$131,0)),0) -> 0.0018 | F19: =C19*E19 -> 0.027
B20: TOTAL RECIPE COST | F20: =SUM(F5:F19) -> 5.518965
B22: Size | C22: Small | D22: Medium | E22: Large
B23: Containers per recipe | C23: 12 | D23: 6 | E23: 3
B24: Ingredient cost | C24: =IF(C23=0,0,$F$20/C23) -> 0.45991375 | D24: =IF(D23=0,0,$F$20/D23) -> 0.9198275 | E24: =IF(E23=0,0,$F$20/E23) -> 1.839655
B25: Container | C25: CONTENER NO : (3) | D25: CONTENER NO : (4) | E25: CONTENER NO : (5)
B26: Container cost | C26: =IFERROR(INDEX(LIST!$G$2:$G$131,MATCH(C25,LIST!$B$2:$B$131,0)),0) -> 0.021 | D26: =IFERROR(INDEX(LIST!$G$2:$G$131,MATCH(D25,LIST!$B$2:$B$131,0)),0) -> 0.0315 | E26: =IFERROR(INDEX(LIST!$G$2:$G$131,MATCH(E25,LIST!$B$2:$B$131,0)),0) -> 0.11666667
B27: Spoons (qty) | C27: 1 | D27: 2 | E27: 3
B28: Spoon cost | C28: =C27*IFERROR(INDEX(LIST!$G$2:$G$131,MATCH("SPOON",LIST!$B$2:$B$131,0)),0) -> 0.0064 | D28: =D27*IFERROR(INDEX(LIST!$G$2:$G$131,MATCH("SPOON",LIST!$B$2:$B$131,0)),0) -> 0.0128 | E28: =E27*IFERROR(INDEX(LIST!$G$2:$G$131,MATCH("SPOON",LIST!$B$2:$B$131,0)),0) -> 0.0192
B29: Bread (qty) | C29: 0.667 | D29: 2 | E29: 4
B30: Bread cost | C30: =C29*IFERROR(INDEX(LIST!$G$2:$G$131,MATCH("Bread",LIST!$B$2:$B$131,0)),0) -> 0.008004 | D30: =D29*IFERROR(INDEX(LIST!$G$2:$G$131,MATCH("Bread",LIST!$B$2:$B$131,0)),0) -> 0.024 | E30: =E29*IFERROR(INDEX(LIST!$G$2:$G$131,MATCH("Bread",LIST!$B$2:$B$131,0)),0) -> 0.048
B31: Bag | C31: Bag Small | D31: Bag Medium | E31: Bag Large
B32: Bag cost | C32: =IFERROR(INDEX(LIST!$G$2:$G$131,MATCH(C31,LIST!$B$2:$B$131,0)),0) -> 0.02 | D32: =IFERROR(INDEX(LIST!$G$2:$G$131,MATCH(D31,LIST!$B$2:$B$131,0)),0) -> 0.03 | E32: =IFERROR(INDEX(LIST!$G$2:$G$131,MATCH(E31,LIST!$B$2:$B$131,0)),0) -> 0.04
B33: Other costs | C33: 0 | D33: 0 | E33: 0
B34: Packaging total | C34: =C26+C28+C30+C32+C33 -> 0.055404 | D34: =D26+D28+D30+D32+D33 -> 0.0983 | E34: =E26+E28+E30+E32+E33 -> 0.22386667
B35: TOTAL COST | C35: =C24+C34 -> 0.51531775 | D35: =D24+D34 -> 1.0181275 | E35: =E24+E34 -> 2.0635217
B36: Store price | C36: 2.5 | D36: 3.2 | E36: 5.4
B37: Store cost % | C37: =IF(C36=0,"",C35/C36) -> 0.2061271 | D37: =IF(D36=0,"",D35/D36) -> 0.31816484 | E37: =IF(E36=0,"",E35/E36) -> 0.38213364
B38: Delivery price | C38: 2.5 | D38: 3.5 | E38: 6
B39: Delivery cost % | C39: =IF(N(C38)=0,"",C35/C38) -> 0.2061271 | D39: =IF(N(D38)=0,"",D35/D38) -> 0.29089357 | E39: =IF(N(E38)=0,"",E35/E38) -> 0.34392028
B40: Store profit | C40: =C36-C35 -> 1.9846823 | D40: =D36-D35 -> 2.1818725 | E40: =E36-E35 -> 3.3364783
B41: Delivery profit | C41: =IF(N(C38)=0,"",C38-C35) -> 1.9846823 | D41: =IF(N(D38)=0,"",D38-D35) -> 2.4818725 | E41: =IF(N(E38)=0,"",E38-E35) -> 3.9364783

Sheet Nashif Chicken
A1: Nashif Chicken
A2: Main dishes · one recipe fills several containers · target 30%
A4: # | B4: Item | C4: Qty | D4: Unit | E4: Unit price | F4: Cost
A5: 1 | B5: Chicken Breast | C5: 1000 | D5: =IFERROR(INDEX(LIST!$F$2:$F$131,MATCH(B5,LIST!$B$2:$B$131,0)),"") -> g | E5: =IFERROR(INDEX(LIST!$G$2:$G$131,MATCH(B5,LIST!$B$2:$B$131,0)),0) -> 0.0015 | F5: =C5*E5 -> 1.5
A6: 2 | B6: ChickPeas | C6: 150 | D6: =IFERROR(INDEX(LIST!$F$2:$F$131,MATCH(B6,LIST!$B$2:$B$131,0)),"") -> g | E6: =IFERROR(INDEX(LIST!$G$2:$G$131,MATCH(B6,LIST!$B$2:$B$131,0)),0) -> 0.00066 | F6: =C6*E6 -> 0.099
A7: 3 | B7: Chana Dal | C7: 250 | D7: =IFERROR(INDEX(LIST!$F$2:$F$131,MATCH(B7,LIST!$B$2:$B$131,0)),"") -> g | E7: =IFERROR(INDEX(LIST!$G$2:$G$131,MATCH(B7,LIST!$B$2:$B$131,0)),0) -> 0.000581 | F7: =C7*E7 -> 0.14525
A8: 4 | B8: Masoor Daal | C8: 250 | D8: =IFERROR(INDEX(LIST!$F$2:$F$131,MATCH(B8,LIST!$B$2:$B$131,0)),"") -> g | E8: =IFERROR(INDEX(LIST!$G$2:$G$131,MATCH(B8,LIST!$B$2:$B$131,0)),0) -> 0.000454 | F8: =C8*E8 -> 0.1135
A9: 5 | B9: Potato | C9: 500 | D9: =IFERROR(INDEX(LIST!$F$2:$F$131,MATCH(B9,LIST!$B$2:$B$131,0)),"") -> g | E9: =IFERROR(INDEX(LIST!$G$2:$G$131,MATCH(B9,LIST!$B$2:$B$131,0)),0) -> 0.00036 | F9: =C9*E9 -> 0.18
A10: 6 | B10: Onion | C10: 200 | D10: =IFERROR(INDEX(LIST!$F$2:$F$131,MATCH(B10,LIST!$B$2:$B$131,0)),"") -> g | E10: =IFERROR(INDEX(LIST!$G$2:$G$131,MATCH(B10,LIST!$B$2:$B$131,0)),0) -> 0.00045 | F10: =C10*E10 -> 0.09
A11: 7 | B11: Tomato | C11: 400 | D11: =IFERROR(INDEX(LIST!$F$2:$F$131,MATCH(B11,LIST!$B$2:$B$131,0)),"") -> g | E11: =IFERROR(INDEX(LIST!$G$2:$G$131,MATCH(B11,LIST!$B$2:$B$131,0)),0) -> 0.0005 | F11: =C11*E11 -> 0.2
A12: 8 | B12: Coriander Leaves | C12: 30 | D12: =IFERROR(INDEX(LIST!$F$2:$F$131,MATCH(B12,LIST!$B$2:$B$131,0)),"") -> g | E12: =IFERROR(INDEX(LIST!$G$2:$G$131,MATCH(B12,LIST!$B$2:$B$131,0)),0) -> 0.0017272727 | F12: =C12*E12 -> 0.051818182
A13: 9 | B13: Ginger | C13: 7.5 | D13: =IFERROR(INDEX(LIST!$F$2:$F$131,MATCH(B13,LIST!$B$2:$B$131,0)),"") -> g | E13: =IFERROR(INDEX(LIST!$G$2:$G$131,MATCH(B13,LIST!$B$2:$B$131,0)),0) -> 0.002 | F13: =C13*E13 -> 0.015
A14: 10 | B14: Garlic Peeled | C14: 7.5 | D14: =IFERROR(INDEX(LIST!$F$2:$F$131,MATCH(B14,LIST!$B$2:$B$131,0)),"") -> g | E14: =IFERROR(INDEX(LIST!$G$2:$G$131,MATCH(B14,LIST!$B$2:$B$131,0)),0) -> 0.0015 | F14: =C14*E14 -> 0.01125
A15: 11 | B15: Mint Leaves | C15: 0 | D15: =IFERROR(INDEX(LIST!$F$2:$F$131,MATCH(B15,LIST!$B$2:$B$131,0)),"") -> g | E15: =IFERROR(INDEX(LIST!$G$2:$G$131,MATCH(B15,LIST!$B$2:$B$131,0)),0) -> 0.0018181818 | F15: =C15*E15 -> 0
A16: 12 | B16: Long Chilly | C16: 25 | D16: =IFERROR(INDEX(LIST!$F$2:$F$131,MATCH(B16,LIST!$B$2:$B$131,0)),"") -> g | E16: =IFERROR(INDEX(LIST!$G$2:$G$131,MATCH(B16,LIST!$B$2:$B$131,0)),0) -> 0.0011 | F16: =C16*E16 -> 0.0275
... A32: 28 | B32: Salt | C32: 15 | D32: =IFERROR(INDEX(LIST!$F$2:$F$131,MATCH(B32,LIST!$B$2:$B$131,0)),"") -> g | E32: =IFERROR(INDEX(LIST!$G$2:$G$131,MATCH(B32,LIST!$B$2:$B$131,0)),0) -> 0.000165 | F32: =C32*E32 -> 0.002475
B33: TOTAL RECIPE COST | F33: =SUM(F5:F32) -> 2.9196442
B35: Size | C35: Small | D35: Medium | E35: Large
B36: Containers per recipe | C36: 8 | D36: 4 | E36: 1.5
B37: Ingredient cost | C37: =IF(C36=0,0,$F$33/C36) -> 0.36495552 | D37: =IF(D36=0,0,$F$33/D36) -> 0.72991105 | E37: =IF(E36=0,0,$F$33/E36) -> 1.9464295
B38: Container | C38: CONTENER NO : (3) | D38: CONTENER NO : (4) | E38: CONTENER NO : (5)
B39: Container cost | C39: =IFERROR(INDEX(LIST!$G$2:$G$131,MATCH(C38,LIST!$B$2:$B$131,0)),0) -> 0.021 | D39: =IFERROR(INDEX(LIST!$G$2:$G$131,MATCH(D38,LIST!$B$2:$B$131,0)),0) -> 0.0315 | E39: =IFERROR(INDEX(LIST!$G$2:$G$131,MATCH(E38,LIST!$B$2:$B$131,0)),0) -> 0.11666667
B40: Spoons (qty) | C40: 1 | D40: 2 | E40: 3
B41: Spoon cost | C41: =C40*IFERROR(INDEX(LIST!$G$2:$G$131,MATCH("SPOON",LIST!$B$2:$B$131,0)),0) -> 0.0064 | D41: =D40*IFERROR(INDEX(LIST!$G$2:$G$131,MATCH("SPOON",LIST!$B$2:$B$131,0)),0) -> 0.0128 | E41: =E40*IFERROR(INDEX(LIST!$G$2:$G$131,MATCH("SPOON",LIST!$B$2:$B$131,0)),0) -> 0.0192
B42: Bread (qty) | C42: 1 | D42: 2 | E42: 4
B43: Bread cost | C43: =C42*IFERROR(INDEX(LIST!$G$2:$G$131,MATCH("Bread",LIST!$B$2:$B$131,0)),0) -> 0.012 | D43: =D42*IFERROR(INDEX(LIST!$G$2:$G$131,MATCH("Bread",LIST!$B$2:$B$131,0)),0) -> 0.024 | E43: =E42*IFERROR(INDEX(LIST!$G$2:$G$131,MATCH("Bread",LIST!$B$2:$B$131,0)),0) -> 0.048
B44: Bag | C44: Bag Small | D44: Bag Medium | E44: Bag Large
B45: Bag cost | C45: =IFERROR(INDEX(LIST!$G$2:$G$131,MATCH(C44,LIST!$B$2:$B$131,0)),0) -> 0.02 | D45: =IFERROR(INDEX(LIST!$G$2:$G$131,MATCH(D44,LIST!$B$2:$B$131,0)),0) -> 0.03 | E45: =IFERROR(INDEX(LIST!$G$2:$G$131,MATCH(E44,LIST!$B$2:$B$131,0)),0) -> 0.04
B46: Other costs | C46: 0 | D46: 0 | E46: 0
B47: Packaging total | C47: =C39+C41+C43+C45+C46 -> 0.0594 | D47: =D39+D41+D43+D45+D46 -> 0.0983 | E47: =E39+E41+E43+E45+E46 -> 0.22386667
B48: TOTAL COST | C48: =C37+C47 -> 0.42435552 | D48: =D37+D47 -> 0.82821105 | E48: =E37+E47 -> 2.1702961
B49: Store price | C49: 1.8 | D49: 3.4 | E49: 6.6
B50: Store cost % | C50: =IF(C49=0,"",C48/C49) -> 0.23575307 | D50: =IF(D49=0,"",D48/D49) -> 0.24359148 | E50: =IF(E49=0,"",E48/E49) -> 0.32883275
B51: Delivery price | C51: 2.2 | D51: 4 | E51: 7.6
B52: Delivery cost % | C52: =IF(N(C51)=0,"",C48/C51) -> 0.19288887 | D52: =IF(N(D51)=0,"",D48/D51) -> 0.20705276 | E52: =IF(N(E51)=0,"",E48/E51) -> 0.28556528
B53: Store profit | C53: =C49-C48 -> 1.3756445 | D53: =D49-D48 -> 2.571789 | E53: =E49-E48 -> 4.4297039
B54: Delivery profit | C54: =IF(N(C51)=0,"",C51-C48) -> 1.7756445 | D54: =IF(N(D51)=0,"",D51-D48) -> 3.171789 | E54: =IF(N(E51)=0,"",E51-E48) -> 5.4297039

Sheet Nashif Meat
A1: Nashif Meat
A2: Main dishes · one recipe fills several containers · target 30%
A4: # | B4: Item | C4: Qty | D4: Unit | E4: Unit price | F4: Cost
A5: 1 | B5: Qeema Meat | C5: 1000 | D5: =IFERROR(INDEX(LIST!$F$2:$F$131,MATCH(B5,LIST!$B$2:$B$131,0)),"") -> g | E5: =IFERROR(INDEX(LIST!$G$2:$G$131,MATCH(B5,LIST!$B$2:$B$131,0)),0) -> 0.0022 | F5: =C5*E5 -> 2.2
A6: 2 | B6: Onion | C6: 100 | D6: =IFERROR(INDEX(LIST!$F$2:$F$131,MATCH(B6,LIST!$B$2:$B$131,0)),"") -> g | E6: =IFERROR(INDEX(LIST!$G$2:$G$131,MATCH(B6,LIST!$B$2:$B$131,0)),0) -> 0.00045 | F6: =C6*E6 -> 0.045
A7: 3 | B7: Tomato | C7: 400 | D7: =IFERROR(INDEX(LIST!$F$2:$F$131,MATCH(B7,LIST!$B$2:$B$131,0)),"") -> g | E7: =IFERROR(INDEX(LIST!$G$2:$G$131,MATCH(B7,LIST!$B$2:$B$131,0)),0) -> 0.0005 | F7: =C7*E7 -> 0.2
A8: 4 | B8: Potato | C8: 200 | D8: =IFERROR(INDEX(LIST!$F$2:$F$131,MATCH(B8,LIST!$B$2:$B$131,0)),"") -> g | E8: =IFERROR(INDEX(LIST!$G$2:$G$131,MATCH(B8,LIST!$B$2:$B$131,0)),0) -> 0.00036 | F8: =C8*E8 -> 0.072
A9: 5 | B9: Green Capiscum | C9: 100 | D9: =IFERROR(INDEX(LIST!$F$2:$F$131,MATCH(B9,LIST!$B$2:$B$131,0)),"") -> g | E9: =IFERROR(INDEX(LIST!$G$2:$G$131,MATCH(B9,LIST!$B$2:$B$131,0)),0) -> 0.00065 | F9: =C9*E9 -> 0.065
A10: 6 | B10: Cabbage White | C10: 200 | D10: =IFERROR(INDEX(LIST!$F$2:$F$131,MATCH(B10,LIST!$B$2:$B$131,0)),"") -> g | E10: =IFERROR(INDEX(LIST!$G$2:$G$131,MATCH(B10,LIST!$B$2:$B$131,0)),0) -> 0.0004 | F10: =C10*E10 -> 0.08
A11: 7 | B11: Long Chilly | C11: 4.5 | D11: =IFERROR(INDEX(LIST!$F$2:$F$131,MATCH(B11,LIST!$B$2:$B$131,0)),"") -> g | E11: =IFERROR(INDEX(LIST!$G$2:$G$131,MATCH(B11,LIST!$B$2:$B$131,0)),0) -> 0.0011 | F11: =C11*E11 -> 0.00495
A12: 8 | B12: Ginger + Garlic Mix | C12: 9 | D12: =IFERROR(INDEX(LIST!$F$2:$F$131,MATCH(B12,LIST!$B$2:$B$131,0)),"") -> g | E12: =IFERROR(INDEX(LIST!$G$2:$G$131,MATCH(B12,LIST!$B$2:$B$131,0)),0) -> 0.0012 | F12: =C12*E12 -> 0.0108
A13: 9 | B13: Vegetable Oil | C13: 70 | D13: =IFERROR(INDEX(LIST!$F$2:$F$131,MATCH(B13,LIST!$B$2:$B$131,0)),"") -> ml | E13: =IFERROR(INDEX(LIST!$G$2:$G$131,MATCH(B13,LIST!$B$2:$B$131,0)),0) -> 0.000594 | F13: =C13*E13 -> 0.04158
A14: 10 | B14: Tomato Paste | C14: 48 | D14: =IFERROR(INDEX(LIST!$F$2:$F$131,MATCH(B14,LIST!$B$2:$B$131,0)),"") -> g | E14: =IFERROR(INDEX(LIST!$G$2:$G$131,MATCH(B14,LIST!$B$2:$B$131,0)),0) -> 0.0006 | F14: =C14*E14 -> 0.0288
A15: 11 | B15: Salt | C15: 6 | D15: =IFERROR(INDEX(LIST!$F$2:$F$131,MATCH(B15,LIST!$B$2:$B$131,0)),"") -> g | E15: =IFERROR(INDEX(LIST!$G$2:$G$131,MATCH(B15,LIST!$B$2:$B$131,0)),0) -> 0.000165 | F15: =C15*E15 -> 0.00099
A16: 12 | B16: Nahai | C16: 200 | D16: =IFERROR(INDEX(LIST!$F$2:$F$131,MATCH(B16,LIST!$B$2:$B$131,0)),"") -> g | E16: =IFERROR(INDEX(LIST!$G$2:$G$131,MATCH(B16,LIST!$B$2:$B$131,0)),0) -> 0.00108 | F16: =C16*E16 -> 0.216
... A26: 22 | B26: Black Lemone Whole | C26: 5 | D26: =IFERROR(INDEX(LIST!$F$2:$F$131,MATCH(B26,LIST!$B$2:$B$131,0)),"") -> g | E26: =IFERROR(INDEX(LIST!$G$2:$G$131,MATCH(B26,LIST!$B$2:$B$131,0)),0) -> 0.00176 | F26: =C26*E26 -> 0.0088
B27: TOTAL RECIPE COST | F27: =SUM(F5:F26) -> 3.038026
B29: Size | C29: Small | D29: Medium | E29: Large
B30: Containers per recipe | C30: 6 | D30: 3 | E30: 1.5
B31: Ingredient cost | C31: =IF(C30=0,0,$F$27/C30) -> 0.50633767 | D31: =IF(D30=0,0,$F$27/D30) -> 1.0126753 | E31: =IF(E30=0,0,$F$27/E30) -> 2.0253507
B32: Container | C32: CONTENER NO : (3) | D32: CONTENER NO : (4) | E32: CONTENER NO : (5)
B33: Container cost | C33: =IFERROR(INDEX(LIST!$G$2:$G$131,MATCH(C32,LIST!$B$2:$B$131,0)),0) -> 0.021 | D33: =IFERROR(INDEX(LIST!$G$2:$G$131,MATCH(D32,LIST!$B$2:$B$131,0)),0) -> 0.0315 | E33: =IFERROR(INDEX(LIST!$G$2:$G$131,MATCH(E32,LIST!$B$2:$B$131,0)),0) -> 0.11666667
B34: Spoons (qty) | C34: 1.45 | D34: 2.9 | E34: 6
B35: Spoon cost | C35: =C34*IFERROR(INDEX(LIST!$G$2:$G$131,MATCH("SPOON",LIST!$B$2:$B$131,0)),0) -> 0.00928 | D35: =D34*IFERROR(INDEX(LIST!$G$2:$G$131,MATCH("SPOON",LIST!$B$2:$B$131,0)),0) -> 0.01856 | E35: =E34*IFERROR(INDEX(LIST!$G$2:$G$131,MATCH("SPOON",LIST!$B$2:$B$131,0)),0) -> 0.0384
B36: Bread (qty) | C36: 0.967 | D36: 2 | E36: 4
B37: Bread cost | C37: =C36*IFERROR(INDEX(LIST!$G$2:$G$131,MATCH("Bread",LIST!$B$2:$B$131,0)),0) -> 0.011604 | D37: =D36*IFERROR(INDEX(LIST!$G$2:$G$131,MATCH("Bread",LIST!$B$2:$B$131,0)),0) -> 0.024 | E37: =E36*IFERROR(INDEX(LIST!$G$2:$G$131,MATCH("Bread",LIST!$B$2:$B$131,0)),0) -> 0.048
B38: Bag | C38: Bag Small | D38: Bag Medium | E38: Bag Large
B39: Bag cost | C39: =IFERROR(INDEX(LIST!$G$2:$G$131,MATCH(C38,LIST!$B$2:$B$131,0)),0) -> 0.02 | D39: =IFERROR(INDEX(LIST!$G$2:$G$131,MATCH(D38,LIST!$B$2:$B$131,0)),0) -> 0.03 | E39: =IFERROR(INDEX(LIST!$G$2:$G$131,MATCH(E38,LIST!$B$2:$B$131,0)),0) -> 0.04
B40: Other costs | C40: 0 | D40: 0 | E40: 0
B41: Packaging total | C41: =C33+C35+C37+C39+C40 -> 0.061884 | D41: =D33+D35+D37+D39+D40 -> 0.10406 | E41: =E33+E35+E37+E39+E40 -> 0.24306667
B42: TOTAL COST | C42: =C31+C41 -> 0.56822167 | D42: =D31+D41 -> 1.1167353 | E42: =E31+E41 -> 2.2684173
B43: Store price | C43: 2 | D43: 3.8 | E43: 7
B44: Store cost % | C44: =IF(C43=0,"",C42/C43) -> 0.28411083 | D44: =IF(D43=0,"",D42/D43) -> 0.29387772 | E44: =IF(E43=0,"",E42/E43) -> 0.32405962
B45: Delivery price | C45: 1.5 | D45: 2.8 | E45: 5.4
B46: Delivery cost % | C46: =IF(N(C45)=0,"",C42/C45) -> 0.37881444 | D46: =IF(N(D45)=0,"",D42/D45) -> 0.39883405 | E46: =IF(N(E45)=0,"",E42/E45) -> 0.42007728
B47: Store profit | C47: =C43-C42 -> 1.4317783 | D47: =D43-D42 -> 2.6832647 | E47: =E43-E42 -> 4.7315827
B48: Delivery profit | C48: =IF(N(C45)=0,"",C45-C42) -> 0.93177833 | D48: =IF(N(D45)=0,"",D45-D42) -> 1.6832647 | E48: =IF(N(E45)=0,"",E45-E42) -> 3.1315827

Sheet Aseeda
A1: Aseeda
A2: Sweets · one recipe fills several containers · target 30%
A4: # | B4: Item | C4: Qty | D4: Unit | E4: Unit price | F4: Cost
A5: 1 | B5: Flour White | C5: 400 | D5: =IFERROR(INDEX(LIST!$F$2:$F$131,MATCH(B5,LIST!$B$2:$B$131,0)),"") -> g | E5: =IFERROR(INDEX(LIST!$G$2:$G$131,MATCH(B5,LIST!$B$2:$B$131,0)),0) -> 0.0001 | F5: =C5*E5 -> 0.04
A6: 2 | B6: Aseel Ghee | C6: 30 | D6: =IFERROR(INDEX(LIST!$F$2:$F$131,MATCH(B6,LIST!$B$2:$B$131,0)),"") -> ml | E6: =IFERROR(INDEX(LIST!$G$2:$G$131,MATCH(B6,LIST!$B$2:$B$131,0)),0) -> 0.001232 | F6: =C6*E6 -> 0.03696
A7: 3 | B7: Cinamon Powder | C7: 2.5 | D7: =IFERROR(INDEX(LIST!$F$2:$F$131,MATCH(B7,LIST!$B$2:$B$131,0)),"") -> g | E7: =IFERROR(INDEX(LIST!$G$2:$G$131,MATCH(B7,LIST!$B$2:$B$131,0)),0) -> 0.0026454 | F7: =C7*E7 -> 0.0066135
A8: 4 | B8: Cardmon Powder | C8: 2.5 | D8: =IFERROR(INDEX(LIST!$F$2:$F$131,MATCH(B8,LIST!$B$2:$B$131,0)),"") -> g | E8: =IFERROR(INDEX(LIST!$G$2:$G$131,MATCH(B8,LIST!$B$2:$B$131,0)),0) -> 0.0154 | F8: =C8*E8 -> 0.0385
A9: 5 | B9: Sugar | C9: 240 | D9: =IFERROR(INDEX(LIST!$F$2:$F$131,MATCH(B9,LIST!$B$2:$B$131,0)),"") -> g | E9: =IFERROR(INDEX(LIST!$G$2:$G$131,MATCH(B9,LIST!$B$2:$B$131,0)),0) -> 0.0003 | F9: =C9*E9 -> 0.072
B10: TOTAL RECIPE COST | F10: =SUM(F5:F9) -> 0.1940735
B12: Size | C12: Single | D12: Small | E12: Medium | F12: Large
B13: Containers per recipe | C13: 5 | D13: 3 | E13: 2 | F13: 1
B14: Ingredient cost | C14: =IF(C13=0,0,$F$10/C13) -> 0.0388147 | D14: =IF(D13=0,0,$F$10/D13) -> 0.064691167 | E14: =IF(E13=0,0,$F$10/E13) -> 0.09703675 | F14: =IF(F13=0,0,$F$10/F13) -> 0.1940735
B15: Container | C15: CONTENER NO : (1) | D15: CONTENER NO : (3) | E15: CONTENER NO : (4) | F15: CONTENER NO : (5)
B16: Container cost | C16: =IFERROR(INDEX(LIST!$G$2:$G$131,MATCH(C15,LIST!$B$2:$B$131,0)),0) -> 0.025 | D16: =IFERROR(INDEX(LIST!$G$2:$G$131,MATCH(D15,LIST!$B$2:$B$131,0)),0) -> 0.021 | E16: =IFERROR(INDEX(LIST!$G$2:$G$131,MATCH(E15,LIST!$B$2:$B$131,0)),0) -> 0.0315 | F16: =IFERROR(INDEX(LIST!$G$2:$G$131,MATCH(F15,LIST!$B$2:$B$131,0)),0) -> 0.11666667
B17: Spoons (qty) | C17: 1 | D17: 2 | E17: 3 | F17: 4
B18: Spoon cost | C18: =C17*IFERROR(INDEX(LIST!$G$2:$G$131,MATCH("SPOON",LIST!$B$2:$B$131,0)),0) -> 0.0064 | D18: =D17*IFERROR(INDEX(LIST!$G$2:$G$131,MATCH("SPOON",LIST!$B$2:$B$131,0)),0) -> 0.0128 | E18: =E17*IFERROR(INDEX(LIST!$G$2:$G$131,MATCH("SPOON",LIST!$B$2:$B$131,0)),0) -> 0.0192 | F18: =F17*IFERROR(INDEX(LIST!$G$2:$G$131,MATCH("SPOON",LIST!$B$2:$B$131,0)),0) -> 0.0256
B19: Bread (qty) | C19: 0 | D19: 0 | E19: 0 | F19: 0
B20: Bread cost | C20: =C19*IFERROR(INDEX(LIST!$G$2:$G$131,MATCH("Bread",LIST!$B$2:$B$131,0)),0) -> 0 | D20: =D19*IFERROR(INDEX(LIST!$G$2:$G$131,MATCH("Bread",LIST!$B$2:$B$131,0)),0) -> 0 | E20: =E19*IFERROR(INDEX(LIST!$G$2:$G$131,MATCH("Bread",LIST!$B$2:$B$131,0)),0) -> 0 | F20: =F19*IFERROR(INDEX(LIST!$G$2:$G$131,MATCH("Bread",LIST!$B$2:$B$131,0)),0) -> 0
B21: Bag | C21: Bag XS | D21: Bag Small | E21: Bag Medium | F21: Bag Large
B22: Bag cost | C22: =IFERROR(INDEX(LIST!$G$2:$G$131,MATCH(C21,LIST!$B$2:$B$131,0)),0) -> 0.01 | D22: =IFERROR(INDEX(LIST!$G$2:$G$131,MATCH(D21,LIST!$B$2:$B$131,0)),0) -> 0.02 | E22: =IFERROR(INDEX(LIST!$G$2:$G$131,MATCH(E21,LIST!$B$2:$B$131,0)),0) -> 0.03 | F22: =IFERROR(INDEX(LIST!$G$2:$G$131,MATCH(F21,LIST!$B$2:$B$131,0)),0) -> 0.04
B23: Other costs | C23: 0 | D23: 0 | E23: 0 | F23: 0
B24: Packaging total | C24: =C16+C18+C20+C22+C23 -> 0.0414 | D24: =D16+D18+D20+D22+D23 -> 0.0538 | E24: =E16+E18+E20+E22+E23 -> 0.0807 | F24: =F16+F18+F20+F22+F23 -> 0.18226667
B25: TOTAL COST | C25: =C14+C24 -> 0.0802147 | D25: =D14+D24 -> 0.11849117 | E25: =E14+E24 -> 0.17773675 | F25: =F14+F24 -> 0.37634017
B26: Store price | C26: 0.4 | D26: 0.7 | E26: 1 | F26: 1.9
B27: Store cost % | C27: =IF(C26=0,"",C25/C26) -> 0.20053675 | D27: =IF(D26=0,"",D25/D26) -> 0.1692731 | E27: =IF(E26=0,"",E25/E26) -> 0.17773675 | F27: =IF(F26=0,"",F25/F26) -> 0.19807377
B28: Delivery price | C28: 0.4 | D28: 1 | E28: 1.5 | F28: 2.5
B29: Delivery cost % | C29: =IF(N(C28)=0,"",C25/C28) -> 0.20053675 | D29: =IF(N(D28)=0,"",D25/D28) -> 0.11849117 | E29: =IF(N(E28)=0,"",E25/E28) -> 0.11849117 | F29: =IF(N(F28)=0,"",F25/F28) -> 0.15053607
B30: Store profit | C30: =C26-C25 -> 0.3197853 | D30: =D26-D25 -> 0.58150883 | E30: =E26-E25 -> 0.82226325 | F30: =F26-F25 -> 1.5236598
B31: Delivery profit | C31: =IF(N(C28)=0,"",C28-C25) -> 0.3197853 | D31: =IF(N(D28)=0,"",D28-D25) -> 0.88150883 | E31: =IF(N(E28)=0,"",E28-E25) -> 1.3222633 | F31: =IF(N(F28)=0,"",F28-F25) -> 2.1236598

Sheet Qeemat
A1: Qeemat
A2: Sweets · one recipe fills several containers · target 30%
A4: # | B4: Item | C4: Qty | D4: Unit | E4: Unit price | F4: Cost
A5: 1 | B5: Qeemat Powder | C5: 1000 | D5: =IFERROR(INDEX(LIST!$F$2:$F$131,MATCH(B5,LIST!$B$2:$B$131,0)),"") -> g | E5: =IFERROR(INDEX(LIST!$G$2:$G$131,MATCH(B5,LIST!$B$2:$B$131,0)),0) -> 0.00145 | F5: =C5*E5 -> 1.45
A6: 2 | B6: Sem sem Seeds | C6: 60 | D6: =IFERROR(INDEX(LIST!$F$2:$F$131,MATCH(B6,LIST!$B$2:$B$131,0)),"") -> g | E6: =IFERROR(INDEX(LIST!$G$2:$G$131,MATCH(B6,LIST!$B$2:$B$131,0)),0) -> 0.00157 | F6: =C6*E6 -> 0.0942
A7: 3 | B7: Vegetable Oil | C7: 400 | D7: =IFERROR(INDEX(LIST!$F$2:$F$131,MATCH(B7,LIST!$B$2:$B$131,0)),"") -> ml | E7: =IFERROR(INDEX(LIST!$G$2:$G$131,MATCH(B7,LIST!$B$2:$B$131,0)),0) -> 0.000594 | F7: =C7*E7 -> 0.2376
A8: 4 | B8: Date Syrup | C8: 300 | D8: =IFERROR(INDEX(LIST!$F$2:$F$131,MATCH(B8,LIST!$B$2:$B$131,0)),"") -> g | E8: =IFERROR(INDEX(LIST!$G$2:$G$131,MATCH(B8,LIST!$B$2:$B$131,0)),0) -> 0.0041666667 | F8: =C8*E8 -> 1.25
A9: 5 | B9: Rose Water | C9: 100 | D9: =IFERROR(INDEX(LIST!$F$2:$F$131,MATCH(B9,LIST!$B$2:$B$131,0)),"") -> ml | E9: =IFERROR(INDEX(LIST!$G$2:$G$131,MATCH(B9,LIST!$B$2:$B$131,0)),0) -> 0.00044444444 | F9: =C9*E9 -> 0.044444444
B10: TOTAL RECIPE COST | F10: =SUM(F5:F9) -> 3.0762444
B12: Size | C12: Medium
B13: Containers per recipe | C13: 7
B14: Ingredient cost | C14: =IF(C13=0,0,$F$10/C13) -> 0.43946349
B15: Container | C15: Alluminium Container S
B16: Container cost | C16: =IFERROR(INDEX(LIST!$G$2:$G$131,MATCH(C15,LIST!$B$2:$B$131,0)),0) -> 0.0024
B17: Spoons (qty) | C17: 0
B18: Spoon cost | C18: =C17*IFERROR(INDEX(LIST!$G$2:$G$131,MATCH("SPOON",LIST!$B$2:$B$131,0)),0) -> 0
B19: Bread (qty) | C19: 0
B20: Bread cost | C20: =C19*IFERROR(INDEX(LIST!$G$2:$G$131,MATCH("Bread",LIST!$B$2:$B$131,0)),0) -> 0
B21: Bag | C21: Bag Medium
B22: Bag cost | C22: =IFERROR(INDEX(LIST!$G$2:$G$131,MATCH(C21,LIST!$B$2:$B$131,0)),0) -> 0.03
B23: Other costs | C23: 0
B24: Packaging total | C24: =C16+C18+C20+C22+C23 -> 0.0324
B25: TOTAL COST | C25: =C14+C24 -> 0.47186349
B26: Store price | C26: 1.4
B27: Store cost % | C27: =IF(C26=0,"",C25/C26) -> 0.33704535
B28: Delivery price | C28: 1.8
B29: Delivery cost % | C29: =IF(N(C28)=0,"",C25/C28) -> 0.26214638
B30: Store profit | C30: =C26-C25 -> 0.92813651
B31: Delivery profit | C31: =IF(N(C28)=0,"",C28-C25) -> 1.3281365

Sheet Balaleet
A1: Balaleet
A2: Sweets · one recipe fills several containers · target 30%
A4: # | B4: Item | C4: Qty | D4: Unit | E4: Unit price | F4: Cost
A5: 1 | B5: Balaleet | C5: 500 | D5: =IFERROR(INDEX(LIST!$F$2:$F$131,MATCH(B5,LIST!$B$2:$B$131,0)),"") -> g | E5: =IFERROR(INDEX(LIST!$G$2:$G$131,MATCH(B5,LIST!$B$2:$B$131,0)),0) -> 0.00108 | F5: =C5*E5 -> 0.54
A6: 2 | B6: Sugar | C6: 240 | D6: =IFERROR(INDEX(LIST!$F$2:$F$131,MATCH(B6,LIST!$B$2:$B$131,0)),"") -> g | E6: =IFERROR(INDEX(LIST!$G$2:$G$131,MATCH(B6,LIST!$B$2:$B$131,0)),0) -> 0.0003 | F6: =C6*E6 -> 0.072
A7: 3 | B7: Rose Water | C7: 30 | D7: =IFERROR(INDEX(LIST!$F$2:$F$131,MATCH(B7,LIST!$B$2:$B$131,0)),"") -> ml | E7: =IFERROR(INDEX(LIST!$G$2:$G$131,MATCH(B7,LIST!$B$2:$B$131,0)),0) -> 0.00044444444 | F7: =C7*E7 -> 0.013333333
A8: 4 | B8: Egg | C8: 10 | D8: =IFERROR(INDEX(LIST!$F$2:$F$131,MATCH(B8,LIST!$B$2:$B$131,0)),"") -> pc | E8: =IFERROR(INDEX(LIST!$G$2:$G$131,MATCH(B8,LIST!$B$2:$B$131,0)),0) -> 0.035 | F8: =C8*E8 -> 0.35
A9: 5 | B9: Cardmon Powder | C9: 30 | D9: =IFERROR(INDEX(LIST!$F$2:$F$131,MATCH(B9,LIST!$B$2:$B$131,0)),"") -> g | E9: =IFERROR(INDEX(LIST!$G$2:$G$131,MATCH(B9,LIST!$B$2:$B$131,0)),0) -> 0.0154 | F9: =C9*E9 -> 0.462
B10: TOTAL RECIPE COST | F10: =SUM(F5:F9) -> 1.4373333
B12: Size | C12: Small | D12: Medium | E12: Large
B13: Containers per recipe | C13: 6 | D13: 4 | E13: 2
B14: Ingredient cost | C14: =IF(C13=0,0,$F$10/C13) -> 0.23955556 | D14: =IF(D13=0,0,$F$10/D13) -> 0.35933333 | E14: =IF(E13=0,0,$F$10/E13) -> 0.71866667
B15: Container | C15: CONTENER NO : (3) | D15: CONTENER NO : (4) | E15: CONTENER NO : (5)
B16: Container cost | C16: =IFERROR(INDEX(LIST!$G$2:$G$131,MATCH(C15,LIST!$B$2:$B$131,0)),0) -> 0.021 | D16: =IFERROR(INDEX(LIST!$G$2:$G$131,MATCH(D15,LIST!$B$2:$B$131,0)),0) -> 0.0315 | E16: =IFERROR(INDEX(LIST!$G$2:$G$131,MATCH(E15,LIST!$B$2:$B$131,0)),0) -> 0.11666667
B17: Spoons (qty) | C17: 1 | D17: 2 | E17: 3
B18: Spoon cost | C18: =C17*IFERROR(INDEX(LIST!$G$2:$G$131,MATCH("SPOON",LIST!$B$2:$B$131,0)),0) -> 0.0064 | D18: =D17*IFERROR(INDEX(LIST!$G$2:$G$131,MATCH("SPOON",LIST!$B$2:$B$131,0)),0) -> 0.0128 | E18: =E17*IFERROR(INDEX(LIST!$G$2:$G$131,MATCH("SPOON",LIST!$B$2:$B$131,0)),0) -> 0.0192
B19: Bread (qty) | C19: 0 | D19: 0 | E19: 0
B20: Bread cost | C20: =C19*IFERROR(INDEX(LIST!$G$2:$G$131,MATCH("Bread",LIST!$B$2:$B$131,0)),0) -> 0 | D20: =D19*IFERROR(INDEX(LIST!$G$2:$G$131,MATCH("Bread",LIST!$B$2:$B$131,0)),0) -> 0 | E20: =E19*IFERROR(INDEX(LIST!$G$2:$G$131,MATCH("Bread",LIST!$B$2:$B$131,0)),0) -> 0
B21: Bag | C21: Bag Small | D21: Bag Medium | E21: Bag Large
B22: Bag cost | C22: =IFERROR(INDEX(LIST!$G$2:$G$131,MATCH(C21,LIST!$B$2:$B$131,0)),0) -> 0.02 | D22: =IFERROR(INDEX(LIST!$G$2:$G$131,MATCH(D21,LIST!$B$2:$B$131,0)),0) -> 0.03 | E22: =IFERROR(INDEX(LIST!$G$2:$G$131,MATCH(E21,LIST!$B$2:$B$131,0)),0) -> 0.04
B23: Other costs | C23: 0 | D23: 0 | E23: 0
B24: Packaging total | C24: =C16+C18+C20+C22+C23 -> 0.0474 | D24: =D16+D18+D20+D22+D23 -> 0.0743 | E24: =E16+E18+E20+E22+E23 -> 0.17586667
B25: TOTAL COST | C25: =C14+C24 -> 0.28695556 | D25: =D14+D24 -> 0.43363333 | E25: =E14+E24 -> 0.89453333
B26: Store price | C26: 1 | D26: 1.6 | E26: 3
B27: Store cost % | C27: =IF(C26=0,"",C25/C26) -> 0.28695556 | D27: =IF(D26=0,"",D25/D26) -> 0.27102083 | E27: =IF(E26=0,"",E25/E26) -> 0.29817778
B28: Delivery price | D28: 2
B29: Delivery cost % | C29: =IF(N(C28)=0,"",C25/C28) | D29: =IF(N(D28)=0,"",D25/D28) -> 0.21681667 | E29: =IF(N(E28)=0,"",E25/E28)
B30: Store profit | C30: =C26-C25 -> 0.71304444 | D30: =D26-D25 -> 1.1663667 | E30: =E26-E25 -> 2.1054667
B31: Delivery profit | C31: =IF(N(C28)=0,"",C28-C25) | D31: =IF(N(D28)=0,"",D28-D25) -> 1.5663667 | E31: =IF(N(E28)=0,"",E28-E25)

Sheet Fateeta
A1: Fateeta
A2: Sweets · one recipe fills several containers · target 30%
A4: # | B4: Item | C4: Qty | D4: Unit | E4: Unit price | F4: Cost
A5: 1 | B5: Date Paste | C5: 1000 | D5: =IFERROR(INDEX(LIST!$F$2:$F$131,MATCH(B5,LIST!$B$2:$B$131,0)),"") -> g | E5: =IFERROR(INDEX(LIST!$G$2:$G$131,MATCH(B5,LIST!$B$2:$B$131,0)),0) -> 0.00073 | F5: =C5*E5 -> 0.73
A6: 2 | B6: Flour White | C6: 1000 | D6: =IFERROR(INDEX(LIST!$F$2:$F$131,MATCH(B6,LIST!$B$2:$B$131,0)),"") -> g | E6: =IFERROR(INDEX(LIST!$G$2:$G$131,MATCH(B6,LIST!$B$2:$B$131,0)),0) -> 0.0001 | F6: =C6*E6 -> 0.1
A7: 3 | B7: Sem sem Seeds | C7: 45 | D7: =IFERROR(INDEX(LIST!$F$2:$F$131,MATCH(B7,LIST!$B$2:$B$131,0)),"") -> g | E7: =IFERROR(INDEX(LIST!$G$2:$G$131,MATCH(B7,LIST!$B$2:$B$131,0)),0) -> 0.00157 | F7: =C7*E7 -> 0.07065
A8: 4 | B8: Vegetable Oil | C8: 600 | D8: =IFERROR(INDEX(LIST!$F$2:$F$131,MATCH(B8,LIST!$B$2:$B$131,0)),"") -> ml | E8: =IFERROR(INDEX(LIST!$G$2:$G$131,MATCH(B8,LIST!$B$2:$B$131,0)),0) -> 0.000594 | F8: =C8*E8 -> 0.3564
B9: TOTAL RECIPE COST | F9: =SUM(F5:F8) -> 1.25705
B11: Size | C11: Single | D11: Small | E11: Medium | F11: Large
B12: Containers per recipe | C12: 10 | D12: 7 | E12: 4 | F12: 2
B13: Ingredient cost | C13: =IF(C12=0,0,$F$9/C12) -> 0.125705 | D13: =IF(D12=0,0,$F$9/D12) -> 0.17957857 | E13: =IF(E12=0,0,$F$9/E12) -> 0.3142625 | F13: =IF(F12=0,0,$F$9/F12) -> 0.628525
B14: Container | C14: CONTENER NO : (1) | D14: CONTENER NO : (3) | E14: CONTENER NO : (4) | F14: CONTENER NO : (5)
B15: Container cost | C15: =IFERROR(INDEX(LIST!$G$2:$G$131,MATCH(C14,LIST!$B$2:$B$131,0)),0) -> 0.025 | D15: =IFERROR(INDEX(LIST!$G$2:$G$131,MATCH(D14,LIST!$B$2:$B$131,0)),0) -> 0.021 | E15: =IFERROR(INDEX(LIST!$G$2:$G$131,MATCH(E14,LIST!$B$2:$B$131,0)),0) -> 0.0315 | F15: =IFERROR(INDEX(LIST!$G$2:$G$131,MATCH(F14,LIST!$B$2:$B$131,0)),0) -> 0.11666667
B16: Spoons (qty) | C16: 1 | D16: 2 | E16: 3 | F16: 4
B17: Spoon cost | C17: =C16*IFERROR(INDEX(LIST!$G$2:$G$131,MATCH("SPOON",LIST!$B$2:$B$131,0)),0) -> 0.0064 | D17: =D16*IFERROR(INDEX(LIST!$G$2:$G$131,MATCH("SPOON",LIST!$B$2:$B$131,0)),0) -> 0.0128 | E17: =E16*IFERROR(INDEX(LIST!$G$2:$G$131,MATCH("SPOON",LIST!$B$2:$B$131,0)),0) -> 0.0192 | F17: =F16*IFERROR(INDEX(LIST!$G$2:$G$131,MATCH("SPOON",LIST!$B$2:$B$131,0)),0) -> 0.0256
B18: Bread (qty) | C18: 0 | D18: 0 | E18: 0 | F18: 0
B19: Bread cost | C19: =C18*IFERROR(INDEX(LIST!$G$2:$G$131,MATCH("Bread",LIST!$B$2:$B$131,0)),0) -> 0 | D19: =D18*IFERROR(INDEX(LIST!$G$2:$G$131,MATCH("Bread",LIST!$B$2:$B$131,0)),0) -> 0 | E19: =E18*IFERROR(INDEX(LIST!$G$2:$G$131,MATCH("Bread",LIST!$B$2:$B$131,0)),0) -> 0 | F19: =F18*IFERROR(INDEX(LIST!$G$2:$G$131,MATCH("Bread",LIST!$B$2:$B$131,0)),0) -> 0
B20: Bag | C20: Bag XS | D20: Bag Small | E20: Bag Medium | F20: Bag Large
B21: Bag cost | C21: =IFERROR(INDEX(LIST!$G$2:$G$131,MATCH(C20,LIST!$B$2:$B$131,0)),0) -> 0.01 | D21: =IFERROR(INDEX(LIST!$G$2:$G$131,MATCH(D20,LIST!$B$2:$B$131,0)),0) -> 0.02 | E21: =IFERROR(INDEX(LIST!$G$2:$G$131,MATCH(E20,LIST!$B$2:$B$131,0)),0) -> 0.03 | F21: =IFERROR(INDEX(LIST!$G$2:$G$131,MATCH(F20,LIST!$B$2:$B$131,0)),0) -> 0.04
B22: Other costs | C22: 0 | D22: 0 | E22: 0 | F22: 0
B23: Packaging total | C23: =C15+C17+C19+C21+C22 -> 0.0414 | D23: =D15+D17+D19+D21+D22 -> 0.0538 | E23: =E15+E17+E19+E21+E22 -> 0.0807 | F23: =F15+F17+F19+F21+F22 -> 0.18226667
B24: TOTAL COST | C24: =C13+C23 -> 0.167105 | D24: =D13+D23 -> 0.23337857 | E24: =E13+E23 -> 0.3949625 | F24: =F13+F23 -> 0.81079167
B25: Store price | C25: 0.6 | D25: 0.9 | E25: 1.6 | F25: 3
B26: Store cost % | C26: =IF(C25=0,"",C24/C25) -> 0.27850833 | D26: =IF(D25=0,"",D24/D25) -> 0.25930952 | E26: =IF(E25=0,"",E24/E25) -> 0.24685156 | F26: =IF(F25=0,"",F24/F25) -> 0.27026389
B27: Delivery price | C27: 0.4 | D27: 1 | E27: 1.5 | F27: 2.5
B28: Delivery cost % | C28: =IF(N(C27)=0,"",C24/C27) -> 0.4177625 | D28: =IF(N(D27)=0,"",D24/D27) -> 0.23337857 | E28: =IF(N(E27)=0,"",E24/E27) -> 0.26330833 | F28: =IF(N(F27)=0,"",F24/F27) -> 0.32431667
B29: Store profit | C29: =C25-C24 -> 0.432895 | D29: =D25-D24 -> 0.66662143 | E29: =E25-E24 -> 1.2050375 | F29: =F25-F24 -> 2.1892083
B30: Delivery profit | C30: =IF(N(C27)=0,"",C27-C24) -> 0.232895 | D30: =IF(N(D27)=0,"",D27-D24) -> 0.76662143 | E30: =IF(N(E27)=0,"",E27-E24) -> 1.1050375 | F30: =IF(N(F27)=0,"",F27-F24) -> 1.6892083
